Workbook

Sheet 00_Übersicht
A1: WÖk Master Items v1.4 FINAL – führende Register- und Governance-Fassung
A2: Stand 16.08.2026 · 621 WÖk-IDs · Begriffsleitfaden v1.5 · SDG+ explizit gekennzeichnet · leere Eingaben bleiben unbewertet · aktive Benchmarks strikt von Legacy-Werten getrennt
A4: Qualitätskennzahlen | F4: Nutzung und Freigabelogik
A6: WÖk-IDs | B6: =COUNTA('01_Item_Register'!A5:A625) -> 621 | C6: Eindeutige Regeln | D6: =COUNTA('03_Scoring_Rules'!A5:A32) -> 28 | F6: 1 | G6: Messwerte werden ausschließlich in 06_Scorecards (Spalte J) eingetragen.
A7: Indikatorfamilien | B7: 204 | C7: Korrigierte #N/A-Zeilen | D7: 320 | F7: 2 | G7: Qualitative oder hybride Regeln benötigen einen nachweisgebundenen Assurance-Score in Spalte K.
A8: Benchmarkabhängig | B8: =COUNTIF('01_Item_Register'!K5:K625,"Benchmarkabhängig") -> 72 | C8: Qualitative Regeln | D8: =COUNTIF('01_Item_Register'!K5:K625,"Qualitativ") -> 54 | F8: 3 | G8: Ein Benchmark wirkt erst, wenn er in 02_Benchmarks vollständig befüllt und auf „Aktiv“ gesetzt ist.
A9: Rechtsgrenzen | B9: =COUNTIF('01_Item_Register'!K5:K625,"Rechts-/Genehmigungsgrenze") -> 10 | C9: Offene −2/−3-Grenzen | D9: =COUNTIF('01_Item_Register'!K5:K625,"Unvollständige Grenzauflösung") -> 10 | F9: 4 | G9: Der FinalScore ist das strengste vorhandene Ergebnis; positive Werte kompensieren keine schlechteren Werte.
F10: 5 | G10: Kritische oder offene Fachlogik ist im Register und Prüfprotokoll gekennzeichnet und nicht automatisch freigegeben.
A12: Schwellenkategorien | F12: Prüfprioritäten
A14: Feste WÖk-Kalibrierung | B14: =COUNTIF('01_Item_Register'!K5:K625,A14) -> 415 | F14: Kritisch | G14: =COUNTIF('01_Item_Register'!AC5:AC625,F14) -> 126
A15: Feste WÖk-Grobkalibrierung | B15: =COUNTIF('01_Item_Register'!K5:K625,A15) -> 48 | F15: Hoch | G15: =COUNTIF('01_Item_Register'!AC5:AC625,F15) -> 168
A16: Benchmarkabhängig | B16: =COUNTIF('01_Item_Register'!K5:K625,A16) -> 72 | F16: Mittel | G16: =COUNTIF('01_Item_Register'!AC5:AC625,F16) -> 327
A17: Qualitativ | B17: =COUNTIF('01_Item_Register'!K5:K625,A17) -> 54
A18: Rechts-/Genehmigungsgrenze | B18: =COUNTIF('01_Item_Register'!K5:K625,A18) -> 10 | F18: Release-Status
A19: Produktspezifische Indexkalibrierung | B19: =COUNTIF('01_Item_Register'!K5:K625,A19) -> 12 | F19: v1.4 FINAL = führende technische Registerfassung
A20: Unvollständige Grenzauflösung | B20: =COUNTIF('01_Item_Register'!K5:K625,A20) -> 10 | F20: Offene Kalibrierungen bleiben ausdrücklich offen
F21: FINAL bedeutet nicht: alle Schwellen extern validiert
A23: Navigation
A25: 01_Item_Register | B25: Vollständiges Register, Quellen-, NACE-, Qualitäts- und Prüfstatus
A26: 02_Benchmarks | B26: Aktive validierte Benchmarks getrennt von Legacy-Werten
A27: 03_Scoring_Rules | B27: 28 normalisierte Regelmuster und offene Kalibrierungen
A28: 04_Tarifmodell | B28: Aktives WÖk-Arbeitsmodell und historische Referenz
A29: 06_Scorecards | B29: Eingabe, automatische Bewertung, FinalScore und Steuersatz
A30: 07_Quellenkatalog | B30: Offizielle und interne Referenzquellen mit Funktion
A31: 08_Prüfprotokoll | B31: Befunde, Korrekturen und verbleibende Fachaufgaben
A32: 09_Methodik_Transparenz | B32: Trennung politischer Richtungsbewertung, Scorecard, Evidenz und Rechenlogik
A33: 10_Public_Export_Schema | B33: Verbindliches Schema für öffentlichen Register-Viewer und Downloads

Sheet 01_Item_Register
A1: 01 · WÖk-ID-Register v1.4 FINAL
A2: 621 eindeutige WÖk-IDs · 162 explizite SDG+-Zuordnungen · Quellenfunktion, Schwellenstatus, NACE-Migration, Systemgrenze, Datenqualität, Assurance und Prüfpriorität
A4: WOK_ID | B4: SDG_or_SDGplus | C4: Target/Unterziel | D4: Indikatorfamilie | E4: Item | F4: Definition/Messgröße | G4: Einheit | H4: Polarity | I4: Rule_ID | J4: Schwellen (WÖk-Klassen) | K4: Schwellenkategorie | L4: Schwellenstatus | M4: Grenzwertbasis | N4: Benchmarkbedarf | O4: Quelle_kurz | P4: Quelle_detail | Q4: Quellenfunktion | R4: Quellenstatus | S4: Source_IDs | T4: NACE_Beispiele_Legacy | U4: NACE_Version | V4: NACE_Rev2.1_Beispiele | W4: NACE_Status | X4: Systemgrenze | Y4: Berechnungslogik | Z4: Datenqualitätsanforderung | AA4: Assurance_Anforderung | AB4: Fachlogik_Status | AC4: Prüfpriorität | AD4: Prüfhinweis | AE4: Version | AF4: Gültig_ab | AG4: Gültig_bis
A5: WOK-S-101 | B5: SDG 1 – Keine Armut | C5: 1.2 | D5: Faire Arbeit & Einkommen | E5: Faire Arbeit & Einkommen – Living Wage | F5: Abdeckung Lebenslohn | G5: % Beschäftigte | H5: higher_is_better | I5: R27 | J5: ≥95:+3; 80–94:+2; 60–79:0; 40–59:‑2; <40:‑3 | K5: Feste WÖk-Kalibrierung | L5: Arbeitskalibrierung – fachlich zu validieren | M5: WÖk-interne Klassenlogik | N5: Optional/Nein | O5: ESRS S1; GRI 401/403/405/406 | P5: ESRS S1, GRI 401/403/405/406, ILO | Q5: Mess-, Berichts- oder Managementrahmen; Schwellen sind grundsätzlich WÖk-Kalibrierungen | R5: Messgrundlage belegt; Schwellenkalibrierung offen | S5: EU-ESRS; GRI; ISO-45001; ILO-LW; ILO-CORE | T5: G47 Handel; K Versicherungen; M72 F&E | U5: Legacy / nicht explizit versioniert | W5: Migration auf NACE Rev. 2.1 erforderlich | X5: Eigene Belegschaft/Organisation; FTE, Beschäftigtengruppe und Zeitraum | Y5: Anteil Beschäftigte ≥ Living Wage (zertifizierte Methodik). | Z5: Primärdaten bevorzugt; Sekundärdaten nur transparent und versioniert; Methode und Systemgrenze dokumentieren | AA5: Limited Assurance; risikobasiert höhere Prüftiefe | AB5: Strukturell nutzbar; Schwellen fachlich zu validieren | AC5: Mittel | AD5: Vollständige fünfstufige numerische Regel. | AE5: v1.4 | AF5: 2026-08-16
A6: WOK-S-102 | B6: SDG 1 – Keine Armut | C6: 1.2 | D6: Faire Arbeit & Einkommen | E6: Faire Arbeit & Einkommen – Tarifbindung | F6: Beschäftigte unter Kollektivvertrag | G6: % | H6: higher_is_better | I6: R26 | J6: ≥90:+3; 70–89:+2; 50–69:0; 30–49:‑2; <30:‑3 | K6: Feste WÖk-Kalibrierung | L6: Arbeitskalibrierung – fachlich zu validieren | M6: WÖk-interne Klassenlogik | N6: Optional/Nein | O6: ESRS S1; GRI 401/403/405/406 | P6: ESRS S1, GRI 401/403/405/406, ILO | Q6: Mess-, Berichts- oder Managementrahmen; Schwellen sind grundsätzlich WÖk-Kalibrierungen | R6: Messgrundlage belegt; Schwellenkalibrierung offen | S6: EU-ESRS; GRI; ISO-45001; ILO-LW; ILO-CORE | T6: G47 Handel; K Versicherungen; M72 F&E | U6: Legacy / nicht explizit versioniert | W6: Migration auf NACE Rev. 2.1 erforderlich | X6: Eigene Belegschaft/Organisation; FTE, Beschäftigtengruppe und Zeitraum | Y6: Quote = Zähler / Nenner gemäß Quelle; in %. | Z6: Primärdaten bevorzugt; Sekundärdaten nur transparent und versioniert; Methode und Systemgrenze dokumentieren | AA6: Limited Assurance; risikobasiert höhere Prüftiefe | AB6: Strukturell nutzbar; Schwellen fachlich zu validieren | AC6: Mittel | AD6: Vollständige fünfstufige numerische Regel. | AE6: v1.4 | AF6: 2026-08-16
A7: WOK-S-103 | B7: SDG 1 – Keine Armut | C7: 1.2 | D7: Faire Arbeit & Einkommen | E7: Faire Arbeit & Einkommen – LTIFR | F7: Arbeitsunfälle pro Mio Stunden | G7: Unfälle/Mio Std. | H7: lower_is_better | I7: R02 | J7: 0:+3; ≤1:+2; ≤3:0; ≤5:‑2; >5:‑3 | K7: Feste WÖk-Kalibrierung | L7: Arbeitskalibrierung – fachlich zu validieren | M7: WÖk-interne Klassenlogik | N7: Optional/Nein | O7: ESRS S1; GRI 401/403/405/406 | P7: ESRS S1, GRI 401/403/405/406, ILO | Q7: Mess-, Berichts- oder Managementrahmen; Schwellen sind grundsätzlich WÖk-Kalibrierungen | R7: Messgrundlage belegt; Schwellenkalibrierung offen | S7: EU-ESRS; GRI; ISO-45001; ILO-LW; ILO-CORE | T7: G47 Handel; K Versicherungen; M72 F&E | U7: Legacy / nicht explizit versioniert | W7: Migration auf NACE Rev. 2.1 erforderlich | X7: Eigene Belegschaft/Organisation; FTE, Beschäftigtengruppe und Zeitraum | Y7: LTIFR = Unfälle mit Ausfallzeit / 1 Mio. Std. (ILO/GRI 403). | Z7: Primärdaten bevorzugt; Sekundärdaten nur transparent und versioniert; Methode und Systemgrenze dokumentieren | AA7: Limited Assurance; risikobasiert höhere Prüftiefe | AB7: Strukturell nutzbar; Schwellen fachlich zu validieren | AC7: Mittel | AD7: Vollständige fünfstufige numerische Regel. | AE7: v1.4 | AF7: 2026-08-16
A8: WOK-S-104 | B8: SDG 1 – Keine Armut | C8: 1.3 | D8: Sozialschutz & Benefits | E8: Sozialschutz & Benefits – Living Wage | F8: Abdeckung Lebenslohn | G8: % Beschäftigte | H8: higher_is_better | I8: R27 | J8: ≥95:+3; 80–94:+2; 60–79:0; 40–59:‑2; <40:‑3 | K8: Feste WÖk-Kalibrierung | L8: Arbeitskalibrierung – fachlich zu validieren | M8: WÖk-interne Klassenlogik | N8: Optional/Nein | O8: ESRS S1; GRI 401/403/405/406 | P8: ESRS S1, GRI 401/403/405/406, ILO | Q8: Mess-, Berichts- oder Managementrahmen; Schwellen sind grundsätzlich WÖk-Kalibrierungen | R8: Messgrundlage belegt; Schwellenkalibrierung offen | S8: EU-ESRS; GRI; ISO-45001; ILO-LW; ILO-CORE | T8: G47 Handel; K Versicherungen; M72 F&E | U8: Legacy / nicht explizit versioniert | W8: Migration auf NACE Rev. 2.1 erforderlich | X8: Eigene Belegschaft/Organisation; FTE, Beschäftigtengruppe und Zeitraum | Y8: Anteil Beschäftigte ≥ Living Wage (zertifizierte Methodik). | Z8: Primärdaten bevorzugt; Sekundärdaten nur transparent und versioniert; Methode und Systemgrenze dokumentieren | AA8: Limited Assurance; risikobasiert höhere Prüftiefe | AB8: Strukturell nutzbar; Schwellen fachlich zu validieren | AC8: Mittel | AD8: Vollständige fünfstufige numerische Regel. | AE8: v1.4 | AF8: 2026-08-16
A9: WOK-S-105 | B9: SDG 1 – Keine Armut | C9: 1.3 | D9: Sozialschutz & Benefits | E9: Sozialschutz & Benefits – Tarifbindung | F9: Beschäftigte unter Kollektivvertrag | G9: % | H9: higher_is_better | I9: R26 | J9: ≥90:+3; 70–89:+2; 50–69:0; 30–49:‑2; <30:‑3 | K9: Feste WÖk-Kalibrierung | L9: Arbeitskalibrierung – fachlich zu validieren | M9: WÖk-interne Klassenlogik | N9: Optional/Nein | O9: ESRS S1; GRI 401/403/405/406 | P9: ESRS S1, GRI 401/403/405/406, ILO | Q9: Mess-, Berichts- oder Managementrahmen; Schwellen sind grundsätzlich WÖk-Kalibrierungen | R9: Messgrundlage belegt; Schwellenkalibrierung offen | S9: EU-ESRS; GRI; ISO-45001; ILO-LW; ILO-CORE | T9: G47 Handel; K Versicherungen; M72 F&E | U9: Legacy / nicht explizit versioniert | W9: Migration auf NACE Rev. 2.1 erforderlich | X9: Eigene Belegschaft/Organisation; FTE, Beschäftigtengruppe und Zeitraum | Y9: Quote = Zähler / Nenner gemäß Quelle; in %. | Z9: Primärdaten bevorzugt; Sekundärdaten nur transparent und versioniert; Methode und Systemgrenze dokumentieren | AA9: Limited Assurance; risikobasiert höhere Prüftiefe | AB9: Strukturell nutzbar; Schwellen fachlich zu validieren | AC9: Mittel | AD9: Vollständige fünfstufige numerische Regel. | AE9: v1.4 | AF9: 2026-08-16
A10: WOK-S-106 | B10: SDG 1 – Keine Armut | C10: 1.3 | D10: Sozialschutz & Benefits | E10: Sozialschutz & Benefits – LTIFR | F10: Arbeitsunfälle pro Mio Stunden | G10: Unfälle/Mio Std. | H10: lower_is_better | I10: R02 | J10: 0:+3; ≤1:+2; ≤3:0; ≤5:‑2; >5:‑3 | K10: Feste WÖk-Kalibrierung | L10: Arbeitskalibrierung – fachlich zu validieren | M10: WÖk-interne Klassenlogik | N10: Optional/Nein | O10: ESRS S1; GRI 401/403/405/406 | P10: ESRS S1, GRI 401/403/405/406, ILO | Q10: Mess-, Berichts- oder Managementrahmen; Schwellen sind grundsätzlich WÖk-Kalibrierungen | R10: Messgrundlage belegt; Schwellenkalibrierung offen | S10: EU-ESRS; GRI; ISO-45001; ILO-LW; ILO-CORE | T10: G47 Handel; K Versicherungen; M72 F&E | U10: Legacy / nicht explizit versioniert | W10: Migration auf NACE Rev. 2.1 erforderlich | X10: Eigene Belegschaft/Organisation; FTE, Beschäftigtengruppe und Zeitraum | Y10: LTIFR = Unfälle mit Ausfallzeit / 1 Mio. Std. (ILO/GRI 403). | Z10: Primärdaten bevorzugt; Sekundärdaten nur transparent und versioniert; Methode und Systemgrenze dokumentieren | AA10: Limited Assurance; risikobasiert höhere Prüftiefe | AB10: Strukturell nutzbar; Schwellen fachlich zu validieren | AC10: Mittel | AD10: Vollständige fünfstufige numerische Regel. | AE10: v1.4 | AF10: 2026-08-16
A11: WOK-SC-101 | B11: SDG 1 – Keine Armut | C11: 1.2 | D11: Living‑Wage in Lieferkette | E11: Living‑Wage in Lieferkette – ESG‑Spend‑Coverage | F11: Anteil verifizierter ESG‑Daten am Spend | G11: % | H11: higher_is_better | I11: R26 | J11: ≥90:+3; 70–89:+2; 50–69:0; 30–49:‑2; <30:‑3 | K11: Feste WÖk-Kalibrierung | L11: Arbeitskalibrierung – fachlich zu validieren | M11: WÖk-interne Klassenlogik | N11: Optional/Nein | O11: ESRS S2; GRI 308/414/408/409 | P11: ESRS S2, GRI 308/414, OECD Due Diligence | Q11: Mess-, Berichts- oder Managementrahmen; Schwellen sind grundsätzlich WÖk-Kalibrierungen | R11: Messgrundlage belegt; Schwellenkalibrierung offen | S11: EU-ESRS; GRI; OECD-DD; ILO-CORE | T11: C20 Chemie; C24 Stahl; C29 Fahrzeuge | U11: Legacy / nicht explizit versioniert | W11: Migration auf NACE Rev. 2.1 erforderlich | X11: Vorgelagerte Lieferkette; relevante Tier-Stufen und Beschaffungsvolumen | Y11: Quote = Zähler / Nenner gemäß Quelle; in %. | Z11: Primärdaten bevorzugt; Sekundärdaten nur transparent und versioniert; Methode und Systemgrenze dokumentieren | AA11: Limited Assurance; risikobasiert höhere Prüftiefe | AB11: Strukturell nutzbar; Schwellen fachlich zu validieren | AC11: Mittel | AD11: Vollständige fünfstufige numerische Regel. | AE11: v1.4 | AF11: 2026-08-16
A12: WOK-SC-102 | B12: SDG 1 – Keine Armut | C12: 1.2 | D12: Living‑Wage in Lieferkette | E12: Living‑Wage in Lieferkette – Kinder/Zwangsarbeit | F12: Audits ohne Verstöße | G12: % Lieferanten | H12: higher_is_better | I12: R28 | J12: ≥98:+3; 90–97:+2; 75–89:0; 50–74:‑2; <50:‑3 | K12: Feste WÖk-Kalibrierung | L12: Arbeitskalibrierung – fachlich zu validieren | M12: WÖk-interne Klassenlogik | N12: Optional/Nein | O12: ESRS S2; GRI 308/414/408/409 | P12: ESRS S2, GRI 308/414, OECD Due Diligence | Q12: Mess-, Berichts- oder Managementrahmen; Schwellen sind grundsätzlich WÖk-Kalibrierungen | R12: Messgrundlage belegt; Schwellenkalibrierung offen | S12: EU-ESRS; GRI; OECD-DD; ILO-CORE | T12: C20 Chemie; C24 Stahl; C29 Fahrzeuge | U12: Legacy / nicht explizit versioniert | W12: Migration auf NACE Rev. 2.1 erforderlich | X12: Vorgelagerte Lieferkette; relevante Tier-Stufen und Beschaffungsvolumen | Y12: Quote = Zähler / Nenner gemäß Quelle; in %. | Z12: Primärdaten bevorzugt; Sekundärdaten nur transparent und versioniert; Methode und Systemgrenze dokumentieren | AA12: Limited Assurance; risikobasiert höhere Prüftiefe | AB12: Strukturell nutzbar; Schwellen fachlich zu validieren | AC12: Mittel | AD12: Vollständige fünfstufige numerische Regel. | AE12: v1.4 | AF12: 2026-08-16
A13: WOK-SC-103 | B13: SDG 1 – Keine Armut | C13: 1.2 | D13: Living‑Wage in Lieferkette | E13: Living‑Wage in Lieferkette – Scope‑3 Daten | F13: Primärdaten‑Abdeckung | G13: % Kategorien | H13: higher_is_better | I13: R23 | J13: ≥80:+3; 60–79:+2; 40–59:0; 20–39:‑2; <20:‑3 | K13: Feste WÖk-Kalibrierung | L13: Arbeitskalibrierung – fachlich zu validieren | M13: WÖk-interne Klassenlogik | N13: Optional/Nein | O13: ESRS E1; GHG Protocol | P13: ESRS E1, GHG Protocol (Corporate/Scope 1–3), ISO 14064/14067 | Q13: Mess-, Berichts- oder Managementrahmen; Schwellen sind grundsätzlich WÖk-Kalibrierungen | R13: Messgrundlage belegt; Schwellenkalibrierung offen | S13: EU-ESRS; GHG-CORP; GHG-S3; GHG-PROD | T13: C20 Chemie; C24 Stahl; C29 Fahrzeuge | U13: Legacy / nicht explizit versioniert | W13: Migration auf NACE Rev. 2.1 erforderlich | X13: Vorgelagerte Lieferkette; relevante Tier-Stufen und Beschaffungsvolumen | Y13: Quote = Zähler / Nenner gemäß Quelle; in %. | Z13: Primärdaten bevorzugt; Sekundärdaten nur transparent und versioniert; Methode und Systemgrenze dokumentieren | AA13: Limited Assurance; risikobasiert höhere Prüftiefe | AB13: Strukturell nutzbar; Schwellen fachlich zu validieren | AC13: Mittel | AD13: Vollständige fünfstufige numerische Regel. | AE13: v1.4 | AF13: 2026-08-16
A14: WOK-G-101 | B14: SDG 1 – Keine Armut | C14: 1.b | D14: Pay Ratio & Fairness | E14: Pay Ratio & Fairness – Antikorruption | F14: Bestätigte Fälle/1.000 FTE | G14: Fälle/1.000 FTE | H14: lower_is_better | I14: R01 | J14: 0:+3; ≤0,2:+2; ≤0,5:0; ≤1:‑2; >1:‑3 | K14: Feste WÖk-Kalibrierung | L14: Arbeitskalibrierung – fachlich zu validieren | M14: WÖk-interne Klassenlogik | N14: Optional/Nein | O14: ESRS G1; GRI 205/207 | P14: ESRS G1, GRI 205/207, OECD Anti‑Bribery | Q14: Mess-, Berichts- oder Managementrahmen; Schwellen sind grundsätzlich WÖk-Kalibrierungen | R14: Messgrundlage belegt; Schwellenkalibrierung offen | S14: EU-ESRS; GRI; OECD-AB | T14: G47 Handel; K Versicherungen; M72 F&E | U14: Legacy / nicht explizit versioniert | W14: Migration auf NACE Rev. 2.1 erforderlich | X14: Organisation/Governance; konsolidierter Kreis und relevante Rechtseinheiten | Y14: Siehe Quelle: Definition gemäß Standard (ESRS/GRI/Taxonomie/ISO). | Z14: Primärdaten bevorzugt; Sekundärdaten nur transparent und versioniert; Methode und Systemgrenze dokumentieren | AA14: Limited Assurance; risikobasiert höhere Prüftiefe | AB14: Strukturell nutzbar; Schwellen fachlich zu validieren | AC14: Mittel | AD14: Vollständige fünfstufige numerische Regel. | AE14: v1.4 | AF14: 2026-08-16
A15: WOK-G-102 | B15: SDG 1 – Keine Armut | C15: 1.b | D15: Pay Ratio & Fairness | E15: Pay Ratio & Fairness – Whistleblowing | F15: Wirksamkeits‑Score | G15: 0–1 | H15: higher_is_better | I15: R16 | J15: ≥0,9:+3; 0,75–0,89:+2; 0,6–0,74:0; 0,4–0,59:‑2; <0,4:‑3 | K15: Feste WÖk-Kalibrierung | L15: Arbeitskalibrierung – fachlich zu validieren | M15: WÖk-interne Klassenlogik | N15: Optional/Nein | O15: ESRS G1; GRI 205/207 | P15: ESRS G1, GRI 205/207, OECD Anti‑Bribery | Q15: Mess-, Berichts- oder Managementrahmen; Schwellen sind grundsätzlich WÖk-Kalibrierungen | R15: Messgrundlage belegt; Schwellenkalibrierung offen | S15: EU-ESRS; GRI; OECD-AB | T15: G47 Handel; K Versicherungen; M72 F&E | U15: Legacy / nicht explizit versioniert | W15: Migration auf NACE Rev. 2.1 erforderlich | X15: Organisation/Governance; konsolidierter Kreis und relevante Rechtseinheiten | Y15: Siehe Quelle: Definition gemäß Standard (ESRS/GRI/Taxonomie/ISO). | Z15: Primärdaten bevorzugt; Sekundärdaten nur transparent und versioniert; Methode und Systemgrenze dokumentieren | AA15: Limited Assurance; risikobasiert höhere Prüftiefe | AB15: Strukturell nutzbar; Schwellen fachlich zu validieren | AC15: Mittel | AD15: Vollständige fünfstufige numerische Regel. | AE15: v1.4 | AF15: 2026-08-16
A16: WOK-G-103 | B16: SDG 1 – Keine Armut | C16: 1.b | D16: Pay Ratio & Fairness | E16: Pay Ratio & Fairness – Steuertransparenz | F16: CbCR‑Offenlegung | G16: 0–1 | H16: higher_is_better | I16: R08 | J16: vollständig:+3; teilweise:+2; minimal:0; schlecht:‑2 | K16: Qualitativ | L16: Assurance und Kriterienkatalog erforderlich | M16: WÖk-interne Kategorien | N16: Optional/Nein | O16: ESRS G1; GRI 205/207 | P16: ESRS G1, GRI 205/207, OECD Anti‑Bribery | Q16: Mess-, Berichts- oder Managementrahmen; Schwellen sind grundsätzlich WÖk-Kalibrierungen | R16: Messgrundlage belegt; Schwellenkalibrierung offen | S16: EU-ESRS; GRI; OECD-AB | T16: G47 Handel; K Versicherungen; M72 F&E | U16: Legacy / nicht explizit versioniert | W16: Migration auf NACE Rev. 2.1 erforderlich | X16: Organisation/Governance; konsolidierter Kreis und relevante Rechtseinheiten | Y16: Siehe Quelle: Definition gemäß Standard (ESRS/GRI/Taxonomie/ISO). | Z16: Dokumentierter Kriterienkatalog; nachvollziehbare Evidenz; DQR A/B bevorzugt | AA16: Unabhängige Fachprüfung/Limited Assurance; bei roten Linien Reasonable Assurance | AB16: Prüfung/Parametrisierung erforderlich | AC16: Hoch | AD16: Die Kategorie −3 fehlt; Vollständigkeit und Wirksamkeit sind feldspezifisch zu definieren. | AE16: v1.4 | AF16: 2026-08-16
... A625: WOK-SYS-220 | B625: SDG+ – Transparenz/Open Data | C625: — | D625: Publikations‑Backlog (OA) | E625: Publikations‑Backlog (OA) – Kooperationen | F625: aktive, evaluierte Partnerschaften/Jahr | G625: #/Jahr | H625: higher_is_better | I625: R20 | J625: ≥5:+3; 3–4:+2; 1–2:0; 0:‑2 | K625: Feste WÖk-Grobkalibrierung | L625: Klasse −3 nur für negative/unzulässige Werte ergänzt | M625: WÖk-interne Grobkalibrierung | N625: Optional/Nein | O625: SROI/SDG17 | P625: SDG 16/17, WJP, V‑Dem | Q625: Methodischer Platzhalter; konkrete Fach- und Primärdatenquelle erforderlich | R625: Platzhalter – fachliche Operationalisierung offen | S625: INT-WOEK-TSROI; SVI-SROI; UN-SDG | T625: G47 Handel; K Versicherungen; M72 F&E | U625: Legacy / nicht explizit versioniert | W625: Migration auf NACE Rev. 2.1 erforderlich | X625: Programm/Portfolio/Systemraum; Empfängergruppe, Region und Zeitraum explizit definieren | Y625: Siehe Quelle: Definition gemäß Standard (ESRS/GRI/Taxonomie/ISO). | Z625: Primärdaten bevorzugt; Sekundärdaten nur transparent und versioniert; Methode und Systemgrenze dokumentieren | AA625: Limited Assurance; risikobasiert höhere Prüftiefe | AB625: Fachlogik nicht abschließend operationalisiert | AC625: Kritisch | AD625: SROI/SDG 17 ist keine hinreichend konkrete Mess- oder Schwellenquelle. Für sachlogisch nichtnegative Zählwerte ist 0 die schlechteste reguläre Klasse (−2). | AE625: v1.4 | AF625: 2026-08-16

Sheet 02_Benchmarks
A1: 02 · Benchmarks und Referenzwerte
A2: Aktive Benchmarks werden nur nach dokumentierter Validierung genutzt. Q:T enthalten ausschließlich Legacy-Rechenwerte aus v1.2 und wirken nicht auf den FinalScore.
A4: WOK_ID | B4: NACE_Legacy | C4: NACE_Version | D4: Region | E4: Tech/Klasse | F4: Einheit | G4: Polarity | H4: Rule_ID | I4: Benchmarkbedarf | J4: Active_BM_Best | K4: Active_BM_Neutral | L4: Active_BM_Warn | M4: Active_BM_Critical | N4: Active_Source_ID | O4: Gültig_ab | P4: Active_Status | Q4: Legacy_BM_Neutral | R4: Legacy_BM_150pct | S4: Legacy_BM_250pct | T4: Legacy_Source | U4: Prüfhinweis
A5: WOK-S-101 | B5: G47 | C5: Legacy / Migration auf NACE Rev. 2.1 offen | D5: EU | F5: % Beschäftigte | G5: higher_is_better | H5: R27 | I5: Optional/Nein | P5: Optional – kein aktiver Benchmark | Q5: 69.5 | R5: 100 | S5: 100 | T5: threshold:0-class | U5: Legacy-Werte bleiben nur als historische Rechenhilfe erhalten und werden nicht für den FinalScore verwendet.
A6: WOK-S-102 | B6: G47 | C6: Legacy / Migration auf NACE Rev. 2.1 offen | D6: EU | F6: % | G6: higher_is_better | H6: R26 | I6: Optional/Nein | P6: Optional – kein aktiver Benchmark | Q6: 59.5 | R6: 89.25 | S6: 100 | T6: threshold:0-class | U6: Legacy-Werte bleiben nur als historische Rechenhilfe erhalten und werden nicht für den FinalScore verwendet.
A7: WOK-S-103 | B7: G47 | C7: Legacy / Migration auf NACE Rev. 2.1 offen | D7: EU | F7: Unfälle/Mio Std. | G7: lower_is_better | H7: R02 | I7: Optional/Nein | P7: Optional – kein aktiver Benchmark | Q7: 3 | R7: 4.5 | S7: 7.5 | T7: threshold:0-class | U7: Legacy-Werte bleiben nur als historische Rechenhilfe erhalten und werden nicht für den FinalScore verwendet.
A8: WOK-S-104 | B8: G47 | C8: Legacy / Migration auf NACE Rev. 2.1 offen | D8: EU | F8: % Beschäftigte | G8: higher_is_better | H8: R27 | I8: Optional/Nein | P8: Optional – kein aktiver Benchmark | Q8: 69.5 | R8: 100 | S8: 100 | T8: threshold:0-class | U8: Legacy-Werte bleiben nur als historische Rechenhilfe erhalten und werden nicht für den FinalScore verwendet.
A9: WOK-S-105 | B9: G47 | C9: Legacy / Migration auf NACE Rev. 2.1 offen | D9: EU | F9: % | G9: higher_is_better | H9: R26 | I9: Optional/Nein | P9: Optional – kein aktiver Benchmark | Q9: 59.5 | R9: 89.25 | S9: 100 | T9: threshold:0-class | U9: Legacy-Werte bleiben nur als historische Rechenhilfe erhalten und werden nicht für den FinalScore verwendet.
A10: WOK-S-106 | B10: G47 | C10: Legacy / Migration auf NACE Rev. 2.1 offen | D10: EU | F10: Unfälle/Mio Std. | G10: lower_is_better | H10: R02 | I10: Optional/Nein | P10: Optional – kein aktiver Benchmark | Q10: 3 | R10: 4.5 | S10: 7.5 | T10: threshold:0-class | U10: Legacy-Werte bleiben nur als historische Rechenhilfe erhalten und werden nicht für den FinalScore verwendet.
A11: WOK-SC-101 | B11: C20 | C11: Legacy / Migration auf NACE Rev. 2.1 offen | D11: EU | F11: % | G11: higher_is_better | H11: R26 | I11: Optional/Nein | P11: Optional – kein aktiver Benchmark | Q11: 59.5 | R11: 89.25 | S11: 100 | T11: threshold:0-class | U11: Legacy-Werte bleiben nur als historische Rechenhilfe erhalten und werden nicht für den FinalScore verwendet.
A12: WOK-SC-102 | B12: C20 | C12: Legacy / Migration auf NACE Rev. 2.1 offen | D12: EU | F12: % Lieferanten | G12: higher_is_better | H12: R28 | I12: Optional/Nein | P12: Optional – kein aktiver Benchmark | Q12: 82 | R12: 100 | S12: 100 | T12: threshold:0-class | U12: Legacy-Werte bleiben nur als historische Rechenhilfe erhalten und werden nicht für den FinalScore verwendet.
A13: WOK-SC-103 | B13: C20 | C13: Legacy / Migration auf NACE Rev. 2.1 offen | D13: EU | F13: % Kategorien | G13: higher_is_better | H13: R23 | I13: Optional/Nein | P13: Optional – kein aktiver Benchmark | Q13: 49.5 | R13: 74.25 | S13: 100 | T13: threshold:0-class | U13: Legacy-Werte bleiben nur als historische Rechenhilfe erhalten und werden nicht für den FinalScore verwendet.
A14: WOK-G-101 | B14: G47 | C14: Legacy / Migration auf NACE Rev. 2.1 offen | D14: EU | F14: Fälle/1.000 FTE | G14: lower_is_better | H14: R01 | I14: Optional/Nein | P14: Optional – kein aktiver Benchmark | Q14: 0.5 | R14: 0.75 | S14: 1.25 | T14: threshold:0-class | U14: Legacy-Werte bleiben nur als historische Rechenhilfe erhalten und werden nicht für den FinalScore verwendet.
A15: WOK-G-102 | B15: G47 | C15: Legacy / Migration auf NACE Rev. 2.1 offen | D15: EU | F15: 0–1 | G15: higher_is_better | H15: R16 | I15: Optional/Nein | P15: Optional – kein aktiver Benchmark | Q15: 0.67 | R15: 1 | S15: 1 | T15: threshold:0-class | U15: Legacy-Werte bleiben nur als historische Rechenhilfe erhalten und werden nicht für den FinalScore verwendet.
A16: WOK-G-103 | B16: G47 | C16: Legacy / Migration auf NACE Rev. 2.1 offen | D16: EU | F16: 0–1 | G16: higher_is_better | H16: R08 | I16: Optional/Nein | P16: Optional – kein aktiver Benchmark | Q16: 0.5 | R16: 0.75 | S16: 0.9 | T16: default:higher_is_better_abs | U16: Legacy-Werte bleiben nur als historische Rechenhilfe erhalten und werden nicht für den FinalScore verwendet.
... A625: WOK-SYS-220 | B625: G47 | C625: Legacy / Migration auf NACE Rev. 2.1 offen | D625: EU | F625: #/Jahr | G625: higher_is_better | H625: R20 | I625: Optional/Nein | P625: Optional – kein aktiver Benchmark | Q625: 1.5 | R625: 2.25 | S625: 3.75 | T625: threshold:0-class | U625: Legacy-Werte bleiben nur als historische Rechenhilfe erhalten und werden nicht für den FinalScore verwendet.

Sheet 03_Scoring_Rules
A1: 03 · Scoring Rules
A2: 28 normalisierte Schwellenmuster. v1.4 ändert keine Schwellen stillschweigend: numerische Regeln bleiben versioniert; qualitative und benchmarkabhängige Regeln verlangen eigene Evidenz.
A4: Rule_ID | B4: Schwelle_original | C4: Regeltyp | D4: Richtung | E4: Eingabemodus | F4: B1 | G4: B2 | H4: B3 | I4: B4 | J4: S1 | K4: S2 | L4: S3 | M4: S4 | N4: S5 | O4: Schwellenkategorie | P4: Status | Q4: Grenzwertbasis | R4: Hinweis | S4: Anzahl_Items
A5: R01 | B5: 0:+3; ≤0,2:+2; ≤0,5:0; ≤1:‑2; >1:‑3 | C5: NUM_LOW | D5: Niedriger ist besser | E5: Numerischer Messwert | F5: 0 | G5: 0.2 | H5: 0.5 | I5: 1 | J5: 3 | K5: 2 | L5: 0 | M5: -2 | N5: -3 | O5: Feste WÖk-Kalibrierung | P5: Arbeitskalibrierung – fachlich zu validieren | Q5: WÖk-interne Klassenlogik | R5: Vollständige fünfstufige numerische Regel. | S5: 46
A6: R02 | B6: 0:+3; ≤1:+2; ≤3:0; ≤5:‑2; >5:‑3 | C6: NUM_LOW | D6: Niedriger ist besser | E6: Numerischer Messwert | F6: 0 | G6: 1 | H6: 3 | I6: 5 | J6: 3 | K6: 2 | L6: 0 | M6: -2 | N6: -3 | O6: Feste WÖk-Kalibrierung | P6: Arbeitskalibrierung – fachlich zu validieren | Q6: WÖk-interne Klassenlogik | R6: Vollständige fünfstufige numerische Regel. | S6: 30
A7: R03 | B7: Net Gain:+3; No Net Loss:0; Net Loss:‑2/‑3 | C7: QUALITATIVE | D7: Qualitative Klassen | E7: Assurance-Score (−3…+3) | O7: Qualitativ | P7: Assurance und Kriterienkatalog erforderlich | Q7: WÖk-Kategorien; fachliche Definition je Wirkungsfeld | R7: Net Gain/No Net Loss/Net Loss ist ohne feldspezifischen Nachweis nicht automatisierbar. | S7: 8
A8: R04 | B8: SBTi 1,5°C:+3; <2°C:+2; Branchenmittel:0; >150%:‑2; >250%:‑3 | C8: MANUAL_HYBRID | D8: Zielpfad/Benchmark | E8: Assurance-Score (−3…+3) | O8: Benchmarkabhängig | P8: SBTi-Validierung und Branchenbenchmark erforderlich | Q8: SBTi-Zielvalidierung plus Branchenbenchmark | R8: Zielstatus und tatsächliche Performance müssen getrennt geprüft werden. | S8: 2
A9: R05 | B9: Top 15%:+3; +15–30%:+2; +31–60%:0; >+60%:‑2/‑3 | C9: BENCHMARK | D9: Benchmarkabhängig | E9: Messwert + aktiver Benchmark | O9: Benchmarkabhängig | P9: Validierter Benchmark fehlt | Q9: Branche/Region/Technologie | R9: Die Grenze >+60 % ist derzeit nicht eindeutig in −2/−3 aufgelöst. | S9: 9
A10: R06 | B10: Top‑10%:+3; Mittel:0; >150%:‑2; >250%:‑3 | C10: BENCHMARK | D10: Benchmarkabhängig | E10: Messwert + aktiver Benchmark | O10: Benchmarkabhängig | P10: Validierter Benchmark fehlt | Q10: Branche/Region/Technologie | R10: Top-10-Prozent, Mittelwert, 150 % und 250 % müssen aus einer dokumentierten Grundgesamtheit stammen. | S10: 49
A11: R07 | B11: Top‑10%:+3; ±Benchmark:0; >150%:‑2; >250%:‑3 | C11: BENCHMARK | D11: Benchmarkabhängig | E11: Messwert + aktiver Benchmark | O11: Benchmarkabhängig | P11: Validierter Benchmark fehlt | Q11: Produktgruppe/Region/Technologie | R11: Produktspezifische Referenzpopulation erforderlich. | S11: 12
A12: R08 | B12: vollständig:+3; teilweise:+2; minimal:0; schlecht:‑2 | C12: QUALITATIVE | D12: Qualitative Klassen | E12: Assurance-Score (−3…+3) | O12: Qualitativ | P12: Assurance und Kriterienkatalog erforderlich | Q12: WÖk-interne Kategorien | R12: Die Kategorie −3 fehlt; Vollständigkeit und Wirksamkeit sind feldspezifisch zu definieren. | S12: 46
A13: R09 | B13: ≤1,2:+3; 1,21–1,4:+2; 1,41–1,6:0; 1,61–1,8:‑2; >1,8:‑3 | C13: NUM_LOW | D13: Niedriger ist besser | E13: Numerischer Messwert | F13: 1.2 | G13: 1.4 | H13: 1.6 | I13: 1.8 | J13: 3 | K13: 2 | L13: 0 | M13: -2 | N13: -3 | O13: Feste WÖk-Kalibrierung | P13: Messstandard belegt; Klassen sind WÖk-Kalibrierung | Q13: PUE-Messung nach ISO/IEC 30134-2; Klassen intern | R13: Klimazone und Rechenzentrumstyp sind bei der Validierung zu berücksichtigen. | S13: 9
A14: R10 | B14: ≤100:+3; 101–250:0; >250:‑2 | C14: NUM_LOW | D14: Niedriger ist besser | E14: Numerischer Messwert | F14: 100 | G14: 250 | H14: 1e+99 | I14: 1e+99 | J14: 3 | K14: 0 | L14: -2 | M14: -2 | N14: -2 | O14: Feste WÖk-Grobkalibrierung | P14: Klassen +2 und −3 fehlen | Q14: WÖk-interne Grobkalibrierung | R14: Automatik bildet nur die explizit vorhandenen Klassen ab. | S14: 8
A15: R11 | B15: ≤2:+3; ≤5:+2; ≤8:0; >8:‑2/‑3 | C15: NUM_LOW | D15: Niedriger ist besser | E15: Numerischer Messwert | F15: 2 | G15: 5 | H15: 8 | I15: 1e+99 | J15: 3 | K15: 2 | L15: 0 | M15: -2 | N15: -2 | O15: Unvollständige Grenzauflösung | P15: Grenze zwischen −2 und −3 offen | Q15: WÖk-Arbeitskalibrierung | R15: Werte >8 werden bis zur Fachentscheidung konservativ mit −2 bewertet; manuelle Verschärfung über Assurance möglich. | S15: 5
A16: R12 | B16: ≤50% Grenzwert:+3; ≤75%:+2; ≤100%:0; 101–120%:‑2; >120%:‑3 | C16: LEGAL_RATIO | D16: Niedriger Anteil am Grenzwert ist besser | E16: Messwert in % des Rechts-/Genehmigungsgrenzwerts | F16: 50 | G16: 75 | H16: 100 | I16: 120 | J16: 3 | K16: 2 | L16: 0 | M16: -2 | N16: -3 | O16: Rechts-/Genehmigungsgrenze | P16: Rechtsfundstelle je Fall erforderlich | Q16: Jeweils anwendbare Rechtsnorm/Genehmigung | R16: Nicht der absolute Messwert, sondern Messwert ÷ Grenzwert × 100 wird bewertet. | S16: 10
A17: R13 | B17: ≤5:+3; 6–10:+2; 11–20:0; 21–30:‑2; >30:‑3 | C17: NUM_LOW | D17: Niedriger ist besser | E17: Numerischer Messwert | F17: 5 | G17: 10 | H17: 20 | I17: 30 | J17: 3 | K17: 2 | L17: 0 | M17: -2 | N17: -3 | O17: Feste WÖk-Kalibrierung | P17: Arbeitskalibrierung – fachlich zu validieren | Q17: WÖk-interne Klassenlogik | R17: Vollständige fünfstufige numerische Regel. | S17: 40
A18: R14 | B18: ≥0,8:+3; 0,6–0,79:+2; 0,4–0,59:0; 0,2–0,39:‑2; <0,2:‑3 | C18: NUM_HIGH | D18: Höher ist besser | E18: Numerischer Messwert | F18: 0.2 | G18: 0.4 | H18: 0.6 | I18: 0.8 | J18: -3 | K18: -2 | L18: 0 | M18: 2 | N18: 3 | O18: Feste WÖk-Kalibrierung | P18: Arbeitskalibrierung – fachlich zu validieren | Q18: WÖk-interne Klassenlogik | R18: Vollständige fünfstufige numerische Regel. | S18: 9
A19: R15 | B19: ≥0,8:+3; 0,7–0,79:+2; 0,6–0,69:0; 0,5–0,59:‑2; <0,5:‑3 | C19: NUM_HIGH | D19: Höher ist besser | E19: Numerischer Messwert | F19: 0.5 | G19: 0.6 | H19: 0.7 | I19: 0.8 | J19: -3 | K19: -2 | L19: 0 | M19: 2 | N19: 3 | O19: Feste WÖk-Kalibrierung | P19: Arbeitskalibrierung – fachlich zu validieren | Q19: WÖk-interne Klassenlogik | R19: Vollständige fünfstufige numerische Regel. | S19: 40
A20: R16 | B20: ≥0,9:+3; 0,75–0,89:+2; 0,6–0,74:0; 0,4–0,59:‑2; <0,4:‑3 | C20: NUM_HIGH | D20: Höher ist besser | E20: Numerischer Messwert | F20: 0.4 | G20: 0.6 | H20: 0.75 | I20: 0.9 | J20: -3 | K20: -2 | L20: 0 | M20: 2 | N20: 3 | O20: Feste WÖk-Kalibrierung | P20: Arbeitskalibrierung – fachlich zu validieren | Q20: WÖk-interne Klassenlogik | R20: Vollständige fünfstufige numerische Regel. | S20: 50
A21: R17 | B21: ≥40:+3; 25–39:+2; 10–24:0; 5–9:‑2; <5:‑3 | C21: NUM_HIGH | D21: Höher ist besser | E21: Numerischer Messwert | F21: 5 | G21: 10 | H21: 25 | I21: 40 | J21: -3 | K21: -2 | L21: 0 | M21: 2 | N21: 3 | O21: Feste WÖk-Kalibrierung | P21: Arbeitskalibrierung – fachlich zu validieren | Q21: WÖk-interne Klassenlogik | R21: Vollständige fünfstufige numerische Regel. | S21: 4
A22: R18 | B22: ≥50:+3; ≥40:+2; ≥30:0; <30:‑2/‑3 | C22: NUM_HIGH | D22: Höher ist besser | E22: Numerischer Messwert | F22: 30 | G22: 40 | H22: 50 | I22: 1e+99 | J22: -2 | K22: 0 | L22: 2 | M22: 3 | N22: 3 | O22: Unvollständige Grenzauflösung | P22: Grenze zwischen −2 und −3 offen | Q22: WÖk-Arbeitskalibrierung | R22: Werte <30 werden bis zur Fachentscheidung mit −2 bewertet; manuelle Verschärfung über Assurance möglich. | S22: 5
A23: R19 | B23: ≥5:+3; 3–4,9:+2; 1–2,9:0; 0,5–0,9:‑2; <0,5:‑3 | C23: NUM_HIGH | D23: Höher ist besser | E23: Numerischer Messwert | F23: 0.5 | G23: 1 | H23: 3 | I23: 5 | J23: -3 | K23: -2 | L23: 0 | M23: 2 | N23: 3 | O23: Feste WÖk-Kalibrierung | P23: Arbeitskalibrierung – fachlich zu validieren | Q23: WÖk-interne Klassenlogik | R23: Vollständige fünfstufige numerische Regel. | S23: 4
A24: R20 | B24: ≥5:+3; 3–4:+2; 1–2:0; 0:‑2 | C24: NUM_HIGH | D24: Höher ist besser | E24: Numerischer Messwert | F24: 0 | G24: 1 | H24: 3 | I24: 5 | J24: -3 | K24: -2 | L24: 0 | M24: 2 | N24: 3 | O24: Feste WÖk-Grobkalibrierung | P24: Klasse −3 nur für negative/unzulässige Werte ergänzt | Q24: WÖk-interne Grobkalibrierung | R24: Für sachlogisch nichtnegative Zählwerte ist 0 die schlechteste reguläre Klasse (−2). | S24: 40
... A32: R28 | B32: ≥98:+3; 90–97:+2; 75–89:0; 50–74:‑2; <50:‑3 | C32: NUM_HIGH | D32: Höher ist besser | E32: Numerischer Wert / Prozentwert gemäß Einheit | F32: 50 | G32: 75 | H32: 90 | I32: 98 | J32: -3 | K32: -2 | L32: 0 | M32: 2 | N32: 3 | O32: Feste WÖk-Kalibrierung | P32: Arbeitskalibrierung – fachlich zu validieren | Q32: WÖk-interne Klassenlogik | R32: Vollständige fünfstufige numerische Regel. | S32: 33

Sheet 04_Tarifmodell
A1: 04 · Tarifmodell
A2: Aktive Fassung: WÖk-Arbeitsmodell v1.3. Keine geltende Rechtsnorm. Historische Modelle werden separat und ohne Rechenwirkung dokumentiert.
A5: FinalScore | B5: Steuerklasse | C5: Steuersatz_pct | D5: Status | E5: Kommentar
A6: -3 | B6: Hoch schädlich | C6: 25 | D6: Aktives WÖk-Arbeitsmodell v1.3 | E6: Höchste Belastung; rote Linien und Prüfpflicht beachten.
A7: -2 | B7: Schädlich | C7: 20 | D7: Aktives WÖk-Arbeitsmodell v1.3 | E7: Deutlich negative Wirkung.
A8: -1 | B8: Schwach | C8: 15 | D8: Aktives WÖk-Arbeitsmodell v1.3 | E8: Negative Wirkung.
A9: 0 | B9: Neutral | C9: 10 | D9: Aktives WÖk-Arbeitsmodell v1.3 | E9: Keine belastbare positive Netto-Wirkung.
A10: 1 | B10: Gut | C10: 5 | D10: Aktives WÖk-Arbeitsmodell v1.3 | E10: Positive Wirkung unterhalb Transformationsniveau.
A11: 2 | B11: Sehr gut | C11: 0 | D11: Aktives WÖk-Arbeitsmodell v1.3 | E11: Starke positive Wirkung.
A12: 3 | B12: Transformativ | C12: 0 | D12: Aktives WÖk-Arbeitsmodell v1.3 | E12: Systemisch transformativ; Nachweis- und Nichtkompensationsprinzip gelten weiter.
A15: Historisches Modell | B15: Bedingung | C15: Satz_pct | D15: Status
A16: Fünfklassenmodell 2025 | B16: Schädlich / mindestens ein Feld negativ | C16: 25 | D16: Historische Referenz – nicht aktiv
A17: Fünfklassenmodell 2025 | B17: Neutral | C17: 19 | D17: Historische Referenz – nicht aktiv
A18: Fünfklassenmodell 2025 | B18: Gut | C18: 12 | D18: Historische Referenz – nicht aktiv
A19: Fünfklassenmodell 2025 | B19: Sehr gut | C19: 5 | D19: Historische Referenz – nicht aktiv
A20: Fünfklassenmodell 2025 | B20: Transformativ | C20: 0 | D20: Historische Referenz – nicht aktiv
A22: Governance-Hinweis: Eine steuerliche Zuordnung darf nur erfolgen, wenn Messwert, Systemgrenze, Quelle, Datenstand und erforderliche Assurance vorliegen. Ein Score von +2 oder +3 hebt negative rote Linien in anderen Wirkungsfeldern nicht auf.

Sheet 05_Changelog
A1: 05 · Changelog v1.2 → v1.4 FINAL
A2: Nachvollziehbare Änderungen an Datenmodell, Scoring, Quellen, Governance, Terminologie und Transparenz.
A4: Change_ID | B4: Bereich | C4: Änderungstyp | D4: Vorher | E4: Nachher | F4: Begründung | G4: Status
A5: CH-001 | B5: Scorecards | C5: Fehlerkorrektur | D5: Leere Messwerte wurden als 0 interpretiert. | E5: Leere Eingaben bleiben unbewertet. | F5: Datenlücken dürfen keinen Score oder Steuersatz erzeugen. | G5: Umgesetzt
A6: CH-002 | B6: Scoring | C6: Fehlerkorrektur | D6: 320 Zeilen verwiesen auf fehlende Archetypen. | E6: Alle 621 Items sind einer von 28 dokumentierten Regeln zugeordnet. | F6: Vermeidung von #N/A und transparente Regelpflege. | G6: Umgesetzt
A7: CH-003 | B7: FinalScore | C7: Fehlerkorrektur | D7: Benchmark wurde bei vorhandenem Archetyp regelmäßig ignoriert. | E7: FinalScore ist das Minimum aller vorhandenen Teilbewertungen. | F7: Konservative Nichtkompensations- und Vorsorgelogik. | G7: Umgesetzt
A8: CH-004 | B8: Benchmarks | C8: Strukturänderung | D8: Generierte Schwellenwerte erschienen als Branchenbenchmarks. | E8: Aktive validierte Benchmarks und Legacy-Rechenwerte sind strikt getrennt. | F8: Keine Scheingenauigkeit oder falsche Quellenbehauptung. | G8: Umgesetzt
A9: CH-005 | B9: Qualitative Regeln | C9: Governance | D9: Qualitative Texte waren nicht operationalisiert. | E9: Assurance-Score und Kriterienkatalog werden explizit verlangt. | F9: Qualitative Wirkung braucht Evidenz und Prüfbarkeit. | G9: Umgesetzt
A10: CH-006 | B10: Rechtsgrenzen | C10: Methodenkorrektur | D10: Einheit und Definition passten nicht zur Prozent-vom-Grenzwert-Regel. | E10: Bewertet wird Messwert ÷ anwendbarer Grenzwert × 100. | F10: Rechts- und Genehmigungsgrenzen müssen fallbezogen parametrisiert werden. | G10: Umgesetzt
A11: CH-007 | B11: NACE | C11: Versionierung | D11: NACE war nicht versioniert. | E11: Legacy-Zuordnung bleibt erhalten; Migration auf NACE Rev. 2.1 wird ausgewiesen. | F11: Klassifikationsänderungen dürfen nicht unsichtbar bleiben. | G11: Umgesetzt
A12: CH-008 | B12: Quellen | C12: Strukturänderung | D12: Messstandards und Schwellenquellen waren vermischt. | E12: Quellenfunktion, Quellenstatus und Source_IDs werden getrennt geführt. | F12: Ein Messstandard belegt nicht automatisch einen Grenzwert. | G12: Umgesetzt
A13: CH-009 | B13: Register | C13: Erweiterung | D13: Systemgrenze, Datenqualität, Assurance und Gültigkeit fehlten. | E13: Pflichtfelder wurden ergänzt. | F13: Auditierbarkeit und spätere Automatisierung. | G13: Umgesetzt
A14: CH-010 | B14: Fachlogik | C14: Qualitätssicherung | D14: Generische Schablonenfehler waren unsichtbar. | E14: Fachlogik_Status, Prüfpriorität und Prüfhinweis kennzeichnen offene Punkte. | F14: Schablonenabweichungen dürfen nicht stillschweigend fortgeschrieben werden. | G14: Umgesetzt
A15: CH-011 | B15: Tarifmodell | C15: Versionierung | D15: Mehrere historische Tarifmodelle standen nebeneinander. | E15: Aktives v1.3-Arbeitsmodell wird klar von historischen Varianten getrennt. | F15: Keine Verwechslung mit geltendem Recht. | G15: Umgesetzt
... A23: CH-019 | B23: Version | C23: Release | D23: v1.3 war geprüfte Arbeits- und Governance-Fassung. | E23: v1.4 FINAL ist die führende technische Registerfassung ab 16.08.2026. | F23: FINAL bezeichnet den führenden Release-Stand, nicht die externe Validierung aller offenen Kalibrierungen. | G23: Umgesetzt

Sheet 06_Scorecards
A1: 06 · Scorecards – Eingabe und Bewertung
A2: Blaue Spalten sind Eingaben. Leere Messwerte erzeugen keinen Score. FinalScore = strengstes vorhandenes Ergebnis aus AutoScore, aktivem BenchmarkScore und Assurance-Score. v1.4: SDG+ explizit gekennzeichnet; Rechenlogik unverändert.
A4: WOK_ID | B4: SDG_or_SDGplus | C4: Target/Unterziel | D4: Indikatorfamilie | E4: Item | F4: Einheit | G4: Polarity | H4: Rule_ID | I4: Regeltyp | J4: Messwert | K4: Assurance_Score | L4: Nachweis/Quelle | M4: Datenstand | N4: AutoScore | O4: BenchmarkScore | P4: FinalScore | Q4: Steuerklasse | R4: Steuersatz_pct | S4: Datenstatus | T4: Prüfhinweis | U4: Schwellen | V4: Quelle_detail | W4: Benchmarkstatus | X4: Quellenstatus | Y4: Prüfpriorität | Z4: Regelstatus | AA4: Systemgrenze | AB4: Datenqualitätsanforderung | AC4: Assurance_Anforderung
A5: WOK-S-101 | B5: SDG 1 – Keine Armut | C5: 1.2 | D5: Faire Arbeit & Einkommen | E5: Faire Arbeit & Einkommen – Living Wage | F5: % Beschäftigte | G5: higher_is_better | H5: R27 | I5: NUM_HIGH | N5: =IF($J5="","",IF($J5<40,-3,IF($J5<60,-2,IF($J5<80,0,IF($J5<95,2,3))))) | O5: =IF($J5="","",IF(OR('02_Benchmarks'!$P5<>"Aktiv",COUNT('02_Benchmarks'!$J5:$M5)<4),"",IF($G5="lower_is_better",IF($J5<='02_Benchmarks'!$J5,3,IF($J5<'02_Benchmarks'!$K5,2,IF($J5<='02_Benchmarks'!$L5,0,IF($J5<='02_Benchmarks'!$M5,-2,-3)))),IF($J5>='02_Benchmarks'!$J5,3,IF($J5>'02_Benchmarks'!$K5,2,IF($J5>='02_Benchmarks'!$L5,0,IF($J5>='02_Benchmarks'!$M5,-2,-3))))))) | P5: =IF(COUNT($N5:$O5)+IF(ISNUMBER($K5),1,0)=0,"",MIN($N5:$O5,$K5)) | Q5: =IF($P5="","",INDEX('04_Tarifmodell'!$B$6:$B$12,$P5+4)) | R5: =IF($P5="","",INDEX('04_Tarifmodell'!$C$6:$C$12,$P5+4)) | S5: =IF(OR($I5="QUALITATIVE",$I5="MANUAL_HYBRID"),IF($K5="","Assurance-Score fehlt","Assurance-bewertet"),IF($I5="BENCHMARK",IF($W5<>"Aktiv",IF($K5="","Benchmark fehlt","Assurance-bewertet"),IF($J5="","Messwert fehlt",IF($P5="","Nicht bewertbar","Berechnet"))),IF(AND($J5="",$K5<>""),"Nur Assurance-Score",IF($J5="","Messwert fehlt",IF($P5="","Nicht bewertbar",IF($P5<=-2,"Kritische Wirkung / Prüfung","Berechnet")))))) -> Messwert fehlt | T5: Vollständige fünfstufige numerische Regel. | U5: ≥95:+3; 80–94:+2; 60–79:0; 40–59:‑2; <40:‑3 | V5: ESRS S1, GRI 401/403/405/406, ILO | W5: ='02_Benchmarks'!$P5 -> Optional – kein aktiver Benchmark | X5: Messgrundlage belegt; Schwellenkalibrierung offen | Y5: Mittel | Z5: Arbeitskalibrierung – fachlich zu validieren | AA5: Eigene Belegschaft/Organisation; FTE, Beschäftigtengruppe und Zeitraum | AB5: Primärdaten bevorzugt; Sekundärdaten nur transparent und versioniert; Methode und Systemgrenze dokumentieren | AC5: Limited Assurance; risikobasiert höhere Prüftiefe
A6: WOK-S-102 | B6: SDG 1 – Keine Armut | C6: 1.2 | D6: Faire Arbeit & Einkommen | E6: Faire Arbeit & Einkommen – Tarifbindung | F6: % | G6: higher_is_better | H6: R26 | I6: NUM_HIGH | N6: =IF($J6="","",IF($J6<30,-3,IF($J6<50,-2,IF($J6<70,0,IF($J6<90,2,3))))) | O6: =IF($J6="","",IF(OR('02_Benchmarks'!$P6<>"Aktiv",COUNT('02_Benchmarks'!$J6:$M6)<4),"",IF($G6="lower_is_better",IF($J6<='02_Benchmarks'!$J6,3,IF($J6<'02_Benchmarks'!$K6,2,IF($J6<='02_Benchmarks'!$L6,0,IF($J6<='02_Benchmarks'!$M6,-2,-3)))),IF($J6>='02_Benchmarks'!$J6,3,IF($J6>'02_Benchmarks'!$K6,2,IF($J6>='02_Benchmarks'!$L6,0,IF($J6>='02_Benchmarks'!$M6,-2,-3))))))) | P6: =IF(COUNT($N6:$O6)+IF(ISNUMBER($K6),1,0)=0,"",MIN($N6:$O6,$K6)) | Q6: =IF($P6="","",INDEX('04_Tarifmodell'!$B$6:$B$12,$P6+4)) | R6: =IF($P6="","",INDEX('04_Tarifmodell'!$C$6:$C$12,$P6+4)) | S6: =IF(OR($I6="QUALITATIVE",$I6="MANUAL_HYBRID"),IF($K6="","Assurance-Score fehlt","Assurance-bewertet"),IF($I6="BENCHMARK",IF($W6<>"Aktiv",IF($K6="","Benchmark fehlt","Assurance-bewertet"),IF($J6="","Messwert fehlt",IF($P6="","Nicht bewertbar","Berechnet"))),IF(AND($J6="",$K6<>""),"Nur Assurance-Score",IF($J6="","Messwert fehlt",IF($P6="","Nicht bewertbar",IF($P6<=-2,"Kritische Wirkung / Prüfung","Berechnet")))))) -> Messwert fehlt | T6: Vollständige fünfstufige numerische Regel. | U6: ≥90:+3; 70–89:+2; 50–69:0; 30–49:‑2; <30:‑3 | V6: ESRS S1, GRI 401/403/405/406, ILO | W6: ='02_Benchmarks'!$P6 -> Optional – kein aktiver Benchmark | X6: Messgrundlage belegt; Schwellenkalibrierung offen | Y6: Mittel | Z6: Arbeitskalibrierung – fachlich zu validieren | AA6: Eigene Belegschaft/Organisation; FTE, Beschäftigtengruppe und Zeitraum | AB6: Primärdaten bevorzugt; Sekundärdaten nur transparent und versioniert; Methode und Systemgrenze dokumentieren | AC6: Limited Assurance; risikobasiert höhere Prüftiefe
A7: WOK-S-103 | B7: SDG 1 – Keine Armut | C7: 1.2 | D7: Faire Arbeit & Einkommen | E7: Faire Arbeit & Einkommen – LTIFR | F7: Unfälle/Mio Std. | G7: lower_is_better | H7: R02 | I7: NUM_LOW | N7: =IF($J7="","",IF($J7<=0,3,IF($J7<=1,2,IF($J7<=3,0,IF($J7<=5,-2,-3))))) | O7: =IF($J7="","",IF(OR('02_Benchmarks'!$P7<>"Aktiv",COUNT('02_Benchmarks'!$J7:$M7)<4),"",IF($G7="lower_is_better",IF($J7<='02_Benchmarks'!$J7,3,IF($J7<'02_Benchmarks'!$K7,2,IF($J7<='02_Benchmarks'!$L7,0,IF($J7<='02_Benchmarks'!$M7,-2,-3)))),IF($J7>='02_Benchmarks'!$J7,3,IF($J7>'02_Benchmarks'!$K7,2,IF($J7>='02_Benchmarks'!$L7,0,IF($J7>='02_Benchmarks'!$M7,-2,-3))))))) | P7: =IF(COUNT($N7:$O7)+IF(ISNUMBER($K7),1,0)=0,"",MIN($N7:$O7,$K7)) | Q7: =IF($P7="","",INDEX('04_Tarifmodell'!$B$6:$B$12,$P7+4)) | R7: =IF($P7="","",INDEX('04_Tarifmodell'!$C$6:$C$12,$P7+4)) | S7: =IF(OR($I7="QUALITATIVE",$I7="MANUAL_HYBRID"),IF($K7="","Assurance-Score fehlt","Assurance-bewertet"),IF($I7="BENCHMARK",IF($W7<>"Aktiv",IF($K7="","Benchmark fehlt","Assurance-bewertet"),IF($J7="","Messwert fehlt",IF($P7="","Nicht bewertbar","Berechnet"))),IF(AND($J7="",$K7<>""),"Nur Assurance-Score",IF($J7="","Messwert fehlt",IF($P7="","Nicht bewertbar",IF($P7<=-2,"Kritische Wirkung / Prüfung","Berechnet")))))) -> Messwert fehlt | T7: Vollständige fünfstufige numerische Regel. | U7: 0:+3; ≤1:+2; ≤3:0; ≤5:‑2; >5:‑3 | V7: ESRS S1, GRI 401/403/405/406, ILO | W7: ='02_Benchmarks'!$P7 -> Optional – kein aktiver Benchmark | X7: Messgrundlage belegt; Schwellenkalibrierung offen | Y7: Mittel | Z7: Arbeitskalibrierung – fachlich zu validieren | AA7: Eigene Belegschaft/Organisation; FTE, Beschäftigtengruppe und Zeitraum | AB7: Primärdaten bevorzugt; Sekundärdaten nur transparent und versioniert; Methode und Systemgrenze dokumentieren | AC7: Limited Assurance; risikobasiert höhere Prüftiefe
A8: WOK-S-104 | B8: SDG 1 – Keine Armut | C8: 1.3 | D8: Sozialschutz & Benefits | E8: Sozialschutz & Benefits – Living Wage | F8: % Beschäftigte | G8: higher_is_better | H8: R27 | I8: NUM_HIGH | N8: =IF($J8="","",IF($J8<40,-3,IF($J8<60,-2,IF($J8<80,0,IF($J8<95,2,3))))) | O8: =IF($J8="","",IF(OR('02_Benchmarks'!$P8<>"Aktiv",COUNT('02_Benchmarks'!$J8:$M8)<4),"",IF($G8="lower_is_better",IF($J8<='02_Benchmarks'!$J8,3,IF($J8<'02_Benchmarks'!$K8,2,IF($J8<='02_Benchmarks'!$L8,0,IF($J8<='02_Benchmarks'!$M8,-2,-3)))),IF($J8>='02_Benchmarks'!$J8,3,IF($J8>'02_Benchmarks'!$K8,2,IF($J8>='02_Benchmarks'!$L8,0,IF($J8>='02_Benchmarks'!$M8,-2,-3))))))) | P8: =IF(COUNT($N8:$O8)+IF(ISNUMBER($K8),1,0)=0,"",MIN($N8:$O8,$K8)) | Q8: =IF($P8="","",INDEX('04_Tarifmodell'!$B$6:$B$12,$P8+4)) | R8: =IF($P8="","",INDEX('04_Tarifmodell'!$C$6:$C$12,$P8+4)) | S8: =IF(OR($I8="QUALITATIVE",$I8="MANUAL_HYBRID"),IF($K8="","Assurance-Score fehlt","Assurance-bewertet"),IF($I8="BENCHMARK",IF($W8<>"Aktiv",IF($K8="","Benchmark fehlt","Assurance-bewertet"),IF($J8="","Messwert fehlt",IF($P8="","Nicht bewertbar","Berechnet"))),IF(AND($J8="",$K8<>""),"Nur Assurance-Score",IF($J8="","Messwert fehlt",IF($P8="","Nicht bewertbar",IF($P8<=-2,"Kritische Wirkung / Prüfung","Berechnet")))))) -> Messwert fehlt | T8: Vollständige fünfstufige numerische Regel. | U8: ≥95:+3; 80–94:+2; 60–79:0; 40–59:‑2; <40:‑3 | V8: ESRS S1, GRI 401/403/405/406, ILO | W8: ='02_Benchmarks'!$P8 -> Optional – kein aktiver Benchmark | X8: Messgrundlage belegt; Schwellenkalibrierung offen | Y8: Mittel | Z8: Arbeitskalibrierung – fachlich zu validieren | AA8: Eigene Belegschaft/Organisation; FTE, Beschäftigtengruppe und Zeitraum | AB8: Primärdaten bevorzugt; Sekundärdaten nur transparent und versioniert; Methode und Systemgrenze dokumentieren | AC8: Limited Assurance; risikobasiert höhere Prüftiefe
A9: WOK-S-105 | B9: SDG 1 – Keine Armut | C9: 1.3 | D9: Sozialschutz & Benefits | E9: Sozialschutz & Benefits – Tarifbindung | F9: % | G9: higher_is_better | H9: R26 | I9: NUM_HIGH | N9: =IF($J9="","",IF($J9<30,-3,IF($J9<50,-2,IF($J9<70,0,IF($J9<90,2,3))))) | O9: =IF($J9="","",IF(OR('02_Benchmarks'!$P9<>"Aktiv",COUNT('02_Benchmarks'!$J9:$M9)<4),"",IF($G9="lower_is_better",IF($J9<='02_Benchmarks'!$J9,3,IF($J9<'02_Benchmarks'!$K9,2,IF($J9<='02_Benchmarks'!$L9,0,IF($J9<='02_Benchmarks'!$M9,-2,-3)))),IF($J9>='02_Benchmarks'!$J9,3,IF($J9>'02_Benchmarks'!$K9,2,IF($J9>='02_Benchmarks'!$L9,0,IF($J9>='02_Benchmarks'!$M9,-2,-3))))))) | P9: =IF(COUNT($N9:$O9)+IF(ISNUMBER($K9),1,0)=0,"",MIN($N9:$O9,$K9)) | Q9: =IF($P9="","",INDEX('04_Tarifmodell'!$B$6:$B$12,$P9+4)) | R9: =IF($P9="","",INDEX('04_Tarifmodell'!$C$6:$C$12,$P9+4)) | S9: =IF(OR($I9="QUALITATIVE",$I9="MANUAL_HYBRID"),IF($K9="","Assurance-Score fehlt","Assurance-bewertet"),IF($I9="BENCHMARK",IF($W9<>"Aktiv",IF($K9="","Benchmark fehlt","Assurance-bewertet"),IF($J9="","Messwert fehlt",IF($P9="","Nicht bewertbar","Berechnet"))),IF(AND($J9="",$K9<>""),"Nur Assurance-Score",IF($J9="","Messwert fehlt",IF($P9="","Nicht bewertbar",IF($P9<=-2,"Kritische Wirkung / Prüfung","Berechnet")))))) -> Messwert fehlt | T9: Vollständige fünfstufige numerische Regel. | U9: ≥90:+3; 70–89:+2; 50–69:0; 30–49:‑2; <30:‑3 | V9: ESRS S1, GRI 401/403/405/406, ILO | W9: ='02_Benchmarks'!$P9 -> Optional – kein aktiver Benchmark | X9: Messgrundlage belegt; Schwellenkalibrierung offen | Y9: Mittel | Z9: Arbeitskalibrierung – fachlich zu validieren | AA9: Eigene Belegschaft/Organisation; FTE, Beschäftigtengruppe und Zeitraum | AB9: Primärdaten bevorzugt; Sekundärdaten nur transparent und versioniert; Methode und Systemgrenze dokumentieren | AC9: Limited Assurance; risikobasiert höhere Prüftiefe
A10: WOK-S-106 | B10: SDG 1 – Keine Armut | C10: 1.3 | D10: Sozialschutz & Benefits | E10: Sozialschutz & Benefits – LTIFR | F10: Unfälle/Mio Std. | G10: lower_is_better | H10: R02 | I10: NUM_LOW | N10: =IF($J10="","",IF($J10<=0,3,IF($J10<=1,2,IF($J10<=3,0,IF($J10<=5,-2,-3))))) | O10: =IF($J10="","",IF(OR('02_Benchmarks'!$P10<>"Aktiv",COUNT('02_Benchmarks'!$J10:$M10)<4),"",IF($G10="lower_is_better",IF($J10<='02_Benchmarks'!$J10,3,IF($J10<'02_Benchmarks'!$K10,2,IF($J10<='02_Benchmarks'!$L10,0,IF($J10<='02_Benchmarks'!$M10,-2,-3)))),IF($J10>='02_Benchmarks'!$J10,3,IF($J10>'02_Benchmarks'!$K10,2,IF($J10>='02_Benchmarks'!$L10,0,IF($J10>='02_Benchmarks'!$M10,-2,-3))))))) | P10: =IF(COUNT($N10:$O10)+IF(ISNUMBER($K10),1,0)=0,"",MIN($N10:$O10,$K10)) | Q10: =IF($P10="","",INDEX('04_Tarifmodell'!$B$6:$B$12,$P10+4)) | R10: =IF($P10="","",INDEX('04_Tarifmodell'!$C$6:$C$12,$P10+4)) | S10: =IF(OR($I10="QUALITATIVE",$I10="MANUAL_HYBRID"),IF($K10="","Assurance-Score fehlt","Assurance-bewertet"),IF($I10="BENCHMARK",IF($W10<>"Aktiv",IF($K10="","Benchmark fehlt","Assurance-bewertet"),IF($J10="","Messwert fehlt",IF($P10="","Nicht bewertbar","Berechnet"))),IF(AND($J10="",$K10<>""),"Nur Assurance-Score",IF($J10="","Messwert fehlt",IF($P10="","Nicht bewertbar",IF($P10<=-2,"Kritische Wirkung / Prüfung","Berechnet")))))) -> Messwert fehlt | T10: Vollständige fünfstufige numerische Regel. | U10: 0:+3; ≤1:+2; ≤3:0; ≤5:‑2; >5:‑3 | V10: ESRS S1, GRI 401/403/405/406, ILO | W10: ='02_Benchmarks'!$P10 -> Optional – kein aktiver Benchmark | X10: Messgrundlage belegt; Schwellenkalibrierung offen | Y10: Mittel | Z10: Arbeitskalibrierung – fachlich zu validieren | AA10: Eigene Belegschaft/Organisation; FTE, Beschäftigtengruppe und Zeitraum | AB10: Primärdaten bevorzugt; Sekundärdaten nur transparent und versioniert; Methode und Systemgrenze dokumentieren | AC10: Limited Assurance; risikobasiert höhere Prüftiefe
A11: WOK-SC-101 | B11: SDG 1 – Keine Armut | C11: 1.2 | D11: Living‑Wage in Lieferkette | E11: Living‑Wage in Lieferkette – ESG‑Spend‑Coverage | F11: % | G11: higher_is_better | H11: R26 | I11: NUM_HIGH | N11: =IF($J11="","",IF($J11<30,-3,IF($J11<50,-2,IF($J11<70,0,IF($J11<90,2,3))))) | O11: =IF($J11="","",IF(OR('02_Benchmarks'!$P11<>"Aktiv",COUNT('02_Benchmarks'!$J11:$M11)<4),"",IF($G11="lower_is_better",IF($J11<='02_Benchmarks'!$J11,3,IF($J11<'02_Benchmarks'!$K11,2,IF($J11<='02_Benchmarks'!$L11,0,IF($J11<='02_Benchmarks'!$M11,-2,-3)))),IF($J11>='02_Benchmarks'!$J11,3,IF($J11>'02_Benchmarks'!$K11,2,IF($J11>='02_Benchmarks'!$L11,0,IF($J11>='02_Benchmarks'!$M11,-2,-3))))))) | P11: =IF(COUNT($N11:$O11)+IF(ISNUMBER($K11),1,0)=0,"",MIN($N11:$O11,$K11)) | Q11: =IF($P11="","",INDEX('04_Tarifmodell'!$B$6:$B$12,$P11+4)) | R11: =IF($P11="","",INDEX('04_Tarifmodell'!$C$6:$C$12,$P11+4)) | S11: =IF(OR($I11="QUALITATIVE",$I11="MANUAL_HYBRID"),IF($K11="","Assurance-Score fehlt","Assurance-bewertet"),IF($I11="BENCHMARK",IF($W11<>"Aktiv",IF($K11="","Benchmark fehlt","Assurance-bewertet"),IF($J11="","Messwert fehlt",IF($P11="","Nicht bewertbar","Berechnet"))),IF(AND($J11="",$K11<>""),"Nur Assurance-Score",IF($J11="","Messwert fehlt",IF($P11="","Nicht bewertbar",IF($P11<=-2,"Kritische Wirkung / Prüfung","Berechnet")))))) -> Messwert fehlt | T11: Vollständige fünfstufige numerische Regel. | U11: ≥90:+3; 70–89:+2; 50–69:0; 30–49:‑2; <30:‑3 | V11: ESRS S2, GRI 308/414, OECD Due Diligence | W11: ='02_Benchmarks'!$P11 -> Optional – kein aktiver Benchmark | X11: Messgrundlage belegt; Schwellenkalibrierung offen | Y11: Mittel | Z11: Arbeitskalibrierung – fachlich zu validieren | AA11: Vorgelagerte Lieferkette; relevante Tier-Stufen und Beschaffungsvolumen | AB11: Primärdaten bevorzugt; Sekundärdaten nur transparent und versioniert; Methode und Systemgrenze dokumentieren | AC11: Limited Assurance; risikobasiert höhere Prüftiefe
A12: WOK-SC-102 | B12: SDG 1 – Keine Armut | C12: 1.2 | D12: Living‑Wage in Lieferkette | E12: Living‑Wage in Lieferkette – Kinder/Zwangsarbeit | F12: % Lieferanten | G12: higher_is_better | H12: R28 | I12: NUM_HIGH | N12: =IF($J12="","",IF($J12<50,-3,IF($J12<75,-2,IF($J12<90,0,IF($J12<98,2,3))))) | O12: =IF($J12="","",IF(OR('02_Benchmarks'!$P12<>"Aktiv",COUNT('02_Benchmarks'!$J12:$M12)<4),"",IF($G12="lower_is_better",IF($J12<='02_Benchmarks'!$J12,3,IF($J12<'02_Benchmarks'!$K12,2,IF($J12<='02_Benchmarks'!$L12,0,IF($J12<='02_Benchmarks'!$M12,-2,-3)))),IF($J12>='02_Benchmarks'!$J12,3,IF($J12>'02_Benchmarks'!$K12,2,IF($J12>='02_Benchmarks'!$L12,0,IF($J12>='02_Benchmarks'!$M12,-2,-3))))))) | P12: =IF(COUNT($N12:$O12)+IF(ISNUMBER($K12),1,0)=0,"",MIN($N12:$O12,$K12)) | Q12: =IF($P12="","",INDEX('04_Tarifmodell'!$B$6:$B$12,$P12+4)) | R12: =IF($P12="","",INDEX('04_Tarifmodell'!$C$6:$C$12,$P12+4)) | S12: =IF(OR($I12="QUALITATIVE",$I12="MANUAL_HYBRID"),IF($K12="","Assurance-Score fehlt","Assurance-bewertet"),IF($I12="BENCHMARK",IF($W12<>"Aktiv",IF($K12="","Benchmark fehlt","Assurance-bewertet"),IF($J12="","Messwert fehlt",IF($P12="","Nicht bewertbar","Berechnet"))),IF(AND($J12="",$K12<>""),"Nur Assurance-Score",IF($J12="","Messwert fehlt",IF($P12="","Nicht bewertbar",IF($P12<=-2,"Kritische Wirkung / Prüfung","Berechnet")))))) -> Messwert fehlt | T12: Vollständige fünfstufige numerische Regel. | U12: ≥98:+3; 90–97:+2; 75–89:0; 50–74:‑2; <50:‑3 | V12: ESRS S2, GRI 308/414, OECD Due Diligence | W12: ='02_Benchmarks'!$P12 -> Optional – kein aktiver Benchmark | X12: Messgrundlage belegt; Schwellenkalibrierung offen | Y12: Mittel | Z12: Arbeitskalibrierung – fachlich zu validieren | AA12: Vorgelagerte Lieferkette; relevante Tier-Stufen und Beschaffungsvolumen | AB12: Primärdaten bevorzugt; Sekundärdaten nur transparent und versioniert; Methode und Systemgrenze dokumentieren | AC12: Limited Assurance; risikobasiert höhere Prüftiefe
A13: WOK-SC-103 | B13: SDG 1 – Keine Armut | C13: 1.2 | D13: Living‑Wage in Lieferkette | E13: Living‑Wage in Lieferkette – Scope‑3 Daten | F13: % Kategorien | G13: higher_is_better | H13: R23 | I13: NUM_HIGH | N13: =IF($J13="","",IF($J13<20,-3,IF($J13<40,-2,IF($J13<60,0,IF($J13<80,2,3))))) | O13: =IF($J13="","",IF(OR('02_Benchmarks'!$P13<>"Aktiv",COUNT('02_Benchmarks'!$J13:$M13)<4),"",IF($G13="lower_is_better",IF($J13<='02_Benchmarks'!$J13,3,IF($J13<'02_Benchmarks'!$K13,2,IF($J13<='02_Benchmarks'!$L13,0,IF($J13<='02_Benchmarks'!$M13,-2,-3)))),IF($J13>='02_Benchmarks'!$J13,3,IF($J13>'02_Benchmarks'!$K13,2,IF($J13>='02_Benchmarks'!$L13,0,IF($J13>='02_Benchmarks'!$M13,-2,-3))))))) | P13: =IF(COUNT($N13:$O13)+IF(ISNUMBER($K13),1,0)=0,"",MIN($N13:$O13,$K13)) | Q13: =IF($P13="","",INDEX('04_Tarifmodell'!$B$6:$B$12,$P13+4)) | R13: =IF($P13="","",INDEX('04_Tarifmodell'!$C$6:$C$12,$P13+4)) | S13: =IF(OR($I13="QUALITATIVE",$I13="MANUAL_HYBRID"),IF($K13="","Assurance-Score fehlt","Assurance-bewertet"),IF($I13="BENCHMARK",IF($W13<>"Aktiv",IF($K13="","Benchmark fehlt","Assurance-bewertet"),IF($J13="","Messwert fehlt",IF($P13="","Nicht bewertbar","Berechnet"))),IF(AND($J13="",$K13<>""),"Nur Assurance-Score",IF($J13="","Messwert fehlt",IF($P13="","Nicht bewertbar",IF($P13<=-2,"Kritische Wirkung / Prüfung","Berechnet")))))) -> Messwert fehlt | T13: Vollständige fünfstufige numerische Regel. | U13: ≥80:+3; 60–79:+2; 40–59:0; 20–39:‑2; <20:‑3 | V13: ESRS E1, GHG Protocol (Corporate/Scope 1–3), ISO 14064/14067 | W13: ='02_Benchmarks'!$P13 -> Optional – kein aktiver Benchmark | X13: Messgrundlage belegt; Schwellenkalibrierung offen | Y13: Mittel | Z13: Arbeitskalibrierung – fachlich zu validieren | AA13: Vorgelagerte Lieferkette; relevante Tier-Stufen und Beschaffungsvolumen | AB13: Primärdaten bevorzugt; Sekundärdaten nur transparent und versioniert; Methode und Systemgrenze dokumentieren | AC13: Limited Assurance; risikobasiert höhere Prüftiefe
A14: WOK-G-101 | B14: SDG 1 – Keine Armut | C14: 1.b | D14: Pay Ratio & Fairness | E14: Pay Ratio & Fairness – Antikorruption | F14: Fälle/1.000 FTE | G14: lower_is_better | H14: R01 | I14: NUM_LOW | N14: =IF($J14="","",IF($J14<=0,3,IF($J14<=0.2,2,IF($J14<=0.5,0,IF($J14<=1,-2,-3))))) | O14: =IF($J14="","",IF(OR('02_Benchmarks'!$P14<>"Aktiv",COUNT('02_Benchmarks'!$J14:$M14)<4),"",IF($G14="lower_is_better",IF($J14<='02_Benchmarks'!$J14,3,IF($J14<'02_Benchmarks'!$K14,2,IF($J14<='02_Benchmarks'!$L14,0,IF($J14<='02_Benchmarks'!$M14,-2,-3)))),IF($J14>='02_Benchmarks'!$J14,3,IF($J14>'02_Benchmarks'!$K14,2,IF($J14>='02_Benchmarks'!$L14,0,IF($J14>='02_Benchmarks'!$M14,-2,-3))))))) | P14: =IF(COUNT($N14:$O14)+IF(ISNUMBER($K14),1,0)=0,"",MIN($N14:$O14,$K14)) | Q14: =IF($P14="","",INDEX('04_Tarifmodell'!$B$6:$B$12,$P14+4)) | R14: =IF($P14="","",INDEX('04_Tarifmodell'!$C$6:$C$12,$P14+4)) | S14: =IF(OR($I14="QUALITATIVE",$I14="MANUAL_HYBRID"),IF($K14="","Assurance-Score fehlt","Assurance-bewertet"),IF($I14="BENCHMARK",IF($W14<>"Aktiv",IF($K14="","Benchmark fehlt","Assurance-bewertet"),IF($J14="","Messwert fehlt",IF($P14="","Nicht bewertbar","Berechnet"))),IF(AND($J14="",$K14<>""),"Nur Assurance-Score",IF($J14="","Messwert fehlt",IF($P14="","Nicht bewertbar",IF($P14<=-2,"Kritische Wirkung / Prüfung","Berechnet")))))) -> Messwert fehlt | T14: Vollständige fünfstufige numerische Regel. | U14: 0:+3; ≤0,2:+2; ≤0,5:0; ≤1:‑2; >1:‑3 | V14: ESRS G1, GRI 205/207, OECD Anti‑Bribery | W14: ='02_Benchmarks'!$P14 -> Optional – kein aktiver Benchmark | X14: Messgrundlage belegt; Schwellenkalibrierung offen | Y14: Mittel | Z14: Arbeitskalibrierung – fachlich zu validieren | AA14: Organisation/Governance; konsolidierter Kreis und relevante Rechtseinheiten | AB14: Primärdaten bevorzugt; Sekundärdaten nur transparent und versioniert; Methode und Systemgrenze dokumentieren | AC14: Limited Assurance; risikobasiert höhere Prüftiefe
A15: WOK-G-102 | B15: SDG 1 – Keine Armut | C15: 1.b | D15: Pay Ratio & Fairness | E15: Pay Ratio & Fairness – Whistleblowing | F15: 0–1 | G15: higher_is_better | H15: R16 | I15: NUM_HIGH | N15: =IF($J15="","",IF($J15<0.4,-3,IF($J15<0.6,-2,IF($J15<0.75,0,IF($J15<0.9,2,3))))) | O15: =IF($J15="","",IF(OR('02_Benchmarks'!$P15<>"Aktiv",COUNT('02_Benchmarks'!$J15:$M15)<4),"",IF($G15="lower_is_better",IF($J15<='02_Benchmarks'!$J15,3,IF($J15<'02_Benchmarks'!$K15,2,IF($J15<='02_Benchmarks'!$L15,0,IF($J15<='02_Benchmarks'!$M15,-2,-3)))),IF($J15>='02_Benchmarks'!$J15,3,IF($J15>'02_Benchmarks'!$K15,2,IF($J15>='02_Benchmarks'!$L15,0,IF($J15>='02_Benchmarks'!$M15,-2,-3))))))) | P15: =IF(COUNT($N15:$O15)+IF(ISNUMBER($K15),1,0)=0,"",MIN($N15:$O15,$K15)) | Q15: =IF($P15="","",INDEX('04_Tarifmodell'!$B$6:$B$12,$P15+4)) | R15: =IF($P15="","",INDEX('04_Tarifmodell'!$C$6:$C$12,$P15+4)) | S15: =IF(OR($I15="QUALITATIVE",$I15="MANUAL_HYBRID"),IF($K15="","Assurance-Score fehlt","Assurance-bewertet"),IF($I15="BENCHMARK",IF($W15<>"Aktiv",IF($K15="","Benchmark fehlt","Assurance-bewertet"),IF($J15="","Messwert fehlt",IF($P15="","Nicht bewertbar","Berechnet"))),IF(AND($J15="",$K15<>""),"Nur Assurance-Score",IF($J15="","Messwert fehlt",IF($P15="","Nicht bewertbar",IF($P15<=-2,"Kritische Wirkung / Prüfung","Berechnet")))))) -> Messwert fehlt | T15: Vollständige fünfstufige numerische Regel. | U15: ≥0,9:+3; 0,75–0,89:+2; 0,6–0,74:0; 0,4–0,59:‑2; <0,4:‑3 | V15: ESRS G1, GRI 205/207, OECD Anti‑Bribery | W15: ='02_Benchmarks'!$P15 -> Optional – kein aktiver Benchmark | X15: Messgrundlage belegt; Schwellenkalibrierung offen | Y15: Mittel | Z15: Arbeitskalibrierung – fachlich zu validieren | AA15: Organisation/Governance; konsolidierter Kreis und relevante Rechtseinheiten | AB15: Primärdaten bevorzugt; Sekundärdaten nur transparent und versioniert; Methode und Systemgrenze dokumentieren | AC15: Limited Assurance; risikobasiert höhere Prüftiefe
A16: WOK-G-103 | B16: SDG 1 – Keine Armut | C16: 1.b | D16: Pay Ratio & Fairness | E16: Pay Ratio & Fairness – Steuertransparenz | F16: 0–1 | G16: higher_is_better | H16: R08 | I16: QUALITATIVE | N16: ="" | O16: =IF($J16="","",IF(OR('02_Benchmarks'!$P16<>"Aktiv",COUNT('02_Benchmarks'!$J16:$M16)<4),"",IF($G16="lower_is_better",IF($J16<='02_Benchmarks'!$J16,3,IF($J16<'02_Benchmarks'!$K16,2,IF($J16<='02_Benchmarks'!$L16,0,IF($J16<='02_Benchmarks'!$M16,-2,-3)))),IF($J16>='02_Benchmarks'!$J16,3,IF($J16>'02_Benchmarks'!$K16,2,IF($J16>='02_Benchmarks'!$L16,0,IF($J16>='02_Benchmarks'!$M16,-2,-3))))))) | P16: =IF(COUNT($N16:$O16)+IF(ISNUMBER($K16),1,0)=0,"",MIN($N16:$O16,$K16)) | Q16: =IF($P16="","",INDEX('04_Tarifmodell'!$B$6:$B$12,$P16+4)) | R16: =IF($P16="","",INDEX('04_Tarifmodell'!$C$6:$C$12,$P16+4)) | S16: =IF(OR($I16="QUALITATIVE",$I16="MANUAL_HYBRID"),IF($K16="","Assurance-Score fehlt","Assurance-bewertet"),IF($I16="BENCHMARK",IF($W16<>"Aktiv",IF($K16="","Benchmark fehlt","Assurance-bewertet"),IF($J16="","Messwert fehlt",IF($P16="","Nicht bewertbar","Berechnet"))),IF(AND($J16="",$K16<>""),"Nur Assurance-Score",IF($J16="","Messwert fehlt",IF($P16="","Nicht bewertbar",IF($P16<=-2,"Kritische Wirkung / Prüfung","Berechnet")))))) -> Assurance-Score fehlt | T16: Die Kategorie −3 fehlt; Vollständigkeit und Wirksamkeit sind feldspezifisch zu definieren. | U16: vollständig:+3; teilweise:+2; minimal:0; schlecht:‑2 | V16: ESRS G1, GRI 205/207, OECD Anti‑Bribery | W16: ='02_Benchmarks'!$P16 -> Optional – kein aktiver Benchmark | X16: Messgrundlage belegt; Schwellenkalibrierung offen | Y16: Hoch | Z16: Assurance und Kriterienkatalog erforderlich | AA16: Organisation/Governance; konsolidierter Kreis und relevante Rechtseinheiten | AB16: Dokumentierter Kriterienkatalog; nachvollziehbare Evidenz; DQR A/B bevorzugt | AC16: Unabhängige Fachprüfung/Limited Assurance; bei roten Linien Reasonable Assurance
A17: WOK-S-107 | B17: SDG 1 – Keine Armut | C17: 1.b | D17: Lokale Beschaffung benachteiligte Gruppen | E17: Lokale Beschaffung benachteiligte Gruppen – ESG‑Spend‑Coverage | F17: % | G17: higher_is_better | H17: R26 | I17: NUM_HIGH | N17: =IF($J17="","",IF($J17<30,-3,IF($J17<50,-2,IF($J17<70,0,IF($J17<90,2,3))))) | O17: =IF($J17="","",IF(OR('02_Benchmarks'!$P17<>"Aktiv",COUNT('02_Benchmarks'!$J17:$M17)<4),"",IF($G17="lower_is_better",IF($J17<='02_Benchmarks'!$J17,3,IF($J17<'02_Benchmarks'!$K17,2,IF($J17<='02_Benchmarks'!$L17,0,IF($J17<='02_Benchmarks'!$M17,-2,-3)))),IF($J17>='02_Benchmarks'!$J17,3,IF($J17>'02_Benchmarks'!$K17,2,IF($J17>='02_Benchmarks'!$L17,0,IF($J17>='02_Benchmarks'!$M17,-2,-3))))))) | P17: =IF(COUNT($N17:$O17)+IF(ISNUMBER($K17),1,0)=0,"",MIN($N17:$O17,$K17)) | Q17: =IF($P17="","",INDEX('04_Tarifmodell'!$B$6:$B$12,$P17+4)) | R17: =IF($P17="","",INDEX('04_Tarifmodell'!$C$6:$C$12,$P17+4)) | S17: =IF(OR($I17="QUALITATIVE",$I17="MANUAL_HYBRID"),IF($K17="","Assurance-Score fehlt","Assurance-bewertet"),IF($I17="BENCHMARK",IF($W17<>"Aktiv",IF($K17="","Benchmark fehlt","Assurance-bewertet"),IF($J17="","Messwert fehlt",IF($P17="","Nicht bewertbar","Berechnet"))),IF(AND($J17="",$K17<>""),"Nur Assurance-Score",IF($J17="","Messwert fehlt",IF($P17="","Nicht bewertbar",IF($P17<=-2,"Kritische Wirkung / Prüfung","Berechnet")))))) -> Messwert fehlt | T17: Vollständige fünfstufige numerische Regel. | U17: ≥90:+3; 70–89:+2; 50–69:0; 30–49:‑2; <30:‑3 | V17: ESRS S2; GRI 308/414/408/409 | W17: ='02_Benchmarks'!$P17 -> Optional – kein aktiver Benchmark | X17: Messgrundlage belegt; Schwellenkalibrierung offen | Y17: Mittel | Z17: Arbeitskalibrierung – fachlich zu validieren | AA17: Eigene Belegschaft/Organisation; FTE, Beschäftigtengruppe und Zeitraum | AB17: Primärdaten bevorzugt; Sekundärdaten nur transparent und versioniert; Methode und Systemgrenze dokumentieren | AC17: Limited Assurance; risikobasiert höhere Prüftiefe
A18: WOK-S-108 | B18: SDG 1 – Keine Armut | C18: 1.b | D18: Lokale Beschaffung benachteiligte Gruppen | E18: Lokale Beschaffung benachteiligte Gruppen – Kinder/Zwangsarbeit | F18: % Lieferanten | G18: higher_is_better | H18: R28 | I18: NUM_HIGH | N18: =IF($J18="","",IF($J18<50,-3,IF($J18<75,-2,IF($J18<90,0,IF($J18<98,2,3))))) | O18: =IF($J18="","",IF(OR('02_Benchmarks'!$P18<>"Aktiv",COUNT('02_Benchmarks'!$J18:$M18)<4),"",IF($G18="lower_is_better",IF($J18<='02_Benchmarks'!$J18,3,IF($J18<'02_Benchmarks'!$K18,2,IF($J18<='02_Benchmarks'!$L18,0,IF($J18<='02_Benchmarks'!$M18,-2,-3)))),IF($J18>='02_Benchmarks'!$J18,3,IF($J18>'02_Benchmarks'!$K18,2,IF($J18>='02_Benchmarks'!$L18,0,IF($J18>='02_Benchmarks'!$M18,-2,-3))))))) | P18: =IF(COUNT($N18:$O18)+IF(ISNUMBER($K18),1,0)=0,"",MIN($N18:$O18,$K18)) | Q18: =IF($P18="","",INDEX('04_Tarifmodell'!$B$6:$B$12,$P18+4)) | R18: =IF($P18="","",INDEX('04_Tarifmodell'!$C$6:$C$12,$P18+4)) | S18: =IF(OR($I18="QUALITATIVE",$I18="MANUAL_HYBRID"),IF($K18="","Assurance-Score fehlt","Assurance-bewertet"),IF($I18="BENCHMARK",IF($W18<>"Aktiv",IF($K18="","Benchmark fehlt","Assurance-bewertet"),IF($J18="","Messwert fehlt",IF($P18="","Nicht bewertbar","Berechnet"))),IF(AND($J18="",$K18<>""),"Nur Assurance-Score",IF($J18="","Messwert fehlt",IF($P18="","Nicht bewertbar",IF($P18<=-2,"Kritische Wirkung / Prüfung","Berechnet")))))) -> Messwert fehlt | T18: Vollständige fünfstufige numerische Regel. | U18: ≥98:+3; 90–97:+2; 75–89:0; 50–74:‑2; <50:‑3 | V18: ESRS S2, GRI 308/414, OECD Due Diligence | W18: ='02_Benchmarks'!$P18 -> Optional – kein aktiver Benchmark | X18: Messgrundlage belegt; Schwellenkalibrierung offen | Y18: Mittel | Z18: Arbeitskalibrierung – fachlich zu validieren | AA18: Eigene Belegschaft/Organisation; FTE, Beschäftigtengruppe und Zeitraum | AB18: Primärdaten bevorzugt; Sekundärdaten nur transparent und versioniert; Methode und Systemgrenze dokumentieren | AC18: Limited Assurance; risikobasiert höhere Prüftiefe
A19: WOK-S-109 | B19: SDG 1 – Keine Armut | C19: 1.b | D19: Lokale Beschaffung benachteiligte Gruppen | E19: Lokale Beschaffung benachteiligte Gruppen – Scope‑3 Daten | F19: % Kategorien | G19: higher_is_better | H19: R23 | I19: NUM_HIGH | N19: =IF($J19="","",IF($J19<20,-3,IF($J19<40,-2,IF($J19<60,0,IF($J19<80,2,3))))) | O19: =IF($J19="","",IF(OR('02_Benchmarks'!$P19<>"Aktiv",COUNT('02_Benchmarks'!$J19:$M19)<4),"",IF($G19="lower_is_better",IF($J19<='02_Benchmarks'!$J19,3,IF($J19<'02_Benchmarks'!$K19,2,IF($J19<='02_Benchmarks'!$L19,0,IF($J19<='02_Benchmarks'!$M19,-2,-3)))),IF($J19>='02_Benchmarks'!$J19,3,IF($J19>'02_Benchmarks'!$K19,2,IF($J19>='02_Benchmarks'!$L19,0,IF($J19>='02_Benchmarks'!$M19,-2,-3))))))) | P19: =IF(COUNT($N19:$O19)+IF(ISNUMBER($K19),1,0)=0,"",MIN($N19:$O19,$K19)) | Q19: =IF($P19="","",INDEX('04_Tarifmodell'!$B$6:$B$12,$P19+4)) | R19: =IF($P19="","",INDEX('04_Tarifmodell'!$C$6:$C$12,$P19+4)) | S19: =IF(OR($I19="QUALITATIVE",$I19="MANUAL_HYBRID"),IF($K19="","Assurance-Score fehlt","Assurance-bewertet"),IF($I19="BENCHMARK",IF($W19<>"Aktiv",IF($K19="","Benchmark fehlt","Assurance-bewertet"),IF($J19="","Messwert fehlt",IF($P19="","Nicht bewertbar","Berechnet"))),IF(AND($J19="",$K19<>""),"Nur Assurance-Score",IF($J19="","Messwert fehlt",IF($P19="","Nicht bewertbar",IF($P19<=-2,"Kritische Wirkung / Prüfung","Berechnet")))))) -> Messwert fehlt | T19: Vollständige fünfstufige numerische Regel. | U19: ≥80:+3; 60–79:+2; 40–59:0; 20–39:‑2; <20:‑3 | V19: ESRS E1, GHG Protocol (Corporate/Scope 1–3), ISO 14064/14067 | W19: ='02_Benchmarks'!$P19 -> Optional – kein aktiver Benchmark | X19: Messgrundlage belegt; Schwellenkalibrierung offen | Y19: Mittel | Z19: Arbeitskalibrierung – fachlich zu validieren | AA19: Eigene Belegschaft/Organisation; FTE, Beschäftigtengruppe und Zeitraum | AB19: Primärdaten bevorzugt; Sekundärdaten nur transparent und versioniert; Methode und Systemgrenze dokumentieren | AC19: Limited Assurance; risikobasiert höhere Prüftiefe
A20: WOK-SYS-101 | B20: SDG 1 – Keine Armut | C20: 1.a | D20: Gemeinwohl‑Investitionen (Armut) | E20: Gemeinwohl‑Investitionen (Armut) – Index | F20: 0–1 | G20: higher_is_better | H20: R15 | I20: NUM_HIGH | N20: =IF($J20="","",IF($J20<0.5,-3,IF($J20<0.6,-2,IF($J20<0.7,0,IF($J20<0.8,2,3))))) | O20: =IF($J20="","",IF(OR('02_Benchmarks'!$P20<>"Aktiv",COUNT('02_Benchmarks'!$J20:$M20)<4),"",IF($G20="lower_is_better",IF($J20<='02_Benchmarks'!$J20,3,IF($J20<'02_Benchmarks'!$K20,2,IF($J20<='02_Benchmarks'!$L20,0,IF($J20<='02_Benchmarks'!$M20,-2,-3)))),IF($J20>='02_Benchmarks'!$J20,3,IF($J20>'02_Benchmarks'!$K20,2,IF($J20>='02_Benchmarks'!$L20,0,IF($J20>='02_Benchmarks'!$M20,-2,-3))))))) | P20: =IF(COUNT($N20:$O20)+IF(ISNUMBER($K20),1,0)=0,"",MIN($N20:$O20,$K20)) | Q20: =IF($P20="","",INDEX('04_Tarifmodell'!$B$6:$B$12,$P20+4)) | R20: =IF($P20="","",INDEX('04_Tarifmodell'!$C$6:$C$12,$P20+4)) | S20: =IF(OR($I20="QUALITATIVE",$I20="MANUAL_HYBRID"),IF($K20="","Assurance-Score fehlt","Assurance-bewertet"),IF($I20="BENCHMARK",IF($W20<>"Aktiv",IF($K20="","Benchmark fehlt","Assurance-bewertet"),IF($J20="","Messwert fehlt",IF($P20="","Nicht bewertbar","Berechnet"))),IF(AND($J20="",$K20<>""),"Nur Assurance-Score",IF($J20="","Messwert fehlt",IF($P20="","Nicht bewertbar",IF($P20<=-2,"Kritische Wirkung / Prüfung","Berechnet")))))) -> Messwert fehlt | T20: SROI/SDG 17 ist keine hinreichend konkrete Mess- oder Schwellenquelle. Vollständige fünfstufige numerische Regel. | U20: ≥0,8:+3; 0,7–0,79:+2; 0,6–0,69:0; 0,5–0,59:‑2; <0,5:‑3 | V20: SDG 16/17, WJP, V‑Dem | W20: ='02_Benchmarks'!$P20 -> Optional – kein aktiver Benchmark | X20: Platzhalter – fachliche Operationalisierung offen | Y20: Kritisch | Z20: Arbeitskalibrierung – fachlich zu validieren | AA20: Programm/Portfolio/Systemraum; Empfängergruppe, Region und Zeitraum explizit definieren | AB20: Primärdaten bevorzugt; Sekundärdaten nur transparent und versioniert; Methode und Systemgrenze dokumentieren | AC20: Limited Assurance; risikobasiert höhere Prüftiefe
A21: WOK-SYS-102 | B21: SDG 1 – Keine Armut | C21: 1.a | D21: Gemeinwohl‑Investitionen (Armut) | E21: Gemeinwohl‑Investitionen (Armut) – Exposure | F21: % | G21: lower_is_better | H21: R13 | I21: NUM_LOW | N21: =IF($J21="","",IF($J21<=5,3,IF($J21<=10,2,IF($J21<=20,0,IF($J21<=30,-2,-3))))) | O21: =IF($J21="","",IF(OR('02_Benchmarks'!$P21<>"Aktiv",COUNT('02_Benchmarks'!$J21:$M21)<4),"",IF($G21="lower_is_better",IF($J21<='02_Benchmarks'!$J21,3,IF($J21<'02_Benchmarks'!$K21,2,IF($J21<='02_Benchmarks'!$L21,0,IF($J21<='02_Benchmarks'!$M21,-2,-3)))),IF($J21>='02_Benchmarks'!$J21,3,IF($J21>'02_Benchmarks'!$K21,2,IF($J21>='02_Benchmarks'!$L21,0,IF($J21>='02_Benchmarks'!$M21,-2,-3))))))) | P21: =IF(COUNT($N21:$O21)+IF(ISNUMBER($K21),1,0)=0,"",MIN($N21:$O21,$K21)) | Q21: =IF($P21="","",INDEX('04_Tarifmodell'!$B$6:$B$12,$P21+4)) | R21: =IF($P21="","",INDEX('04_Tarifmodell'!$C$6:$C$12,$P21+4)) | S21: =IF(OR($I21="QUALITATIVE",$I21="MANUAL_HYBRID"),IF($K21="","Assurance-Score fehlt","Assurance-bewertet"),IF($I21="BENCHMARK",IF($W21<>"Aktiv",IF($K21="","Benchmark fehlt","Assurance-bewertet"),IF($J21="","Messwert fehlt",IF($P21="","Nicht bewertbar","Berechnet"))),IF(AND($J21="",$K21<>""),"Nur Assurance-Score",IF($J21="","Messwert fehlt",IF($P21="","Nicht bewertbar",IF($P21<=-2,"Kritische Wirkung / Prüfung","Berechnet")))))) -> Messwert fehlt | T21: SROI/SDG 17 ist keine hinreichend konkrete Mess- oder Schwellenquelle. Vollständige fünfstufige numerische Regel. | U21: ≤5:+3; 6–10:+2; 11–20:0; 21–30:‑2; >30:‑3 | V21: SROI/SDG17 | W21: ='02_Benchmarks'!$P21 -> Optional – kein aktiver Benchmark | X21: Platzhalter – fachliche Operationalisierung offen | Y21: Kritisch | Z21: Arbeitskalibrierung – fachlich zu validieren | AA21: Programm/Portfolio/Systemraum; Empfängergruppe, Region und Zeitraum explizit definieren | AB21: Primärdaten bevorzugt; Sekundärdaten nur transparent und versioniert; Methode und Systemgrenze dokumentieren | AC21: Limited Assurance; risikobasiert höhere Prüftiefe
A22: WOK-SYS-103 | B22: SDG 1 – Keine Armut | C22: 1.a | D22: Gemeinwohl‑Investitionen (Armut) | E22: Gemeinwohl‑Investitionen (Armut) – Kooperationen | F22: #/Jahr | G22: higher_is_better | H22: R20 | I22: NUM_HIGH | N22: =IF($J22="","",IF($J22<0,-3,IF($J22<1,-2,IF($J22<3,0,IF($J22<5,2,3))))) | O22: =IF($J22="","",IF(OR('02_Benchmarks'!$P22<>"Aktiv",COUNT('02_Benchmarks'!$J22:$M22)<4),"",IF($G22="lower_is_better",IF($J22<='02_Benchmarks'!$J22,3,IF($J22<'02_Benchmarks'!$K22,2,IF($J22<='02_Benchmarks'!$L22,0,IF($J22<='02_Benchmarks'!$M22,-2,-3)))),IF($J22>='02_Benchmarks'!$J22,3,IF($J22>'02_Benchmarks'!$K22,2,IF($J22>='02_Benchmarks'!$L22,0,IF($J22>='02_Benchmarks'!$M22,-2,-3))))))) | P22: =IF(COUNT($N22:$O22)+IF(ISNUMBER($K22),1,0)=0,"",MIN($N22:$O22,$K22)) | Q22: =IF($P22="","",INDEX('04_Tarifmodell'!$B$6:$B$12,$P22+4)) | R22: =IF($P22="","",INDEX('04_Tarifmodell'!$C$6:$C$12,$P22+4)) | S22: =IF(OR($I22="QUALITATIVE",$I22="MANUAL_HYBRID"),IF($K22="","Assurance-Score fehlt","Assurance-bewertet"),IF($I22="BENCHMARK",IF($W22<>"Aktiv",IF($K22="","Benchmark fehlt","Assurance-bewertet"),IF($J22="","Messwert fehlt",IF($P22="","Nicht bewertbar","Berechnet"))),IF(AND($J22="",$K22<>""),"Nur Assurance-Score",IF($J22="","Messwert fehlt",IF($P22="","Nicht bewertbar",IF($P22<=-2,"Kritische Wirkung / Prüfung","Berechnet")))))) -> Messwert fehlt | T22: SROI/SDG 17 ist keine hinreichend konkrete Mess- oder Schwellenquelle. Für sachlogisch nichtnegative Zählwerte ist 0 die schlechteste reguläre Klasse (−2). | U22: ≥5:+3; 3–4:+2; 1–2:0; 0:‑2 | V22: SDG 16/17, WJP, V‑Dem | W22: ='02_Benchmarks'!$P22 -> Optional – kein aktiver Benchmark | X22: Platzhalter – fachliche Operationalisierung offen | Y22: Kritisch | Z22: Klasse −3 nur für negative/unzulässige Werte ergänzt | AA22: Programm/Portfolio/Systemraum; Empfängergruppe, Region und Zeitraum explizit definieren | AB22: Primärdaten bevorzugt; Sekundärdaten nur transparent und versioniert; Methode und Systemgrenze dokumentieren | AC22: Limited Assurance; risikobasiert höhere Prüftiefe
A23: WOK-S-110 | B23: SDG 1 – Keine Armut | C23: 1.2 | D23: Unterbeschäftigung & Prekarität | E23: Unterbeschäftigung & Prekarität – Living Wage | F23: % Beschäftigte | G23: higher_is_better | H23: R27 | I23: NUM_HIGH | N23: =IF($J23="","",IF($J23<40,-3,IF($J23<60,-2,IF($J23<80,0,IF($J23<95,2,3))))) | O23: =IF($J23="","",IF(OR('02_Benchmarks'!$P23<>"Aktiv",COUNT('02_Benchmarks'!$J23:$M23)<4),"",IF($G23="lower_is_better",IF($J23<='02_Benchmarks'!$J23,3,IF($J23<'02_Benchmarks'!$K23,2,IF($J23<='02_Benchmarks'!$L23,0,IF($J23<='02_Benchmarks'!$M23,-2,-3)))),IF($J23>='02_Benchmarks'!$J23,3,IF($J23>'02_Benchmarks'!$K23,2,IF($J23>='02_Benchmarks'!$L23,0,IF($J23>='02_Benchmarks'!$M23,-2,-3))))))) | P23: =IF(COUNT($N23:$O23)+IF(ISNUMBER($K23),1,0)=0,"",MIN($N23:$O23,$K23)) | Q23: =IF($P23="","",INDEX('04_Tarifmodell'!$B$6:$B$12,$P23+4)) | R23: =IF($P23="","",INDEX('04_Tarifmodell'!$C$6:$C$12,$P23+4)) | S23: =IF(OR($I23="QUALITATIVE",$I23="MANUAL_HYBRID"),IF($K23="","Assurance-Score fehlt","Assurance-bewertet"),IF($I23="BENCHMARK",IF($W23<>"Aktiv",IF($K23="","Benchmark fehlt","Assurance-bewertet"),IF($J23="","Messwert fehlt",IF($P23="","Nicht bewertbar","Berechnet"))),IF(AND($J23="",$K23<>""),"Nur Assurance-Score",IF($J23="","Messwert fehlt",IF($P23="","Nicht bewertbar",IF($P23<=-2,"Kritische Wirkung / Prüfung","Berechnet")))))) -> Messwert fehlt | T23: Vollständige fünfstufige numerische Regel. | U23: ≥95:+3; 80–94:+2; 60–79:0; 40–59:‑2; <40:‑3 | V23: ESRS S1, GRI 401/403/405/406, ILO | W23: ='02_Benchmarks'!$P23 -> Optional – kein aktiver Benchmark | X23: Messgrundlage belegt; Schwellenkalibrierung offen | Y23: Mittel | Z23: Arbeitskalibrierung – fachlich zu validieren | AA23: Eigene Belegschaft/Organisation; FTE, Beschäftigtengruppe und Zeitraum | AB23: Primärdaten bevorzugt; Sekundärdaten nur transparent und versioniert; Methode und Systemgrenze dokumentieren | AC23: Limited Assurance; risikobasiert höhere Prüftiefe
A24: WOK-S-111 | B24: SDG 1 – Keine Armut | C24: 1.2 | D24: Unterbeschäftigung & Prekarität | E24: Unterbeschäftigung & Prekarität – Tarifbindung | F24: % | G24: higher_is_better | H24: R26 | I24: NUM_HIGH | N24: =IF($J24="","",IF($J24<30,-3,IF($J24<50,-2,IF($J24<70,0,IF($J24<90,2,3))))) | O24: =IF($J24="","",IF(OR('02_Benchmarks'!$P24<>"Aktiv",COUNT('02_Benchmarks'!$J24:$M24)<4),"",IF($G24="lower_is_better",IF($J24<='02_Benchmarks'!$J24,3,IF($J24<'02_Benchmarks'!$K24,2,IF($J24<='02_Benchmarks'!$L24,0,IF($J24<='02_Benchmarks'!$M24,-2,-3)))),IF($J24>='02_Benchmarks'!$J24,3,IF($J24>'02_Benchmarks'!$K24,2,IF($J24>='02_Benchmarks'!$L24,0,IF($J24>='02_Benchmarks'!$M24,-2,-3))))))) | P24: =IF(COUNT($N24:$O24)+IF(ISNUMBER($K24),1,0)=0,"",MIN($N24:$O24,$K24)) | Q24: =IF($P24="","",INDEX('04_Tarifmodell'!$B$6:$B$12,$P24+4)) | R24: =IF($P24="","",INDEX('04_Tarifmodell'!$C$6:$C$12,$P24+4)) | S24: =IF(OR($I24="QUALITATIVE",$I24="MANUAL_HYBRID"),IF($K24="","Assurance-Score fehlt","Assurance-bewertet"),IF($I24="BENCHMARK",IF($W24<>"Aktiv",IF($K24="","Benchmark fehlt","Assurance-bewertet"),IF($J24="","Messwert fehlt",IF($P24="","Nicht bewertbar","Berechnet"))),IF(AND($J24="",$K24<>""),"Nur Assurance-Score",IF($J24="","Messwert fehlt",IF($P24="","Nicht bewertbar",IF($P24<=-2,"Kritische Wirkung / Prüfung","Berechnet")))))) -> Messwert fehlt | T24: Vollständige fünfstufige numerische Regel. | U24: ≥90:+3; 70–89:+2; 50–69:0; 30–49:‑2; <30:‑3 | V24: ESRS S1, GRI 401/403/405/406, ILO | W24: ='02_Benchmarks'!$P24 -> Optional – kein aktiver Benchmark | X24: Messgrundlage belegt; Schwellenkalibrierung offen | Y24: Mittel | Z24: Arbeitskalibrierung – fachlich zu validieren | AA24: Eigene Belegschaft/Organisation; FTE, Beschäftigtengruppe und Zeitraum | AB24: Primärdaten bevorzugt; Sekundärdaten nur transparent und versioniert; Methode und Systemgrenze dokumentieren | AC24: Limited Assurance; risikobasiert höhere Prüftiefe
A25: WOK-S-112 | B25: SDG 1 – Keine Armut | C25: 1.2 | D25: Unterbeschäftigung & Prekarität | E25: Unterbeschäftigung & Prekarität – LTIFR | F25: Unfälle/Mio Std. | G25: lower_is_better | H25: R02 | I25: NUM_LOW | N25: =IF($J25="","",IF($J25<=0,3,IF($J25<=1,2,IF($J25<=3,0,IF($J25<=5,-2,-3))))) | O25: =IF($J25="","",IF(OR('02_Benchmarks'!$P25<>"Aktiv",COUNT('02_Benchmarks'!$J25:$M25)<4),"",IF($G25="lower_is_better",IF($J25<='02_Benchmarks'!$J25,3,IF($J25<'02_Benchmarks'!$K25,2,IF($J25<='02_Benchmarks'!$L25,0,IF($J25<='02_Benchmarks'!$M25,-2,-3)))),IF($J25>='02_Benchmarks'!$J25,3,IF($J25>'02_Benchmarks'!$K25,2,IF($J25>='02_Benchmarks'!$L25,0,IF($J25>='02_Benchmarks'!$M25,-2,-3))))))) | P25: =IF(COUNT($N25:$O25)+IF(ISNUMBER($K25),1,0)=0,"",MIN($N25:$O25,$K25)) | Q25: =IF($P25="","",INDEX('04_Tarifmodell'!$B$6:$B$12,$P25+4)) | R25: =IF($P25="","",INDEX('04_Tarifmodell'!$C$6:$C$12,$P25+4)) | S25: =IF(OR($I25="QUALITATIVE",$I25="MANUAL_HYBRID"),IF($K25="","Assurance-Score fehlt","Assurance-bewertet"),IF($I25="BENCHMARK",IF($W25<>"Aktiv",IF($K25="","Benchmark fehlt","Assurance-bewertet"),IF($J25="","Messwert fehlt",IF($P25="","Nicht bewertbar","Berechnet"))),IF(AND($J25="",$K25<>""),"Nur Assurance-Score",IF($J25="","Messwert fehlt",IF($P25="","Nicht bewertbar",IF($P25<=-2,"Kritische Wirkung / Prüfung","Berechnet")))))) -> Messwert fehlt | T25: Vollständige fünfstufige numerische Regel. | U25: 0:+3; ≤1:+2; ≤3:0; ≤5:‑2; >5:‑3 | V25: ESRS S1, GRI 401/403/405/406, ILO | W25: ='02_Benchmarks'!$P25 -> Optional – kein aktiver Benchmark | X25: Messgrundlage belegt; Schwellenkalibrierung offen | Y25: Mittel | Z25: Arbeitskalibrierung – fachlich zu validieren | AA25: Eigene Belegschaft/Organisation; FTE, Beschäftigtengruppe und Zeitraum | AB25: Primärdaten bevorzugt; Sekundärdaten nur transparent und versioniert; Methode und Systemgrenze dokumentieren | AC25: Limited Assurance; risikobasiert höhere Prüftiefe
A26: WOK-G-104 | B26: SDG 1 – Keine Armut | C26: 1.a | D26: Steuertransparenz für Sozialstaat | E26: Steuertransparenz für Sozialstaat – Antikorruption | F26: Fälle/1.000 FTE | G26: lower_is_better | H26: R01 | I26: NUM_LOW | N26: =IF($J26="","",IF($J26<=0,3,IF($J26<=0.2,2,IF($J26<=0.5,0,IF($J26<=1,-2,-3))))) | O26: =IF($J26="","",IF(OR('02_Benchmarks'!$P26<>"Aktiv",COUNT('02_Benchmarks'!$J26:$M26)<4),"",IF($G26="lower_is_better",IF($J26<='02_Benchmarks'!$J26,3,IF($J26<'02_Benchmarks'!$K26,2,IF($J26<='02_Benchmarks'!$L26,0,IF($J26<='02_Benchmarks'!$M26,-2,-3)))),IF($J26>='02_Benchmarks'!$J26,3,IF($J26>'02_Benchmarks'!$K26,2,IF($J26>='02_Benchmarks'!$L26,0,IF($J26>='02_Benchmarks'!$M26,-2,-3))))))) | P26: =IF(COUNT($N26:$O26)+IF(ISNUMBER($K26),1,0)=0,"",MIN($N26:$O26,$K26)) | Q26: =IF($P26="","",INDEX('04_Tarifmodell'!$B$6:$B$12,$P26+4)) | R26: =IF($P26="","",INDEX('04_Tarifmodell'!$C$6:$C$12,$P26+4)) | S26: =IF(OR($I26="QUALITATIVE",$I26="MANUAL_HYBRID"),IF($K26="","Assurance-Score fehlt","Assurance-bewertet"),IF($I26="BENCHMARK",IF($W26<>"Aktiv",IF($K26="","Benchmark fehlt","Assurance-bewertet"),IF($J26="","Messwert fehlt",IF($P26="","Nicht bewertbar","Berechnet"))),IF(AND($J26="",$K26<>""),"Nur Assurance-Score",IF($J26="","Messwert fehlt",IF($P26="","Nicht bewertbar",IF($P26<=-2,"Kritische Wirkung / Prüfung","Berechnet")))))) -> Messwert fehlt | T26: Vollständige fünfstufige numerische Regel. | U26: 0:+3; ≤0,2:+2; ≤0,5:0; ≤1:‑2; >1:‑3 | V26: ESRS G1, GRI 205/207, OECD Anti‑Bribery | W26: ='02_Benchmarks'!$P26 -> Optional – kein aktiver Benchmark | X26: Messgrundlage belegt; Schwellenkalibrierung offen | Y26: Mittel | Z26: Arbeitskalibrierung – fachlich zu validieren | AA26: Organisation/Governance; konsolidierter Kreis und relevante Rechtseinheiten | AB26: Primärdaten bevorzugt; Sekundärdaten nur transparent und versioniert; Methode und Systemgrenze dokumentieren | AC26: Limited Assurance; risikobasiert höhere Prüftiefe
A27: WOK-G-105 | B27: SDG 1 – Keine Armut | C27: 1.a | D27: Steuertransparenz für Sozialstaat | E27: Steuertransparenz für Sozialstaat – Whistleblowing | F27: 0–1 | G27: higher_is_better | H27: R16 | I27: NUM_HIGH | N27: =IF($J27="","",IF($J27<0.4,-3,IF($J27<0.6,-2,IF($J27<0.75,0,IF($J27<0.9,2,3))))) | O27: =IF($J27="","",IF(OR('02_Benchmarks'!$P27<>"Aktiv",COUNT('02_Benchmarks'!$J27:$M27)<4),"",IF($G27="lower_is_better",IF($J27<='02_Benchmarks'!$J27,3,IF($J27<'02_Benchmarks'!$K27,2,IF($J27<='02_Benchmarks'!$L27,0,IF($J27<='02_Benchmarks'!$M27,-2,-3)))),IF($J27>='02_Benchmarks'!$J27,3,IF($J27>'02_Benchmarks'!$K27,2,IF($J27>='02_Benchmarks'!$L27,0,IF($J27>='02_Benchmarks'!$M27,-2,-3))))))) | P27: =IF(COUNT($N27:$O27)+IF(ISNUMBER($K27),1,0)=0,"",MIN($N27:$O27,$K27)) | Q27: =IF($P27="","",INDEX('04_Tarifmodell'!$B$6:$B$12,$P27+4)) | R27: =IF($P27="","",INDEX('04_Tarifmodell'!$C$6:$C$12,$P27+4)) | S27: =IF(OR($I27="QUALITATIVE",$I27="MANUAL_HYBRID"),IF($K27="","Assurance-Score fehlt","Assurance-bewertet"),IF($I27="BENCHMARK",IF($W27<>"Aktiv",IF($K27="","Benchmark fehlt","Assurance-bewertet"),IF($J27="","Messwert fehlt",IF($P27="","Nicht bewertbar","Berechnet"))),IF(AND($J27="",$K27<>""),"Nur Assurance-Score",IF($J27="","Messwert fehlt",IF($P27="","Nicht bewertbar",IF($P27<=-2,"Kritische Wirkung / Prüfung","Berechnet")))))) -> Messwert fehlt | T27: Vollständige fünfstufige numerische Regel. | U27: ≥0,9:+3; 0,75–0,89:+2; 0,6–0,74:0; 0,4–0,59:‑2; <0,4:‑3 | V27: ESRS G1, GRI 205/207, OECD Anti‑Bribery | W27: ='02_Benchmarks'!$P27 -> Optional – kein aktiver Benchmark | X27: Messgrundlage belegt; Schwellenkalibrierung offen | Y27: Mittel | Z27: Arbeitskalibrierung – fachlich zu validieren | AA27: Organisation/Governance; konsolidierter Kreis und relevante Rechtseinheiten | AB27: Primärdaten bevorzugt; Sekundärdaten nur transparent und versioniert; Methode und Systemgrenze dokumentieren | AC27: Limited Assurance; risikobasiert höhere Prüftiefe
A28: WOK-G-106 | B28: SDG 1 – Keine Armut | C28: 1.a | D28: Steuertransparenz für Sozialstaat | E28: Steuertransparenz für Sozialstaat – Steuertransparenz | F28: 0–1 | G28: higher_is_better | H28: R08 | I28: QUALITATIVE | N28: ="" | O28: =IF($J28="","",IF(OR('02_Benchmarks'!$P28<>"Aktiv",COUNT('02_Benchmarks'!$J28:$M28)<4),"",IF($G28="lower_is_better",IF($J28<='02_Benchmarks'!$J28,3,IF($J28<'02_Benchmarks'!$K28,2,IF($J28<='02_Benchmarks'!$L28,0,IF($J28<='02_Benchmarks'!$M28,-2,-3)))),IF($J28>='02_Benchmarks'!$J28,3,IF($J28>'02_Benchmarks'!$K28,2,IF($J28>='02_Benchmarks'!$L28,0,IF($J28>='02_Benchmarks'!$M28,-2,-3))))))) | P28: =IF(COUNT($N28:$O28)+IF(ISNUMBER($K28),1,0)=0,"",MIN($N28:$O28,$K28)) | Q28: =IF($P28="","",INDEX('04_Tarifmodell'!$B$6:$B$12,$P28+4)) | R28: =IF($P28="","",INDEX('04_Tarifmodell'!$C$6:$C$12,$P28+4)) | S28: =IF(OR($I28="QUALITATIVE",$I28="MANUAL_HYBRID"),IF($K28="","Assurance-Score fehlt","Assurance-bewertet"),IF($I28="BENCHMARK",IF($W28<>"Aktiv",IF($K28="","Benchmark fehlt","Assurance-bewertet"),IF($J28="","Messwert fehlt",IF($P28="","Nicht bewertbar","Berechnet"))),IF(AND($J28="",$K28<>""),"Nur Assurance-Score",IF($J28="","Messwert fehlt",IF($P28="","Nicht bewertbar",IF($P28<=-2,"Kritische Wirkung / Prüfung","Berechnet")))))) -> Assurance-Score fehlt | T28: Die Kategorie −3 fehlt; Vollständigkeit und Wirksamkeit sind feldspezifisch zu definieren. | U28: vollständig:+3; teilweise:+2; minimal:0; schlecht:‑2 | V28: ESRS G1, GRI 205/207, OECD Anti‑Bribery | W28: ='02_Benchmarks'!$P28 -> Optional – kein aktiver Benchmark | X28: Messgrundlage belegt; Schwellenkalibrierung offen | Y28: Hoch | Z28: Assurance und Kriterienkatalog erforderlich | AA28: Organisation/Governance; konsolidierter Kreis und relevante Rechtseinheiten | AB28: Dokumentierter Kriterienkatalog; nachvollziehbare Evidenz; DQR A/B bevorzugt | AC28: Unabhängige Fachprüfung/Limited Assurance; bei roten Linien Reasonable Assurance
A29: WOK-S-113 | B29: SDG 1 – Keine Armut | C29: 1.2 | D29: Existenzsichernde Teilzeit/Minijobs | E29: Existenzsichernde Teilzeit/Minijobs – Living Wage | F29: % Beschäftigte | G29: higher_is_better | H29: R27 | I29: NUM_HIGH | N29: =IF($J29="","",IF($J29<40,-3,IF($J29<60,-2,IF($J29<80,0,IF($J29<95,2,3))))) | O29: =IF($J29="","",IF(OR('02_Benchmarks'!$P29<>"Aktiv",COUNT('02_Benchmarks'!$J29:$M29)<4),"",IF($G29="lower_is_better",IF($J29<='02_Benchmarks'!$J29,3,IF($J29<'02_Benchmarks'!$K29,2,IF($J29<='02_Benchmarks'!$L29,0,IF($J29<='02_Benchmarks'!$M29,-2,-3)))),IF($J29>='02_Benchmarks'!$J29,3,IF($J29>'02_Benchmarks'!$K29,2,IF($J29>='02_Benchmarks'!$L29,0,IF($J29>='02_Benchmarks'!$M29,-2,-3))))))) | P29: =IF(COUNT($N29:$O29)+IF(ISNUMBER($K29),1,0)=0,"",MIN($N29:$O29,$K29)) | Q29: =IF($P29="","",INDEX('04_Tarifmodell'!$B$6:$B$12,$P29+4)) | R29: =IF($P29="","",INDEX('04_Tarifmodell'!$C$6:$C$12,$P29+4)) | S29: =IF(OR($I29="QUALITATIVE",$I29="MANUAL_HYBRID"),IF($K29="","Assurance-Score fehlt","Assurance-bewertet"),IF($I29="BENCHMARK",IF($W29<>"Aktiv",IF($K29="","Benchmark fehlt","Assurance-bewertet"),IF($J29="","Messwert fehlt",IF($P29="","Nicht bewertbar","Berechnet"))),IF(AND($J29="",$K29<>""),"Nur Assurance-Score",IF($J29="","Messwert fehlt",IF($P29="","Nicht bewertbar",IF($P29<=-2,"Kritische Wirkung / Prüfung","Berechnet")))))) -> Messwert fehlt | T29: Vollständige fünfstufige numerische Regel. | U29: ≥95:+3; 80–94:+2; 60–79:0; 40–59:‑2; <40:‑3 | V29: ESRS S1, GRI 401/403/405/406, ILO | W29: ='02_Benchmarks'!$P29 -> Optional – kein aktiver Benchmark | X29: Messgrundlage belegt; Schwellenkalibrierung offen | Y29: Mittel | Z29: Arbeitskalibrierung – fachlich zu validieren | AA29: Eigene Belegschaft/Organisation; FTE, Beschäftigtengruppe und Zeitraum | AB29: Primärdaten bevorzugt; Sekundärdaten nur transparent und versioniert; Methode und Systemgrenze dokumentieren | AC29: Limited Assurance; risikobasiert höhere Prüftiefe
A30: WOK-S-114 | B30: SDG 1 – Keine Armut | C30: 1.2 | D30: Existenzsichernde Teilzeit/Minijobs | E30: Existenzsichernde Teilzeit/Minijobs – Tarifbindung | F30: % | G30: higher_is_better | H30: R26 | I30: NUM_HIGH | N30: =IF($J30="","",IF($J30<30,-3,IF($J30<50,-2,IF($J30<70,0,IF($J30<90,2,3))))) | O30: =IF($J30="","",IF(OR('02_Benchmarks'!$P30<>"Aktiv",COUNT('02_Benchmarks'!$J30:$M30)<4),"",IF($G30="lower_is_better",IF($J30<='02_Benchmarks'!$J30,3,IF($J30<'02_Benchmarks'!$K30,2,IF($J30<='02_Benchmarks'!$L30,0,IF($J30<='02_Benchmarks'!$M30,-2,-3)))),IF($J30>='02_Benchmarks'!$J30,3,IF($J30>'02_Benchmarks'!$K30,2,IF($J30>='02_Benchmarks'!$L30,0,IF($J30>='02_Benchmarks'!$M30,-2,-3))))))) | P30: =IF(COUNT($N30:$O30)+IF(ISNUMBER($K30),1,0)=0,"",MIN($N30:$O30,$K30)) | Q30: =IF($P30="","",INDEX('04_Tarifmodell'!$B$6:$B$12,$P30+4)) | R30: =IF($P30="","",INDEX('04_Tarifmodell'!$C$6:$C$12,$P30+4)) | S30: =IF(OR($I30="QUALITATIVE",$I30="MANUAL_HYBRID"),IF($K30="","Assurance-Score fehlt","Assurance-bewertet"),IF($I30="BENCHMARK",IF($W30<>"Aktiv",IF($K30="","Benchmark fehlt","Assurance-bewertet"),IF($J30="","Messwert fehlt",IF($P30="","Nicht bewertbar","Berechnet"))),IF(AND($J30="",$K30<>""),"Nur Assurance-Score",IF($J30="","Messwert fehlt",IF($P30="","Nicht bewertbar",IF($P30<=-2,"Kritische Wirkung / Prüfung","Berechnet")))))) -> Messwert fehlt | T30: Vollständige fünfstufige numerische Regel. | U30: ≥90:+3; 70–89:+2; 50–69:0; 30–49:‑2; <30:‑3 | V30: ESRS S1, GRI 401/403/405/406, ILO | W30: ='02_Benchmarks'!$P30 -> Optional – kein aktiver Benchmark | X30: Messgrundlage belegt; Schwellenkalibrierung offen | Y30: Mittel | Z30: Arbeitskalibrierung – fachlich zu validieren | AA30: Eigene Belegschaft/Organisation; FTE, Beschäftigtengruppe und Zeitraum | AB30: Primärdaten bevorzugt; Sekundärdaten nur transparent und versioniert; Methode und Systemgrenze dokumentieren | AC30: Limited Assurance; risikobasiert höhere Prüftiefe
A31: WOK-S-115 | B31: SDG 1 – Keine Armut | C31: 1.2 | D31: Existenzsichernde Teilzeit/Minijobs | E31: Existenzsichernde Teilzeit/Minijobs – LTIFR | F31: Unfälle/Mio Std. | G31: lower_is_better | H31: R02 | I31: NUM_LOW | N31: =IF($J31="","",IF($J31<=0,3,IF($J31<=1,2,IF($J31<=3,0,IF($J31<=5,-2,-3))))) | O31: =IF($J31="","",IF(OR('02_Benchmarks'!$P31<>"Aktiv",COUNT('02_Benchmarks'!$J31:$M31)<4),"",IF($G31="lower_is_better",IF($J31<='02_Benchmarks'!$J31,3,IF($J31<'02_Benchmarks'!$K31,2,IF($J31<='02_Benchmarks'!$L31,0,IF($J31<='02_Benchmarks'!$M31,-2,-3)))),IF($J31>='02_Benchmarks'!$J31,3,IF($J31>'02_Benchmarks'!$K31,2,IF($J31>='02_Benchmarks'!$L31,0,IF($J31>='02_Benchmarks'!$M31,-2,-3))))))) | P31: =IF(COUNT($N31:$O31)+IF(ISNUMBER($K31),1,0)=0,"",MIN($N31:$O31,$K31)) | Q31: =IF($P31="","",INDEX('04_Tarifmodell'!$B$6:$B$12,$P31+4)) | R31: =IF($P31="","",INDEX('04_Tarifmodell'!$C$6:$C$12,$P31+4)) | S31: =IF(OR($I31="QUALITATIVE",$I31="MANUAL_HYBRID"),IF($K31="","Assurance-Score fehlt","Assurance-bewertet"),IF($I31="BENCHMARK",IF($W31<>"Aktiv",IF($K31="","Benchmark fehlt","Assurance-bewertet"),IF($J31="","Messwert fehlt",IF($P31="","Nicht bewertbar","Berechnet"))),IF(AND($J31="",$K31<>""),"Nur Assurance-Score",IF($J31="","Messwert fehlt",IF($P31="","Nicht bewertbar",IF($P31<=-2,"Kritische Wirkung / Prüfung","Berechnet")))))) -> Messwert fehlt | T31: Vollständige fünfstufige numerische Regel. | U31: 0:+3; ≤1:+2; ≤3:0; ≤5:‑2; >5:‑3 | V31: ESRS S1, GRI 401/403/405/406, ILO | W31: ='02_Benchmarks'!$P31 -> Optional – kein aktiver Benchmark | X31: Messgrundlage belegt; Schwellenkalibrierung offen | Y31: Mittel | Z31: Arbeitskalibrierung – fachlich zu validieren | AA31: Eigene Belegschaft/Organisation; FTE, Beschäftigtengruppe und Zeitraum | AB31: Primärdaten bevorzugt; Sekundärdaten nur transparent und versioniert; Methode und Systemgrenze dokumentieren | AC31: Limited Assurance; risikobasiert höhere Prüftiefe
A32: WOK-E-101 | B32: SDG 2 – Kein Hunger | C32: 2.4 | D32: Nährstoffmanagement (N‑Überschuss) | E32: Nährstoffmanagement (N‑Überschuss) – Entnahme (WSI) | F32: m³*WSI | G32: lower_is_better | H32: R06 | I32: BENCHMARK | N32: ="" | O32: =IF($J32="","",IF(OR('02_Benchmarks'!$P32<>"Aktiv",COUNT('02_Benchmarks'!$J32:$M32)<4),"",IF($G32="lower_is_better",IF($J32<='02_Benchmarks'!$J32,3,IF($J32<'02_Benchmarks'!$K32,2,IF($J32<='02_Benchmarks'!$L32,0,IF($J32<='02_Benchmarks'!$M32,-2,-3)))),IF($J32>='02_Benchmarks'!$J32,3,IF($J32>'02_Benchmarks'!$K32,2,IF($J32>='02_Benchmarks'!$L32,0,IF($J32>='02_Benchmarks'!$M32,-2,-3))))))) | P32: =IF(COUNT($N32:$O32)+IF(ISNUMBER($K32),1,0)=0,"",MIN($N32:$O32,$K32)) | Q32: =IF($P32="","",INDEX('04_Tarifmodell'!$B$6:$B$12,$P32+4)) | R32: =IF($P32="","",INDEX('04_Tarifmodell'!$C$6:$C$12,$P32+4)) | S32: =IF(OR($I32="QUALITATIVE",$I32="MANUAL_HYBRID"),IF($K32="","Assurance-Score fehlt","Assurance-bewertet"),IF($I32="BENCHMARK",IF($W32<>"Aktiv",IF($K32="","Benchmark fehlt","Assurance-bewertet"),IF($J32="","Messwert fehlt",IF($P32="","Nicht bewertbar","Berechnet"))),IF(AND($J32="",$K32<>""),"Nur Assurance-Score",IF($J32="","Messwert fehlt",IF($P32="","Nicht bewertbar",IF($P32<=-2,"Kritische Wirkung / Prüfung","Berechnet")))))) -> Benchmark fehlt | T32: Top-10-Prozent, Mittelwert, 150 % und 250 % müssen aus einer dokumentierten Grundgesamtheit stammen. | U32: Top‑10%:+3; Mittel:0; >150%:‑2; >250%:‑3 | V32: ESRS E3, WRI Aqueduct, ISO 14046 (Water Footprint) | W32: ='02_Benchmarks'!$P32 -> Offen – validierter Benchmark fehlt | X32: Teilbelegt – Benchmarkquelle fehlt | Y32: Hoch | Z32: Validierter Benchmark fehlt | AA32: Standort/Prozess/Aktivität; Bezugsgröße und relevante Umweltmedien | AB32: Primärdaten plus repräsentativer, versionierter Benchmarkdatensatz; Stichprobe und Population offenlegen | AC32: Messwert-Assurance und unabhängige Benchmark-Governance
A33: WOK-E-102 | B33: SDG 2 – Kein Hunger | C33: 2.4 | D33: Nährstoffmanagement (N‑Überschuss) | E33: Nährstoffmanagement (N‑Überschuss) – Reuse | F33: % | G33: higher_is_better | H33: R25 | I33: NUM_HIGH | N33: =IF($J33="","",IF($J33<30,-3,IF($J33<50,-2,IF($J33<70,0,IF($J33<90,2,3))))) | O33: =IF($J33="","",IF(OR('02_Benchmarks'!$P33<>"Aktiv",COUNT('02_Benchmarks'!$J33:$M33)<4),"",IF($G33="lower_is_better",IF($J33<='02_Benchmarks'!$J33,3,IF($J33<'02_Benchmarks'!$K33,2,IF($J33<='02_Benchmarks'!$L33,0,IF($J33<='02_Benchmarks'!$M33,-2,-3)))),IF($J33>='02_Benchmarks'!$J33,3,IF($J33>'02_Benchmarks'!$K33,2,IF($J33>='02_Benchmarks'!$L33,0,IF($J33>='02_Benchmarks'!$M33,-2,-3))))))) | P33: =IF(COUNT($N33:$O33)+IF(ISNUMBER($K33),1,0)=0,"",MIN($N33:$O33,$K33)) | Q33: =IF($P33="","",INDEX('04_Tarifmodell'!$B$6:$B$12,$P33+4)) | R33: =IF($P33="","",INDEX('04_Tarifmodell'!$C$6:$C$12,$P33+4)) | S33: =IF(OR($I33="QUALITATIVE",$I33="MANUAL_HYBRID"),IF($K33="","Assurance-Score fehlt","Assurance-bewertet"),IF($I33="BENCHMARK",IF($W33<>"Aktiv",IF($K33="","Benchmark fehlt","Assurance-bewertet"),IF($J33="","Messwert fehlt",IF($P33="","Nicht bewertbar","Berechnet"))),IF(AND($J33="",$K33<>""),"Nur Assurance-Score",IF($J33="","Messwert fehlt",IF($P33="","Nicht bewertbar",IF($P33<=-2,"Kritische Wirkung / Prüfung","Berechnet")))))) -> Messwert fehlt | T33: Vollständige fünfstufige Prozentregel. | U33: ≥90%:+3; 70–89%:+2; 50–69%:0; 30–49%:‑2; <30%:‑3 | V33: ESRS E3, WRI Aqueduct, ISO 14046 (Water Footprint) | W33: ='02_Benchmarks'!$P33 -> Optional – kein aktiver Benchmark | X33: Messgrundlage belegt; Schwellenkalibrierung offen | Y33: Mittel | Z33: Arbeitskalibrierung – fachlich zu validieren | AA33: Standort/Prozess/Aktivität; Bezugsgröße und relevante Umweltmedien | AB33: Primärdaten bevorzugt; Sekundärdaten nur transparent und versioniert; Methode und Systemgrenze dokumentieren | AC33: Limited Assurance; risikobasiert höhere Prüftiefe
A34: WOK-E-103 | B34: SDG 2 – Kein Hunger | C34: 2.4 | D34: Nährstoffmanagement (N‑Überschuss) | E34: Nährstoffmanagement (N‑Überschuss) – Abwasserqualität | F34: % des Grenzwerts | G34: lower_is_better | H34: R12 | I34: LEGAL_RATIO | N34: =IF($J34="","",IF($J34<=50,3,IF($J34<=75,2,IF($J34<=100,0,IF($J34<=120,-2,-3))))) | O34: =IF($J34="","",IF(OR('02_Benchmarks'!$P34<>"Aktiv",COUNT('02_Benchmarks'!$J34:$M34)<4),"",IF($G34="lower_is_better",IF($J34<='02_Benchmarks'!$J34,3,IF($J34<'02_Benchmarks'!$K34,2,IF($J34<='02_Benchmarks'!$L34,0,IF($J34<='02_Benchmarks'!$M34,-2,-3)))),IF($J34>='02_Benchmarks'!$J34,3,IF($J34>'02_Benchmarks'!$K34,2,IF($J34>='02_Benchmarks'!$L34,0,IF($J34>='02_Benchmarks'!$M34,-2,-3))))))) | P34: =IF(COUNT($N34:$O34)+IF(ISNUMBER($K34),1,0)=0,"",MIN($N34:$O34,$K34)) | Q34: =IF($P34="","",INDEX('04_Tarifmodell'!$B$6:$B$12,$P34+4)) | R34: =IF($P34="","",INDEX('04_Tarifmodell'!$C$6:$C$12,$P34+4)) | S34: =IF(OR($I34="QUALITATIVE",$I34="MANUAL_HYBRID"),IF($K34="","Assurance-Score fehlt","Assurance-bewertet"),IF($I34="BENCHMARK",IF($W34<>"Aktiv",IF($K34="","Benchmark fehlt","Assurance-bewertet"),IF($J34="","Messwert fehlt",IF($P34="","Nicht bewertbar","Berechnet"))),IF(AND($J34="",$K34<>""),"Nur Assurance-Score",IF($J34="","Messwert fehlt",IF($P34="","Nicht bewertbar",IF($P34<=-2,"Kritische Wirkung / Prüfung","Berechnet")))))) -> Messwert fehlt | T34: Nicht der absolute Messwert, sondern Messwert ÷ Grenzwert × 100 wird bewertet. | U34: ≤50% Grenzwert:+3; ≤75%:+2; ≤100%:0; 101–120%:‑2; >120%:‑3 | V34: ESRS E3, WRI Aqueduct, ISO 14046 (Water Footprint) | W34: ='02_Benchmarks'!$P34 -> Optional – kein aktiver Benchmark | X34: Teilbelegt – Rechtsfundstelle je Messung fehlt | Y34: Hoch | Z34: Rechtsfundstelle je Fall erforderlich | AA34: Standort/Prozess/Aktivität; Bezugsgröße und relevante Umweltmedien | AB34: Kalibrierter Messwert; Rechtsfundstelle, Grenzwert, Einheit, Messpunkt und Zeitraum | AC34: Behördlicher/akkreditierter Nachweis oder unabhängige Prüfung
A35: WOK-E-104 | B35: SDG 2 – Kein Hunger | C35: 2.4 | D35: Pestizideinsatz | E35: Pestizideinsatz – Abfallintensität | F35: kg/t | G35: lower_is_better | H35: R06 | I35: BENCHMARK | N35: ="" | O35: =IF($J35="","",IF(OR('02_Benchmarks'!$P35<>"Aktiv",COUNT('02_Benchmarks'!$J35:$M35)<4),"",IF($G35="lower_is_better",IF($J35<='02_Benchmarks'!$J35,3,IF($J35<'02_Benchmarks'!$K35,2,IF($J35<='02_Benchmarks'!$L35,0,IF($J35<='02_Benchmarks'!$M35,-2,-3)))),IF($J35>='02_Benchmarks'!$J35,3,IF($J35>'02_Benchmarks'!$K35,2,IF($J35>='02_Benchmarks'!$L35,0,IF($J35>='02_Benchmarks'!$M35,-2,-3))))))) | P35: =IF(COUNT($N35:$O35)+IF(ISNUMBER($K35),1,0)=0,"",MIN($N35:$O35,$K35)) | Q35: =IF($P35="","",INDEX('04_Tarifmodell'!$B$6:$B$12,$P35+4)) | R35: =IF($P35="","",INDEX('04_Tarifmodell'!$C$6:$C$12,$P35+4)) | S35: =IF(OR($I35="QUALITATIVE",$I35="MANUAL_HYBRID"),IF($K35="","Assurance-Score fehlt","Assurance-bewertet"),IF($I35="BENCHMARK",IF($W35<>"Aktiv",IF($K35="","Benchmark fehlt","Assurance-bewertet"),IF($J35="","Messwert fehlt",IF($P35="","Nicht bewertbar","Berechnet"))),IF(AND($J35="",$K35<>""),"Nur Assurance-Score",IF($J35="","Messwert fehlt",IF($P35="","Nicht bewertbar",IF($P35<=-2,"Kritische Wirkung / Prüfung","Berechnet")))))) -> Benchmark fehlt | T35: Item-Bezeichnung und Messdefinition passen nicht ausreichend zusammen. Top-10-Prozent, Mittelwert, 150 % und 250 % müssen aus einer dokumentierten Grundgesamtheit stammen. | U35: Top‑10%:+3; Mittel:0; >150%:‑2; >250%:‑3 | V35: ESRS E5, GRI 306, WEEE/VerpackG | W35: ='02_Benchmarks'!$P35 -> Offen – validierter Benchmark fehlt | X35: Teilbelegt – Benchmarkquelle fehlt | Y35: Kritisch | Z35: Validierter Benchmark fehlt | AA35: Standort/Prozess/Aktivität; Bezugsgröße und relevante Umweltmedien | AB35: Primärdaten plus repräsentativer, versionierter Benchmarkdatensatz; Stichprobe und Population offenlegen | AC35: Messwert-Assurance und unabhängige Benchmark-Governance
A36: WOK-E-105 | B36: SDG 2 – Kein Hunger | C36: 2.4 | D36: Pestizideinsatz | E36: Pestizideinsatz – Recyclingquote | F36: % | G36: higher_is_better | H36: R25 | I36: NUM_HIGH | N36: =IF($J36="","",IF($J36<30,-3,IF($J36<50,-2,IF($J36<70,0,IF($J36<90,2,3))))) | O36: =IF($J36="","",IF(OR('02_Benchmarks'!$P36<>"Aktiv",COUNT('02_Benchmarks'!$J36:$M36)<4),"",IF($G36="lower_is_better",IF($J36<='02_Benchmarks'!$J36,3,IF($J36<'02_Benchmarks'!$K36,2,IF($J36<='02_Benchmarks'!$L36,0,IF($J36<='02_Benchmarks'!$M36,-2,-3)))),IF($J36>='02_Benchmarks'!$J36,3,IF($J36>'02_Benchmarks'!$K36,2,IF($J36>='02_Benchmarks'!$L36,0,IF($J36>='02_Benchmarks'!$M36,-2,-3))))))) | P36: =IF(COUNT($N36:$O36)+IF(ISNUMBER($K36),1,0)=0,"",MIN($N36:$O36,$K36)) | Q36: =IF($P36="","",INDEX('04_Tarifmodell'!$B$6:$B$12,$P36+4)) | R36: =IF($P36="","",INDEX('04_Tarifmodell'!$C$6:$C$12,$P36+4)) | S36: =IF(OR($I36="QUALITATIVE",$I36="MANUAL_HYBRID"),IF($K36="","Assurance-Score fehlt","Assurance-bewertet"),IF($I36="BENCHMARK",IF($W36<>"Aktiv",IF($K36="","Benchmark fehlt","Assurance-bewertet"),IF($J36="","Messwert fehlt",IF($P36="","Nicht bewertbar","Berechnet"))),IF(AND($J36="",$K36<>""),"Nur Assurance-Score",IF($J36="","Messwert fehlt",IF($P36="","Nicht bewertbar",IF($P36<=-2,"Kritische Wirkung / Prüfung","Berechnet")))))) -> Messwert fehlt | T36: Item-Bezeichnung und Messdefinition passen nicht ausreichend zusammen. Vollständige fünfstufige Prozentregel. | U36: ≥90%:+3; 70–89%:+2; 50–69%:0; 30–49%:‑2; <30%:‑3 | V36: ESRS E5, GRI 306, WEEE/VerpackG | W36: ='02_Benchmarks'!$P36 -> Optional – kein aktiver Benchmark | X36: Messgrundlage belegt; Schwellenkalibrierung offen | Y36: Kritisch | Z36: Arbeitskalibrierung – fachlich zu validieren | AA36: Standort/Prozess/Aktivität; Bezugsgröße und relevante Umweltmedien | AB36: Primärdaten bevorzugt; Sekundärdaten nur transparent und versioniert; Methode und Systemgrenze dokumentieren | AC36: Limited Assurance; risikobasiert höhere Prüftiefe
A37: WOK-E-106 | B37: SDG 2 – Kein Hunger | C37: 2.4 | D37: Pestizideinsatz | E37: Pestizideinsatz – Gefährlicher Abfall | F37: kg/t | G37: lower_is_better | H37: R06 | I37: BENCHMARK | N37: ="" | O37: =IF($J37="","",IF(OR('02_Benchmarks'!$P37<>"Aktiv",COUNT('02_Benchmarks'!$J37:$M37)<4),"",IF($G37="lower_is_better",IF($J37<='02_Benchmarks'!$J37,3,IF($J37<'02_Benchmarks'!$K37,2,IF($J37<='02_Benchmarks'!$L37,0,IF($J37<='02_Benchmarks'!$M37,-2,-3)))),IF($J37>='02_Benchmarks'!$J37,3,IF($J37>'02_Benchmarks'!$K37,2,IF($J37>='02_Benchmarks'!$L37,0,IF($J37>='02_Benchmarks'!$M37,-2,-3))))))) | P37: =IF(COUNT($N37:$O37)+IF(ISNUMBER($K37),1,0)=0,"",MIN($N37:$O37,$K37)) | Q37: =IF($P37="","",INDEX('04_Tarifmodell'!$B$6:$B$12,$P37+4)) | R37: =IF($P37="","",INDEX('04_Tarifmodell'!$C$6:$C$12,$P37+4)) | S37: =IF(OR($I37="QUALITATIVE",$I37="MANUAL_HYBRID"),IF($K37="","Assurance-Score fehlt","Assurance-bewertet"),IF($I37="BENCHMARK",IF($W37<>"Aktiv",IF($K37="","Benchmark fehlt","Assurance-bewertet"),IF($J37="","Messwert fehlt",IF($P37="","Nicht bewertbar","Berechnet"))),IF(AND($J37="",$K37<>""),"Nur Assurance-Score",IF($J37="","Messwert fehlt",IF($P37="","Nicht bewertbar",IF($P37<=-2,"Kritische Wirkung / Prüfung","Berechnet")))))) -> Benchmark fehlt | T37: Item-Bezeichnung und Messdefinition passen nicht ausreichend zusammen. Top-10-Prozent, Mittelwert, 150 % und 250 % müssen aus einer dokumentierten Grundgesamtheit stammen. | U37: Top‑10%:+3; Mittel:0; >150%:‑2; >250%:‑3 | V37: ESRS E5, GRI 306, WEEE/VerpackG | W37: ='02_Benchmarks'!$P37 -> Offen – validierter Benchmark fehlt | X37: Teilbelegt – Benchmarkquelle fehlt | Y37: Kritisch | Z37: Validierter Benchmark fehlt | AA37: Standort/Prozess/Aktivität; Bezugsgröße und relevante Umweltmedien | AB37: Primärdaten plus repräsentativer, versionierter Benchmarkdatensatz; Stichprobe und Population offenlegen | AC37: Messwert-Assurance und unabhängige Benchmark-Governance
A38: WOK-E-107 | B38: SDG 2 – Kein Hunger | C38: 2.4 | D38: Wasserentnahme (WSI) | E38: Wasserentnahme (WSI) – Entnahme (WSI) | F38: m³*WSI | G38: lower_is_better | H38: R06 | I38: BENCHMARK | N38: ="" | O38: =IF($J38="","",IF(OR('02_Benchmarks'!$P38<>"Aktiv",COUNT('02_Benchmarks'!$J38:$M38)<4),"",IF($G38="lower_is_better",IF($J38<='02_Benchmarks'!$J38,3,IF($J38<'02_Benchmarks'!$K38,2,IF($J38<='02_Benchmarks'!$L38,0,IF($J38<='02_Benchmarks'!$M38,-2,-3)))),IF($J38>='02_Benchmarks'!$J38,3,IF($J38>'02_Benchmarks'!$K38,2,IF($J38>='02_Benchmarks'!$L38,0,IF($J38>='02_Benchmarks'!$M38,-2,-3))))))) | P38: =IF(COUNT($N38:$O38)+IF(ISNUMBER($K38),1,0)=0,"",MIN($N38:$O38,$K38)) | Q38: =IF($P38="","",INDEX('04_Tarifmodell'!$B$6:$B$12,$P38+4)) | R38: =IF($P38="","",INDEX('04_Tarifmodell'!$C$6:$C$12,$P38+4)) | S38: =IF(OR($I38="QUALITATIVE",$I38="MANUAL_HYBRID"),IF($K38="","Assurance-Score fehlt","Assurance-bewertet"),IF($I38="BENCHMARK",IF($W38<>"Aktiv",IF($K38="","Benchmark fehlt","Assurance-bewertet"),IF($J38="","Messwert fehlt",IF($P38="","Nicht bewertbar","Berechnet"))),IF(AND($J38="",$K38<>""),"Nur Assurance-Score",IF($J38="","Messwert fehlt",IF($P38="","Nicht bewertbar",IF($P38<=-2,"Kritische Wirkung / Prüfung","Berechnet")))))) -> Benchmark fehlt | T38: Top-10-Prozent, Mittelwert, 150 % und 250 % müssen aus einer dokumentierten Grundgesamtheit stammen. | U38: Top‑10%:+3; Mittel:0; >150%:‑2; >250%:‑3 | V38: ESRS E3, WRI Aqueduct, ISO 14046 (Water Footprint) | W38: ='02_Benchmarks'!$P38 -> Offen – validierter Benchmark fehlt | X38: Teilbelegt – Benchmarkquelle fehlt | Y38: Hoch | Z38: Validierter Benchmark fehlt | AA38: Standort/Prozess/Aktivität; Bezugsgröße und relevante Umweltmedien | AB38: Primärdaten plus repräsentativer, versionierter Benchmarkdatensatz; Stichprobe und Population offenlegen | AC38: Messwert-Assurance und unabhängige Benchmark-Governance
A39: WOK-E-108 | B39: SDG 2 – Kein Hunger | C39: 2.4 | D39: Wasserentnahme (WSI) | E39: Wasserentnahme (WSI) – Reuse | F39: % | G39: higher_is_better | H39: R25 | I39: NUM_HIGH | N39: =IF($J39="","",IF($J39<30,-3,IF($J39<50,-2,IF($J39<70,0,IF($J39<90,2,3))))) | O39: =IF($J39="","",IF(OR('02_Benchmarks'!$P39<>"Aktiv",COUNT('02_Benchmarks'!$J39:$M39)<4),"",IF($G39="lower_is_better",IF($J39<='02_Benchmarks'!$J39,3,IF($J39<'02_Benchmarks'!$K39,2,IF($J39<='02_Benchmarks'!$L39,0,IF($J39<='02_Benchmarks'!$M39,-2,-3)))),IF($J39>='02_Benchmarks'!$J39,3,IF($J39>'02_Benchmarks'!$K39,2,IF($J39>='02_Benchmarks'!$L39,0,IF($J39>='02_Benchmarks'!$M39,-2,-3))))))) | P39: =IF(COUNT($N39:$O39)+IF(ISNUMBER($K39),1,0)=0,"",MIN($N39:$O39,$K39)) | Q39: =IF($P39="","",INDEX('04_Tarifmodell'!$B$6:$B$12,$P39+4)) | R39: =IF($P39="","",INDEX('04_Tarifmodell'!$C$6:$C$12,$P39+4)) | S39: =IF(OR($I39="QUALITATIVE",$I39="MANUAL_HYBRID"),IF($K39="","Assurance-Score fehlt","Assurance-bewertet"),IF($I39="BENCHMARK",IF($W39<>"Aktiv",IF($K39="","Benchmark fehlt","Assurance-bewertet"),IF($J39="","Messwert fehlt",IF($P39="","Nicht bewertbar","Berechnet"))),IF(AND($J39="",$K39<>""),"Nur Assurance-Score",IF($J39="","Messwert fehlt",IF($P39="","Nicht bewertbar",IF($P39<=-2,"Kritische Wirkung / Prüfung","Berechnet")))))) -> Messwert fehlt | T39: Vollständige fünfstufige Prozentregel. | U39: ≥90%:+3; 70–89%:+2; 50–69%:0; 30–49%:‑2; <30%:‑3 | V39: ESRS E3, WRI Aqueduct, ISO 14046 (Water Footprint) | W39: ='02_Benchmarks'!$P39 -> Optional – kein aktiver Benchmark | X39: Messgrundlage belegt; Schwellenkalibrierung offen | Y39: Mittel | Z39: Arbeitskalibrierung – fachlich zu validieren | AA39: Standort/Prozess/Aktivität; Bezugsgröße und relevante Umweltmedien | AB39: Primärdaten bevorzugt; Sekundärdaten nur transparent und versioniert; Methode und Systemgrenze dokumentieren | AC39: Limited Assurance; risikobasiert höhere Prüftiefe
A40: WOK-E-109 | B40: SDG 2 – Kein Hunger | C40: 2.4 | D40: Wasserentnahme (WSI) | E40: Wasserentnahme (WSI) – Abwasserqualität | F40: % des Grenzwerts | G40: lower_is_better | H40: R12 | I40: LEGAL_RATIO | N40: =IF($J40="","",IF($J40<=50,3,IF($J40<=75,2,IF($J40<=100,0,IF($J40<=120,-2,-3))))) | O40: =IF($J40="","",IF(OR('02_Benchmarks'!$P40<>"Aktiv",COUNT('02_Benchmarks'!$J40:$M40)<4),"",IF($G40="lower_is_better",IF($J40<='02_Benchmarks'!$J40,3,IF($J40<'02_Benchmarks'!$K40,2,IF($J40<='02_Benchmarks'!$L40,0,IF($J40<='02_Benchmarks'!$M40,-2,-3)))),IF($J40>='02_Benchmarks'!$J40,3,IF($J40>'02_Benchmarks'!$K40,2,IF($J40>='02_Benchmarks'!$L40,0,IF($J40>='02_Benchmarks'!$M40,-2,-3))))))) | P40: =IF(COUNT($N40:$O40)+IF(ISNUMBER($K40),1,0)=0,"",MIN($N40:$O40,$K40)) | Q40: =IF($P40="","",INDEX('04_Tarifmodell'!$B$6:$B$12,$P40+4)) | R40: =IF($P40="","",INDEX('04_Tarifmodell'!$C$6:$C$12,$P40+4)) | S40: =IF(OR($I40="QUALITATIVE",$I40="MANUAL_HYBRID"),IF($K40="","Assurance-Score fehlt","Assurance-bewertet"),IF($I40="BENCHMARK",IF($W40<>"Aktiv",IF($K40="","Benchmark fehlt","Assurance-bewertet"),IF($J40="","Messwert fehlt",IF($P40="","Nicht bewertbar","Berechnet"))),IF(AND($J40="",$K40<>""),"Nur Assurance-Score",IF($J40="","Messwert fehlt",IF($P40="","Nicht bewertbar",IF($P40<=-2,"Kritische Wirkung / Prüfung","Berechnet")))))) -> Messwert fehlt | T40: Nicht der absolute Messwert, sondern Messwert ÷ Grenzwert × 100 wird bewertet. | U40: ≤50% Grenzwert:+3; ≤75%:+2; ≤100%:0; 101–120%:‑2; >120%:‑3 | V40: ESRS E3, WRI Aqueduct, ISO 14046 (Water Footprint) | W40: ='02_Benchmarks'!$P40 -> Optional – kein aktiver Benchmark | X40: Teilbelegt – Rechtsfundstelle je Messung fehlt | Y40: Hoch | Z40: Rechtsfundstelle je Fall erforderlich | AA40: Standort/Prozess/Aktivität; Bezugsgröße und relevante Umweltmedien | AB40: Kalibrierter Messwert; Rechtsfundstelle, Grenzwert, Einheit, Messpunkt und Zeitraum | AC40: Behördlicher/akkreditierter Nachweis oder unabhängige Prüfung
A41: WOK-SC-104 | B41: SDG 2 – Kein Hunger | C41: 2.3 | D41: Kleinbauern‑Integration | E41: Kleinbauern‑Integration – ESG‑Spend‑Coverage | F41: % | G41: higher_is_better | H41: R26 | I41: NUM_HIGH | N41: =IF($J41="","",IF($J41<30,-3,IF($J41<50,-2,IF($J41<70,0,IF($J41<90,2,3))))) | O41: =IF($J41="","",IF(OR('02_Benchmarks'!$P41<>"Aktiv",COUNT('02_Benchmarks'!$J41:$M41)<4),"",IF($G41="lower_is_better",IF($J41<='02_Benchmarks'!$J41,3,IF($J41<'02_Benchmarks'!$K41,2,IF($J41<='02_Benchmarks'!$L41,0,IF($J41<='02_Benchmarks'!$M41,-2,-3)))),IF($J41>='02_Benchmarks'!$J41,3,IF($J41>'02_Benchmarks'!$K41,2,IF($J41>='02_Benchmarks'!$L41,0,IF($J41>='02_Benchmarks'!$M41,-2,-3))))))) | P41: =IF(COUNT($N41:$O41)+IF(ISNUMBER($K41),1,0)=0,"",MIN($N41:$O41,$K41)) | Q41: =IF($P41="","",INDEX('04_Tarifmodell'!$B$6:$B$12,$P41+4)) | R41: =IF($P41="","",INDEX('04_Tarifmodell'!$C$6:$C$12,$P41+4)) | S41: =IF(OR($I41="QUALITATIVE",$I41="MANUAL_HYBRID"),IF($K41="","Assurance-Score fehlt","Assurance-bewertet"),IF($I41="BENCHMARK",IF($W41<>"Aktiv",IF($K41="","Benchmark fehlt","Assurance-bewertet"),IF($J41="","Messwert fehlt",IF($P41="","Nicht bewertbar","Berechnet"))),IF(AND($J41="",$K41<>""),"Nur Assurance-Score",IF($J41="","Messwert fehlt",IF($P41="","Nicht bewertbar",IF($P41<=-2,"Kritische Wirkung / Prüfung","Berechnet")))))) -> Messwert fehlt | T41: Vollständige fünfstufige numerische Regel. | U41: ≥90:+3; 70–89:+2; 50–69:0; 30–49:‑2; <30:‑3 | V41: ESRS S2; GRI 308/414/408/409 | W41: ='02_Benchmarks'!$P41 -> Optional – kein aktiver Benchmark | X41: Messgrundlage belegt; Schwellenkalibrierung offen | Y41: Mittel | Z41: Arbeitskalibrierung – fachlich zu validieren | AA41: Vorgelagerte Lieferkette; relevante Tier-Stufen und Beschaffungsvolumen | AB41: Primärdaten bevorzugt; Sekundärdaten nur transparent und versioniert; Methode und Systemgrenze dokumentieren | AC41: Limited Assurance; risikobasiert höhere Prüftiefe
A42: WOK-SC-105 | B42: SDG 2 – Kein Hunger | C42: 2.3 | D42: Kleinbauern‑Integration | E42: Kleinbauern‑Integration – Kinder/Zwangsarbeit | F42: % Lieferanten | G42: higher_is_better | H42: R28 | I42: NUM_HIGH | N42: =IF($J42="","",IF($J42<50,-3,IF($J42<75,-2,IF($J42<90,0,IF($J42<98,2,3))))) | O42: =IF($J42="","",IF(OR('02_Benchmarks'!$P42<>"Aktiv",COUNT('02_Benchmarks'!$J42:$M42)<4),"",IF($G42="lower_is_better",IF($J42<='02_Benchmarks'!$J42,3,IF($J42<'02_Benchmarks'!$K42,2,IF($J42<='02_Benchmarks'!$L42,0,IF($J42<='02_Benchmarks'!$M42,-2,-3)))),IF($J42>='02_Benchmarks'!$J42,3,IF($J42>'02_Benchmarks'!$K42,2,IF($J42>='02_Benchmarks'!$L42,0,IF($J42>='02_Benchmarks'!$M42,-2,-3))))))) | P42: =IF(COUNT($N42:$O42)+IF(ISNUMBER($K42),1,0)=0,"",MIN($N42:$O42,$K42)) | Q42: =IF($P42="","",INDEX('04_Tarifmodell'!$B$6:$B$12,$P42+4)) | R42: =IF($P42="","",INDEX('04_Tarifmodell'!$C$6:$C$12,$P42+4)) | S42: =IF(OR($I42="QUALITATIVE",$I42="MANUAL_HYBRID"),IF($K42="","Assurance-Score fehlt","Assurance-bewertet"),IF($I42="BENCHMARK",IF($W42<>"Aktiv",IF($K42="","Benchmark fehlt","Assurance-bewertet"),IF($J42="","Messwert fehlt",IF($P42="","Nicht bewertbar","Berechnet"))),IF(AND($J42="",$K42<>""),"Nur Assurance-Score",IF($J42="","Messwert fehlt",IF($P42="","Nicht bewertbar",IF($P42<=-2,"Kritische Wirkung / Prüfung","Berechnet")))))) -> Messwert fehlt | T42: Vollständige fünfstufige numerische Regel. | U42: ≥98:+3; 90–97:+2; 75–89:0; 50–74:‑2; <50:‑3 | V42: ESRS S2, GRI 308/414, OECD Due Diligence | W42: ='02_Benchmarks'!$P42 -> Optional – kein aktiver Benchmark | X42: Messgrundlage belegt; Schwellenkalibrierung offen | Y42: Mittel | Z42: Arbeitskalibrierung – fachlich zu validieren | AA42: Vorgelagerte Lieferkette; relevante Tier-Stufen und Beschaffungsvolumen | AB42: Primärdaten bevorzugt; Sekundärdaten nur transparent und versioniert; Methode und Systemgrenze dokumentieren | AC42: Limited Assurance; risikobasiert höhere Prüftiefe
A43: WOK-SC-106 | B43: SDG 2 – Kein Hunger | C43: 2.3 | D43: Kleinbauern‑Integration | E43: Kleinbauern‑Integration – Scope‑3 Daten | F43: % Kategorien | G43: higher_is_better | H43: R23 | I43: NUM_HIGH | N43: =IF($J43="","",IF($J43<20,-3,IF($J43<40,-2,IF($J43<60,0,IF($J43<80,2,3))))) | O43: =IF($J43="","",IF(OR('02_Benchmarks'!$P43<>"Aktiv",COUNT('02_Benchmarks'!$J43:$M43)<4),"",IF($G43="lower_is_better",IF($J43<='02_Benchmarks'!$J43,3,IF($J43<'02_Benchmarks'!$K43,2,IF($J43<='02_Benchmarks'!$L43,0,IF($J43<='02_Benchmarks'!$M43,-2,-3)))),IF($J43>='02_Benchmarks'!$J43,3,IF($J43>'02_Benchmarks'!$K43,2,IF($J43>='02_Benchmarks'!$L43,0,IF($J43>='02_Benchmarks'!$M43,-2,-3))))))) | P43: =IF(COUNT($N43:$O43)+IF(ISNUMBER($K43),1,0)=0,"",MIN($N43:$O43,$K43)) | Q43: =IF($P43="","",INDEX('04_Tarifmodell'!$B$6:$B$12,$P43+4)) | R43: =IF($P43="","",INDEX('04_Tarifmodell'!$C$6:$C$12,$P43+4)) | S43: =IF(OR($I43="QUALITATIVE",$I43="MANUAL_HYBRID"),IF($K43="","Assurance-Score fehlt","Assurance-bewertet"),IF($I43="BENCHMARK",IF($W43<>"Aktiv",IF($K43="","Benchmark fehlt","Assurance-bewertet"),IF($J43="","Messwert fehlt",IF($P43="","Nicht bewertbar","Berechnet"))),IF(AND($J43="",$K43<>""),"Nur Assurance-Score",IF($J43="","Messwert fehlt",IF($P43="","Nicht bewertbar",IF($P43<=-2,"Kritische Wirkung / Prüfung","Berechnet")))))) -> Messwert fehlt | T43: Vollständige fünfstufige numerische Regel. | U43: ≥80:+3; 60–79:+2; 40–59:0; 20–39:‑2; <20:‑3 | V43: ESRS E1, GHG Protocol (Corporate/Scope 1–3), ISO 14064/14067 | W43: ='02_Benchmarks'!$P43 -> Optional – kein aktiver Benchmark | X43: Messgrundlage belegt; Schwellenkalibrierung offen | Y43: Mittel | Z43: Arbeitskalibrierung – fachlich zu validieren | AA43: Vorgelagerte Lieferkette; relevante Tier-Stufen und Beschaffungsvolumen | AB43: Primärdaten bevorzugt; Sekundärdaten nur transparent und versioniert; Methode und Systemgrenze dokumentieren | AC43: Limited Assurance; risikobasiert höhere Prüftiefe
A44: WOK-P-101 | B44: SDG 2 – Kein Hunger | C44: 2.4 | D44: Produkt‑PCF Agrar | E44: Produkt‑PCF Agrar – PCF | F44: kg CO₂e/Einheit | G44: lower_is_better | H44: R07 | I44: BENCHMARK | N44: ="" | O44: =IF($J44="","",IF(OR('02_Benchmarks'!$P44<>"Aktiv",COUNT('02_Benchmarks'!$J44:$M44)<4),"",IF($G44="lower_is_better",IF($J44<='02_Benchmarks'!$J44,3,IF($J44<'02_Benchmarks'!$K44,2,IF($J44<='02_Benchmarks'!$L44,0,IF($J44<='02_Benchmarks'!$M44,-2,-3)))),IF($J44>='02_Benchmarks'!$J44,3,IF($J44>'02_Benchmarks'!$K44,2,IF($J44>='02_Benchmarks'!$L44,0,IF($J44>='02_Benchmarks'!$M44,-2,-3))))))) | P44: =IF(COUNT($N44:$O44)+IF(ISNUMBER($K44),1,0)=0,"",MIN($N44:$O44,$K44)) | Q44: =IF($P44="","",INDEX('04_Tarifmodell'!$B$6:$B$12,$P44+4)) | R44: =IF($P44="","",INDEX('04_Tarifmodell'!$C$6:$C$12,$P44+4)) | S44: =IF(OR($I44="QUALITATIVE",$I44="MANUAL_HYBRID"),IF($K44="","Assurance-Score fehlt","Assurance-bewertet"),IF($I44="BENCHMARK",IF($W44<>"Aktiv",IF($K44="","Benchmark fehlt","Assurance-bewertet"),IF($J44="","Messwert fehlt",IF($P44="","Nicht bewertbar","Berechnet"))),IF(AND($J44="",$K44<>""),"Nur Assurance-Score",IF($J44="","Messwert fehlt",IF($P44="","Nicht bewertbar",IF($P44<=-2,"Kritische Wirkung / Prüfung","Berechnet")))))) -> Benchmark fehlt | T44: Produktspezifische Referenzpopulation erforderlich. | U44: Top‑10%:+3; ±Benchmark:0; >150%:‑2; >250%:‑3 | V44: ISO 14067/14040/44 (LCA/PCF), PEF/EF 3.1, EU Reparierbarkeitsindex | W44: ='02_Benchmarks'!$P44 -> Offen – validierter Benchmark fehlt | X44: Teilbelegt – Benchmarkquelle fehlt | Y44: Hoch | Z44: Validierter Benchmark fehlt | AA44: Produkt/Funktionseinheit; Lebenszyklusgrenze mindestens cradle-to-gate, bei Nutzungs-/End-of-Life-Relevanz cradle-to-grave | AB44: Primärdaten plus repräsentativer, versionierter Benchmarkdatensatz; Stichprobe und Population offenlegen | AC44: Messwert-Assurance und unabhängige Benchmark-Governance
A45: WOK-P-102 | B45: SDG 2 – Kein Hunger | C45: 2.4 | D45: Produkt‑PCF Agrar | E45: Produkt‑PCF Agrar – Reparierbarkeit | F45: Score 0–10 | G45: higher_is_better | H45: R24 | I45: NUM_HIGH | N45: =IF($J45="","",IF($J45<2,-3,IF($J45<4,-2,IF($J45<6,0,IF($J45<8,2,3))))) | O45: =IF($J45="","",IF(OR('02_Benchmarks'!$P45<>"Aktiv",COUNT('02_Benchmarks'!$J45:$M45)<4),"",IF($G45="lower_is_better",IF($J45<='02_Benchmarks'!$J45,3,IF($J45<'02_Benchmarks'!$K45,2,IF($J45<='02_Benchmarks'!$L45,0,IF($J45<='02_Benchmarks'!$M45,-2,-3)))),IF($J45>='02_Benchmarks'!$J45,3,IF($J45>'02_Benchmarks'!$K45,2,IF($J45>='02_Benchmarks'!$L45,0,IF($J45>='02_Benchmarks'!$M45,-2,-3))))))) | P45: =IF(COUNT($N45:$O45)+IF(ISNUMBER($K45),1,0)=0,"",MIN($N45:$O45,$K45)) | Q45: =IF($P45="","",INDEX('04_Tarifmodell'!$B$6:$B$12,$P45+4)) | R45: =IF($P45="","",INDEX('04_Tarifmodell'!$C$6:$C$12,$P45+4)) | S45: =IF(OR($I45="QUALITATIVE",$I45="MANUAL_HYBRID"),IF($K45="","Assurance-Score fehlt","Assurance-bewertet"),IF($I45="BENCHMARK",IF($W45<>"Aktiv",IF($K45="","Benchmark fehlt","Assurance-bewertet"),IF($J45="","Messwert fehlt",IF($P45="","Nicht bewertbar","Berechnet"))),IF(AND($J45="",$K45<>""),"Nur Assurance-Score",IF($J45="","Messwert fehlt",IF($P45="","Nicht bewertbar",IF($P45<=-2,"Kritische Wirkung / Prüfung","Berechnet")))))) -> Messwert fehlt | T45: Indexsystem, Produktgruppe und Rechtsstand festlegen. Französischer Index und EU-Score sind nicht pauschal austauschbar. | U45: ≥8:+3; 6–7,9:+2; 4–5,9:0; 2–3,9:‑2; <2:‑3 | V45: ISO 14067/14040/44 (LCA/PCF), PEF/EF 3.1, EU Reparierbarkeitsindex | W45: ='02_Benchmarks'!$P45 -> Optional – kein aktiver Benchmark | X45: Teilbelegt – produktspezifisch zu validieren | Y45: Hoch | Z45: Indexsystem und Produktgruppe müssen ausgewiesen werden | AA45: Produkt/Funktionseinheit; Lebenszyklusgrenze mindestens cradle-to-gate, bei Nutzungs-/End-of-Life-Relevanz cradle-to-grave | AB45: Primärdaten oder qualitätsgesicherte Sekundärdaten; Methode, Zeitraum und Systemgrenze dokumentieren | AC45: Limited Assurance; bei materieller Steuerwirkung risikobasiert vertiefen
A46: WOK-P-103 | B46: SDG 2 – Kein Hunger | C46: 2.4 | D46: Produkt‑PCF Agrar | E46: Produkt‑PCF Agrar – Rücknahme/Recycling | F46: % | G46: higher_is_better | H46: R22 | I46: NUM_HIGH | N46: =IF($J46="","",IF($J46<15,-3,IF($J46<30,-2,IF($J46<50,0,IF($J46<70,2,3))))) | O46: =IF($J46="","",IF(OR('02_Benchmarks'!$P46<>"Aktiv",COUNT('02_Benchmarks'!$J46:$M46)<4),"",IF($G46="lower_is_better",IF($J46<='02_Benchmarks'!$J46,3,IF($J46<'02_Benchmarks'!$K46,2,IF($J46<='02_Benchmarks'!$L46,0,IF($J46<='02_Benchmarks'!$M46,-2,-3)))),IF($J46>='02_Benchmarks'!$J46,3,IF($J46>'02_Benchmarks'!$K46,2,IF($J46>='02_Benchmarks'!$L46,0,IF($J46>='02_Benchmarks'!$M46,-2,-3))))))) | P46: =IF(COUNT($N46:$O46)+IF(ISNUMBER($K46),1,0)=0,"",MIN($N46:$O46,$K46)) | Q46: =IF($P46="","",INDEX('04_Tarifmodell'!$B$6:$B$12,$P46+4)) | R46: =IF($P46="","",INDEX('04_Tarifmodell'!$C$6:$C$12,$P46+4)) | S46: =IF(OR($I46="QUALITATIVE",$I46="MANUAL_HYBRID"),IF($K46="","Assurance-Score fehlt","Assurance-bewertet"),IF($I46="BENCHMARK",IF($W46<>"Aktiv",IF($K46="","Benchmark fehlt","Assurance-bewertet"),IF($J46="","Messwert fehlt",IF($P46="","Nicht bewertbar","Berechnet"))),IF(AND($J46="",$K46<>""),"Nur Assurance-Score",IF($J46="","Messwert fehlt",IF($P46="","Nicht bewertbar",IF($P46<=-2,"Kritische Wirkung / Prüfung","Berechnet")))))) -> Messwert fehlt | T46: Vollständige fünfstufige numerische Regel. | U46: ≥70:+3; 50–69:+2; 30–49:0; 15–29:‑2; <15:‑3 | V46: ESRS E5, GRI 306, WEEE/VerpackG | W46: ='02_Benchmarks'!$P46 -> Optional – kein aktiver Benchmark | X46: Messgrundlage belegt; Schwellenkalibrierung offen | Y46: Mittel | Z46: Arbeitskalibrierung – fachlich zu validieren | AA46: Produkt/Funktionseinheit; Lebenszyklusgrenze mindestens cradle-to-gate, bei Nutzungs-/End-of-Life-Relevanz cradle-to-grave | AB46: Primärdaten bevorzugt; Sekundärdaten nur transparent und versioniert; Methode und Systemgrenze dokumentieren | AC46: Limited Assurance; risikobasiert höhere Prüftiefe
A47: WOK-E-110 | B47: SDG 2 – Kein Hunger | C47: 2.4 | D47: Boden‑Organik/Fruchtbarkeit | E47: Boden‑Organik/Fruchtbarkeit – Nettoeffekt | F47: Qualitativ → Klasse | G47: higher_is_better | H47: R03 | I47: QUALITATIVE | N47: ="" | O47: =IF($J47="","",IF(OR('02_Benchmarks'!$P47<>"Aktiv",COUNT('02_Benchmarks'!$J47:$M47)<4),"",IF($G47="lower_is_better",IF($J47<='02_Benchmarks'!$J47,3,IF($J47<'02_Benchmarks'!$K47,2,IF($J47<='02_Benchmarks'!$L47,0,IF($J47<='02_Benchmarks'!$M47,-2,-3)))),IF($J47>='02_Benchmarks'!$J47,3,IF($J47>'02_Benchmarks'!$K47,2,IF($J47>='02_Benchmarks'!$L47,0,IF($J47>='02_Benchmarks'!$M47,-2,-3))))))) | P47: =IF(COUNT($N47:$O47)+IF(ISNUMBER($K47),1,0)=0,"",MIN($N47:$O47,$K47)) | Q47: =IF($P47="","",INDEX('04_Tarifmodell'!$B$6:$B$12,$P47+4)) | R47: =IF($P47="","",INDEX('04_Tarifmodell'!$C$6:$C$12,$P47+4)) | S47: =IF(OR($I47="QUALITATIVE",$I47="MANUAL_HYBRID"),IF($K47="","Assurance-Score fehlt","Assurance-bewertet"),IF($I47="BENCHMARK",IF($W47<>"Aktiv",IF($K47="","Benchmark fehlt","Assurance-bewertet"),IF($J47="","Messwert fehlt",IF($P47="","Nicht bewertbar","Berechnet"))),IF(AND($J47="",$K47<>""),"Nur Assurance-Score",IF($J47="","Messwert fehlt",IF($P47="","Nicht bewertbar",IF($P47<=-2,"Kritische Wirkung / Prüfung","Berechnet")))))) -> Assurance-Score fehlt | T47: Net Gain/No Net Loss/Net Loss ist ohne feldspezifischen Nachweis nicht automatisierbar. | U47: Net Gain:+3; No Net Loss:0; Net Loss:‑2/‑3 | V47: ESRS E4, CBD/GBF, EN 15978 (Bau) | W47: ='02_Benchmarks'!$P47 -> Optional – kein aktiver Benchmark | X47: Messgrundlage belegt; Schwellenkalibrierung offen | Y47: Hoch | Z47: Assurance und Kriterienkatalog erforderlich | AA47: Standort/Prozess/Aktivität; Bezugsgröße und relevante Umweltmedien | AB47: Dokumentierter Kriterienkatalog; nachvollziehbare Evidenz; DQR A/B bevorzugt | AC47: Unabhängige Fachprüfung/Limited Assurance; bei roten Linien Reasonable Assurance
A48: WOK-E-111 | B48: SDG 2 – Kein Hunger | C48: 2.4 | D48: Boden‑Organik/Fruchtbarkeit | E48: Boden‑Organik/Fruchtbarkeit – Landumwandlung | F48: ha/Jahr | G48: lower_is_better | H48: R02 | I48: NUM_LOW | N48: =IF($J48="","",IF($J48<=0,3,IF($J48<=1,2,IF($J48<=3,0,IF($J48<=5,-2,-3))))) | O48: =IF($J48="","",IF(OR('02_Benchmarks'!$P48<>"Aktiv",COUNT('02_Benchmarks'!$J48:$M48)<4),"",IF($G48="lower_is_better",IF($J48<='02_Benchmarks'!$J48,3,IF($J48<'02_Benchmarks'!$K48,2,IF($J48<='02_Benchmarks'!$L48,0,IF($J48<='02_Benchmarks'!$M48,-2,-3)))),IF($J48>='02_Benchmarks'!$J48,3,IF($J48>'02_Benchmarks'!$K48,2,IF($J48>='02_Benchmarks'!$L48,0,IF($J48>='02_Benchmarks'!$M48,-2,-3))))))) | P48: =IF(COUNT($N48:$O48)+IF(ISNUMBER($K48),1,0)=0,"",MIN($N48:$O48,$K48)) | Q48: =IF($P48="","",INDEX('04_Tarifmodell'!$B$6:$B$12,$P48+4)) | R48: =IF($P48="","",INDEX('04_Tarifmodell'!$C$6:$C$12,$P48+4)) | S48: =IF(OR($I48="QUALITATIVE",$I48="MANUAL_HYBRID"),IF($K48="","Assurance-Score fehlt","Assurance-bewertet"),IF($I48="BENCHMARK",IF($W48<>"Aktiv",IF($K48="","Benchmark fehlt","Assurance-bewertet"),IF($J48="","Messwert fehlt",IF($P48="","Nicht bewertbar","Berechnet"))),IF(AND($J48="",$K48<>""),"Nur Assurance-Score",IF($J48="","Messwert fehlt",IF($P48="","Nicht bewertbar",IF($P48<=-2,"Kritische Wirkung / Prüfung","Berechnet")))))) -> Messwert fehlt | T48: Vollständige fünfstufige numerische Regel. | U48: 0:+3; ≤1:+2; ≤3:0; ≤5:‑2; >5:‑3 | V48: ESRS E4, CBD/GBF, EN 15978 (Bau) | W48: ='02_Benchmarks'!$P48 -> Optional – kein aktiver Benchmark | X48: Messgrundlage belegt; Schwellenkalibrierung offen | Y48: Mittel | Z48: Arbeitskalibrierung – fachlich zu validieren | AA48: Standort/Prozess/Aktivität; Bezugsgröße und relevante Umweltmedien | AB48: Primärdaten bevorzugt; Sekundärdaten nur transparent und versioniert; Methode und Systemgrenze dokumentieren | AC48: Limited Assurance; risikobasiert höhere Prüftiefe
A49: WOK-E-112 | B49: SDG 2 – Kein Hunger | C49: 2.4 | D49: Boden‑Organik/Fruchtbarkeit | E49: Boden‑Organik/Fruchtbarkeit – Deforestationsfrei | F49: % | G49: higher_is_better | H49: R28 | I49: NUM_HIGH | N49: =IF($J49="","",IF($J49<50,-3,IF($J49<75,-2,IF($J49<90,0,IF($J49<98,2,3))))) | O49: =IF($J49="","",IF(OR('02_Benchmarks'!$P49<>"Aktiv",COUNT('02_Benchmarks'!$J49:$M49)<4),"",IF($G49="lower_is_better",IF($J49<='02_Benchmarks'!$J49,3,IF($J49<'02_Benchmarks'!$K49,2,IF($J49<='02_Benchmarks'!$L49,0,IF($J49<='02_Benchmarks'!$M49,-2,-3)))),IF($J49>='02_Benchmarks'!$J49,3,IF($J49>'02_Benchmarks'!$K49,2,IF($J49>='02_Benchmarks'!$L49,0,IF($J49>='02_Benchmarks'!$M49,-2,-3))))))) | P49: =IF(COUNT($N49:$O49)+IF(ISNUMBER($K49),1,0)=0,"",MIN($N49:$O49,$K49)) | Q49: =IF($P49="","",INDEX('04_Tarifmodell'!$B$6:$B$12,$P49+4)) | R49: =IF($P49="","",INDEX('04_Tarifmodell'!$C$6:$C$12,$P49+4)) | S49: =IF(OR($I49="QUALITATIVE",$I49="MANUAL_HYBRID"),IF($K49="","Assurance-Score fehlt","Assurance-bewertet"),IF($I49="BENCHMARK",IF($W49<>"Aktiv",IF($K49="","Benchmark fehlt","Assurance-bewertet"),IF($J49="","Messwert fehlt",IF($P49="","Nicht bewertbar","Berechnet"))),IF(AND($J49="",$K49<>""),"Nur Assurance-Score",IF($J49="","Messwert fehlt",IF($P49="","Nicht bewertbar",IF($P49<=-2,"Kritische Wirkung / Prüfung","Berechnet")))))) -> Messwert fehlt | T49: Vollständige fünfstufige numerische Regel. | U49: ≥98:+3; 90–97:+2; 75–89:0; 50–74:‑2; <50:‑3 | V49: ESRS E4, CBD/GBF, EN 15978 (Bau) | W49: ='02_Benchmarks'!$P49 -> Optional – kein aktiver Benchmark | X49: Messgrundlage belegt; Schwellenkalibrierung offen | Y49: Mittel | Z49: Arbeitskalibrierung – fachlich zu validieren | AA49: Standort/Prozess/Aktivität; Bezugsgröße und relevante Umweltmedien | AB49: Primärdaten bevorzugt; Sekundärdaten nur transparent und versioniert; Methode und Systemgrenze dokumentieren | AC49: Limited Assurance; risikobasiert höhere Prüftiefe
A50: WOK-S-116 | B50: SDG 2 – Kein Hunger | C50: 2.3 | D50: Saisonarbeits‑Standards | E50: Saisonarbeits‑Standards – Living Wage | F50: % Beschäftigte | G50: higher_is_better | H50: R27 | I50: NUM_HIGH | N50: =IF($J50="","",IF($J50<40,-3,IF($J50<60,-2,IF($J50<80,0,IF($J50<95,2,3))))) | O50: =IF($J50="","",IF(OR('02_Benchmarks'!$P50<>"Aktiv",COUNT('02_Benchmarks'!$J50:$M50)<4),"",IF($G50="lower_is_better",IF($J50<='02_Benchmarks'!$J50,3,IF($J50<'02_Benchmarks'!$K50,2,IF($J50<='02_Benchmarks'!$L50,0,IF($J50<='02_Benchmarks'!$M50,-2,-3)))),IF($J50>='02_Benchmarks'!$J50,3,IF($J50>'02_Benchmarks'!$K50,2,IF($J50>='02_Benchmarks'!$L50,0,IF($J50>='02_Benchmarks'!$M50,-2,-3))))))) | P50: =IF(COUNT($N50:$O50)+IF(ISNUMBER($K50),1,0)=0,"",MIN($N50:$O50,$K50)) | Q50: =IF($P50="","",INDEX('04_Tarifmodell'!$B$6:$B$12,$P50+4)) | R50: =IF($P50="","",INDEX('04_Tarifmodell'!$C$6:$C$12,$P50+4)) | S50: =IF(OR($I50="QUALITATIVE",$I50="MANUAL_HYBRID"),IF($K50="","Assurance-Score fehlt","Assurance-bewertet"),IF($I50="BENCHMARK",IF($W50<>"Aktiv",IF($K50="","Benchmark fehlt","Assurance-bewertet"),IF($J50="","Messwert fehlt",IF($P50="","Nicht bewertbar","Berechnet"))),IF(AND($J50="",$K50<>""),"Nur Assurance-Score",IF($J50="","Messwert fehlt",IF($P50="","Nicht bewertbar",IF($P50<=-2,"Kritische Wirkung / Prüfung","Berechnet")))))) -> Messwert fehlt | T50: Vollständige fünfstufige numerische Regel. | U50: ≥95:+3; 80–94:+2; 60–79:0; 40–59:‑2; <40:‑3 | V50: ESRS S1, GRI 401/403/405/406, ILO | W50: ='02_Benchmarks'!$P50 -> Optional – kein aktiver Benchmark | X50: Messgrundlage belegt; Schwellenkalibrierung offen | Y50: Mittel | Z50: Arbeitskalibrierung – fachlich zu validieren | AA50: Eigene Belegschaft/Organisation; FTE, Beschäftigtengruppe und Zeitraum | AB50: Primärdaten bevorzugt; Sekundärdaten nur transparent und versioniert; Methode und Systemgrenze dokumentieren | AC50: Limited Assurance; risikobasiert höhere Prüftiefe
A51: WOK-S-117 | B51: SDG 2 – Kein Hunger | C51: 2.3 | D51: Saisonarbeits‑Standards | E51: Saisonarbeits‑Standards – Tarifbindung | F51: % | G51: higher_is_better | H51: R26 | I51: NUM_HIGH | N51: =IF($J51="","",IF($J51<30,-3,IF($J51<50,-2,IF($J51<70,0,IF($J51<90,2,3))))) | O51: =IF($J51="","",IF(OR('02_Benchmarks'!$P51<>"Aktiv",COUNT('02_Benchmarks'!$J51:$M51)<4),"",IF($G51="lower_is_better",IF($J51<='02_Benchmarks'!$J51,3,IF($J51<'02_Benchmarks'!$K51,2,IF($J51<='02_Benchmarks'!$L51,0,IF($J51<='02_Benchmarks'!$M51,-2,-3)))),IF($J51>='02_Benchmarks'!$J51,3,IF($J51>'02_Benchmarks'!$K51,2,IF($J51>='02_Benchmarks'!$L51,0,IF($J51>='02_Benchmarks'!$M51,-2,-3))))))) | P51: =IF(COUNT($N51:$O51)+IF(ISNUMBER($K51),1,0)=0,"",MIN($N51:$O51,$K51)) | Q51: =IF($P51="","",INDEX('04_Tarifmodell'!$B$6:$B$12,$P51+4)) | R51: =IF($P51="","",INDEX('04_Tarifmodell'!$C$6:$C$12,$P51+4)) | S51: =IF(OR($I51="QUALITATIVE",$I51="MANUAL_HYBRID"),IF($K51="","Assurance-Score fehlt","Assurance-bewertet"),IF($I51="BENCHMARK",IF($W51<>"Aktiv",IF($K51="","Benchmark fehlt","Assurance-bewertet"),IF($J51="","Messwert fehlt",IF($P51="","Nicht bewertbar","Berechnet"))),IF(AND($J51="",$K51<>""),"Nur Assurance-Score",IF($J51="","Messwert fehlt",IF($P51="","Nicht bewertbar",IF($P51<=-2,"Kritische Wirkung / Prüfung","Berechnet")))))) -> Messwert fehlt | T51: Vollständige fünfstufige numerische Regel. | U51: ≥90:+3; 70–89:+2; 50–69:0; 30–49:‑2; <30:‑3 | V51: ESRS S1, GRI 401/403/405/406, ILO | W51: ='02_Benchmarks'!$P51 -> Optional – kein aktiver Benchmark | X51: Messgrundlage belegt; Schwellenkalibrierung offen | Y51: Mittel | Z51: Arbeitskalibrierung – fachlich zu validieren | AA51: Eigene Belegschaft/Organisation; FTE, Beschäftigtengruppe und Zeitraum | AB51: Primärdaten bevorzugt; Sekundärdaten nur transparent und versioniert; Methode und Systemgrenze dokumentieren | AC51: Limited Assurance; risikobasiert höhere Prüftiefe
A52: WOK-S-118 | B52: SDG 2 – Kein Hunger | C52: 2.3 | D52: Saisonarbeits‑Standards | E52: Saisonarbeits‑Standards – LTIFR | F52: Unfälle/Mio Std. | G52: lower_is_better | H52: R02 | I52: NUM_LOW | N52: =IF($J52="","",IF($J52<=0,3,IF($J52<=1,2,IF($J52<=3,0,IF($J52<=5,-2,-3))))) | O52: =IF($J52="","",IF(OR('02_Benchmarks'!$P52<>"Aktiv",COUNT('02_Benchmarks'!$J52:$M52)<4),"",IF($G52="lower_is_better",IF($J52<='02_Benchmarks'!$J52,3,IF($J52<'02_Benchmarks'!$K52,2,IF($J52<='02_Benchmarks'!$L52,0,IF($J52<='02_Benchmarks'!$M52,-2,-3)))),IF($J52>='02_Benchmarks'!$J52,3,IF($J52>'02_Benchmarks'!$K52,2,IF($J52>='02_Benchmarks'!$L52,0,IF($J52>='02_Benchmarks'!$M52,-2,-3))))))) | P52: =IF(COUNT($N52:$O52)+IF(ISNUMBER($K52),1,0)=0,"",MIN($N52:$O52,$K52)) | Q52: =IF($P52="","",INDEX('04_Tarifmodell'!$B$6:$B$12,$P52+4)) | R52: =IF($P52="","",INDEX('04_Tarifmodell'!$C$6:$C$12,$P52+4)) | S52: =IF(OR($I52="QUALITATIVE",$I52="MANUAL_HYBRID"),IF($K52="","Assurance-Score fehlt","Assurance-bewertet"),IF($I52="BENCHMARK",IF($W52<>"Aktiv",IF($K52="","Benchmark fehlt","Assurance-bewertet"),IF($J52="","Messwert fehlt",IF($P52="","Nicht bewertbar","Berechnet"))),IF(AND($J52="",$K52<>""),"Nur Assurance-Score",IF($J52="","Messwert fehlt",IF($P52="","Nicht bewertbar",IF($P52<=-2,"Kritische Wirkung / Prüfung","Berechnet")))))) -> Messwert fehlt | T52: Vollständige fünfstufige numerische Regel. | U52: 0:+3; ≤1:+2; ≤3:0; ≤5:‑2; >5:‑3 | V52: ESRS S1, GRI 401/403/405/406, ILO | W52: ='02_Benchmarks'!$P52 -> Optional – kein aktiver Benchmark | X52: Messgrundlage belegt; Schwellenkalibrierung offen | Y52: Mittel | Z52: Arbeitskalibrierung – fachlich zu validieren | AA52: Eigene Belegschaft/Organisation; FTE, Beschäftigtengruppe und Zeitraum | AB52: Primärdaten bevorzugt; Sekundärdaten nur transparent und versioniert; Methode und Systemgrenze dokumentieren | AC52: Limited Assurance; risikobasiert höhere Prüftiefe
A53: WOK-G-107 | B53: SDG 2 – Kein Hunger | C53: 2.1 | D53: Lebensmittelsicherheit & Rückrufe | E53: Lebensmittelsicherheit & Rückrufe – Antikorruption | F53: Fälle/1.000 FTE | G53: lower_is_better | H53: R01 | I53: NUM_LOW | N53: =IF($J53="","",IF($J53<=0,3,IF($J53<=0.2,2,IF($J53<=0.5,0,IF($J53<=1,-2,-3))))) | O53: =IF($J53="","",IF(OR('02_Benchmarks'!$P53<>"Aktiv",COUNT('02_Benchmarks'!$J53:$M53)<4),"",IF($G53="lower_is_better",IF($J53<='02_Benchmarks'!$J53,3,IF($J53<'02_Benchmarks'!$K53,2,IF($J53<='02_Benchmarks'!$L53,0,IF($J53<='02_Benchmarks'!$M53,-2,-3)))),IF($J53>='02_Benchmarks'!$J53,3,IF($J53>'02_Benchmarks'!$K53,2,IF($J53>='02_Benchmarks'!$L53,0,IF($J53>='02_Benchmarks'!$M53,-2,-3))))))) | P53: =IF(COUNT($N53:$O53)+IF(ISNUMBER($K53),1,0)=0,"",MIN($N53:$O53,$K53)) | Q53: =IF($P53="","",INDEX('04_Tarifmodell'!$B$6:$B$12,$P53+4)) | R53: =IF($P53="","",INDEX('04_Tarifmodell'!$C$6:$C$12,$P53+4)) | S53: =IF(OR($I53="QUALITATIVE",$I53="MANUAL_HYBRID"),IF($K53="","Assurance-Score fehlt","Assurance-bewertet"),IF($I53="BENCHMARK",IF($W53<>"Aktiv",IF($K53="","Benchmark fehlt","Assurance-bewertet"),IF($J53="","Messwert fehlt",IF($P53="","Nicht bewertbar","Berechnet"))),IF(AND($J53="",$K53<>""),"Nur Assurance-Score",IF($J53="","Messwert fehlt",IF($P53="","Nicht bewertbar",IF($P53<=-2,"Kritische Wirkung / Prüfung","Berechnet")))))) -> Messwert fehlt | T53: Vollständige fünfstufige numerische Regel. | U53: 0:+3; ≤0,2:+2; ≤0,5:0; ≤1:‑2; >1:‑3 | V53: ESRS G1, GRI 205/207, OECD Anti‑Bribery | W53: ='02_Benchmarks'!$P53 -> Optional – kein aktiver Benchmark | X53: Messgrundlage belegt; Schwellenkalibrierung offen | Y53: Mittel | Z53: Arbeitskalibrierung – fachlich zu validieren | AA53: Organisation/Governance; konsolidierter Kreis und relevante Rechtseinheiten | AB53: Primärdaten bevorzugt; Sekundärdaten nur transparent und versioniert; Methode und Systemgrenze dokumentieren | AC53: Limited Assurance; risikobasiert höhere Prüftiefe
A54: WOK-G-108 | B54: SDG 2 – Kein Hunger | C54: 2.1 | D54: Lebensmittelsicherheit & Rückrufe | E54: Lebensmittelsicherheit & Rückrufe – Whistleblowing | F54: 0–1 | G54: higher_is_better | H54: R16 | I54: NUM_HIGH | N54: =IF($J54="","",IF($J54<0.4,-3,IF($J54<0.6,-2,IF($J54<0.75,0,IF($J54<0.9,2,3))))) | O54: =IF($J54="","",IF(OR('02_Benchmarks'!$P54<>"Aktiv",COUNT('02_Benchmarks'!$J54:$M54)<4),"",IF($G54="lower_is_better",IF($J54<='02_Benchmarks'!$J54,3,IF($J54<'02_Benchmarks'!$K54,2,IF($J54<='02_Benchmarks'!$L54,0,IF($J54<='02_Benchmarks'!$M54,-2,-3)))),IF($J54>='02_Benchmarks'!$J54,3,IF($J54>'02_Benchmarks'!$K54,2,IF($J54>='02_Benchmarks'!$L54,0,IF($J54>='02_Benchmarks'!$M54,-2,-3))))))) | P54: =IF(COUNT($N54:$O54)+IF(ISNUMBER($K54),1,0)=0,"",MIN($N54:$O54,$K54)) | Q54: =IF($P54="","",INDEX('04_Tarifmodell'!$B$6:$B$12,$P54+4)) | R54: =IF($P54="","",INDEX('04_Tarifmodell'!$C$6:$C$12,$P54+4)) | S54: =IF(OR($I54="QUALITATIVE",$I54="MANUAL_HYBRID"),IF($K54="","Assurance-Score fehlt","Assurance-bewertet"),IF($I54="BENCHMARK",IF($W54<>"Aktiv",IF($K54="","Benchmark fehlt","Assurance-bewertet"),IF($J54="","Messwert fehlt",IF($P54="","Nicht bewertbar","Berechnet"))),IF(AND($J54="",$K54<>""),"Nur Assurance-Score",IF($J54="","Messwert fehlt",IF($P54="","Nicht bewertbar",IF($P54<=-2,"Kritische Wirkung / Prüfung","Berechnet")))))) -> Messwert fehlt | T54: Vollständige fünfstufige numerische Regel. | U54: ≥0,9:+3; 0,75–0,89:+2; 0,6–0,74:0; 0,4–0,59:‑2; <0,4:‑3 | V54: ESRS G1, GRI 205/207, OECD Anti‑Bribery | W54: ='02_Benchmarks'!$P54 -> Optional – kein aktiver Benchmark | X54: Messgrundlage belegt; Schwellenkalibrierung offen | Y54: Mittel | Z54: Arbeitskalibrierung – fachlich zu validieren | AA54: Organisation/Governance; konsolidierter Kreis und relevante Rechtseinheiten | AB54: Primärdaten bevorzugt; Sekundärdaten nur transparent und versioniert; Methode und Systemgrenze dokumentieren | AC54: Limited Assurance; risikobasiert höhere Prüftiefe
A55: WOK-G-109 | B55: SDG 2 – Kein Hunger | C55: 2.1 | D55: Lebensmittelsicherheit & Rückrufe | E55: Lebensmittelsicherheit & Rückrufe – Steuertransparenz | F55: 0–1 | G55: higher_is_better | H55: R08 | I55: QUALITATIVE | N55: ="" | O55: =IF($J55="","",IF(OR('02_Benchmarks'!$P55<>"Aktiv",COUNT('02_Benchmarks'!$J55:$M55)<4),"",IF($G55="lower_is_better",IF($J55<='02_Benchmarks'!$J55,3,IF($J55<'02_Benchmarks'!$K55,2,IF($J55<='02_Benchmarks'!$L55,0,IF($J55<='02_Benchmarks'!$M55,-2,-3)))),IF($J55>='02_Benchmarks'!$J55,3,IF($J55>'02_Benchmarks'!$K55,2,IF($J55>='02_Benchmarks'!$L55,0,IF($J55>='02_Benchmarks'!$M55,-2,-3))))))) | P55: =IF(COUNT($N55:$O55)+IF(ISNUMBER($K55),1,0)=0,"",MIN($N55:$O55,$K55)) | Q55: =IF($P55="","",INDEX('04_Tarifmodell'!$B$6:$B$12,$P55+4)) | R55: =IF($P55="","",INDEX('04_Tarifmodell'!$C$6:$C$12,$P55+4)) | S55: =IF(OR($I55="QUALITATIVE",$I55="MANUAL_HYBRID"),IF($K55="","Assurance-Score fehlt","Assurance-bewertet"),IF($I55="BENCHMARK",IF($W55<>"Aktiv",IF($K55="","Benchmark fehlt","Assurance-bewertet"),IF($J55="","Messwert fehlt",IF($P55="","Nicht bewertbar","Berechnet"))),IF(AND($J55="",$K55<>""),"Nur Assurance-Score",IF($J55="","Messwert fehlt",IF($P55="","Nicht bewertbar",IF($P55<=-2,"Kritische Wirkung / Prüfung","Berechnet")))))) -> Assurance-Score fehlt | T55: Die Kategorie −3 fehlt; Vollständigkeit und Wirksamkeit sind feldspezifisch zu definieren. | U55: vollständig:+3; teilweise:+2; minimal:0; schlecht:‑2 | V55: ESRS G1, GRI 205/207, OECD Anti‑Bribery | W55: ='02_Benchmarks'!$P55 -> Optional – kein aktiver Benchmark | X55: Messgrundlage belegt; Schwellenkalibrierung offen | Y55: Hoch | Z55: Assurance und Kriterienkatalog erforderlich | AA55: Organisation/Governance; konsolidierter Kreis und relevante Rechtseinheiten | AB55: Dokumentierter Kriterienkatalog; nachvollziehbare Evidenz; DQR A/B bevorzugt | AC55: Unabhängige Fachprüfung/Limited Assurance; bei roten Linien Reasonable Assurance
A56: WOK-E-113 | B56: SDG 2 – Kein Hunger | C56: 2.1 | D56: Food Waste entlang Kette | E56: Food Waste entlang Kette – Abfallintensität | F56: kg/t | G56: lower_is_better | H56: R06 | I56: BENCHMARK | N56: ="" | O56: =IF($J56="","",IF(OR('02_Benchmarks'!$P56<>"Aktiv",COUNT('02_Benchmarks'!$J56:$M56)<4),"",IF($G56="lower_is_better",IF($J56<='02_Benchmarks'!$J56,3,IF($J56<'02_Benchmarks'!$K56,2,IF($J56<='02_Benchmarks'!$L56,0,IF($J56<='02_Benchmarks'!$M56,-2,-3)))),IF($J56>='02_Benchmarks'!$J56,3,IF($J56>'02_Benchmarks'!$K56,2,IF($J56>='02_Benchmarks'!$L56,0,IF($J56>='02_Benchmarks'!$M56,-2,-3))))))) | P56: =IF(COUNT($N56:$O56)+IF(ISNUMBER($K56),1,0)=0,"",MIN($N56:$O56,$K56)) | Q56: =IF($P56="","",INDEX('04_Tarifmodell'!$B$6:$B$12,$P56+4)) | R56: =IF($P56="","",INDEX('04_Tarifmodell'!$C$6:$C$12,$P56+4)) | S56: =IF(OR($I56="QUALITATIVE",$I56="MANUAL_HYBRID"),IF($K56="","Assurance-Score fehlt","Assurance-bewertet"),IF($I56="BENCHMARK",IF($W56<>"Aktiv",IF($K56="","Benchmark fehlt","Assurance-bewertet"),IF($J56="","Messwert fehlt",IF($P56="","Nicht bewertbar","Berechnet"))),IF(AND($J56="",$K56<>""),"Nur Assurance-Score",IF($J56="","Messwert fehlt",IF($P56="","Nicht bewertbar",IF($P56<=-2,"Kritische Wirkung / Prüfung","Berechnet")))))) -> Benchmark fehlt | T56: Top-10-Prozent, Mittelwert, 150 % und 250 % müssen aus einer dokumentierten Grundgesamtheit stammen. | U56: Top‑10%:+3; Mittel:0; >150%:‑2; >250%:‑3 | V56: ESRS E5, GRI 306, WEEE/VerpackG | W56: ='02_Benchmarks'!$P56 -> Offen – validierter Benchmark fehlt | X56: Teilbelegt – Benchmarkquelle fehlt | Y56: Hoch | Z56: Validierter Benchmark fehlt | AA56: Standort/Prozess/Aktivität; Bezugsgröße und relevante Umweltmedien | AB56: Primärdaten plus repräsentativer, versionierter Benchmarkdatensatz; Stichprobe und Population offenlegen | AC56: Messwert-Assurance und unabhängige Benchmark-Governance
A57: WOK-E-114 | B57: SDG 2 – Kein Hunger | C57: 2.1 | D57: Food Waste entlang Kette | E57: Food Waste entlang Kette – Recyclingquote | F57: % | G57: higher_is_better | H57: R25 | I57: NUM_HIGH | N57: =IF($J57="","",IF($J57<30,-3,IF($J57<50,-2,IF($J57<70,0,IF($J57<90,2,3))))) | O57: =IF($J57="","",IF(OR('02_Benchmarks'!$P57<>"Aktiv",COUNT('02_Benchmarks'!$J57:$M57)<4),"",IF($G57="lower_is_better",IF($J57<='02_Benchmarks'!$J57,3,IF($J57<'02_Benchmarks'!$K57,2,IF($J57<='02_Benchmarks'!$L57,0,IF($J57<='02_Benchmarks'!$M57,-2,-3)))),IF($J57>='02_Benchmarks'!$J57,3,IF($J57>'02_Benchmarks'!$K57,2,IF($J57>='02_Benchmarks'!$L57,0,IF($J57>='02_Benchmarks'!$M57,-2,-3))))))) | P57: =IF(COUNT($N57:$O57)+IF(ISNUMBER($K57),1,0)=0,"",MIN($N57:$O57,$K57)) | Q57: =IF($P57="","",INDEX('04_Tarifmodell'!$B$6:$B$12,$P57+4)) | R57: =IF($P57="","",INDEX('04_Tarifmodell'!$C$6:$C$12,$P57+4)) | S57: =IF(OR($I57="QUALITATIVE",$I57="MANUAL_HYBRID"),IF($K57="","Assurance-Score fehlt","Assurance-bewertet"),IF($I57="BENCHMARK",IF($W57<>"Aktiv",IF($K57="","Benchmark fehlt","Assurance-bewertet"),IF($J57="","Messwert fehlt",IF($P57="","Nicht bewertbar","Berechnet"))),IF(AND($J57="",$K57<>""),"Nur Assurance-Score",IF($J57="","Messwert fehlt",IF($P57="","Nicht bewertbar",IF($P57<=-2,"Kritische Wirkung / Prüfung","Berechnet")))))) -> Messwert fehlt | T57: Vollständige fünfstufige Prozentregel. | U57: ≥90%:+3; 70–89%:+2; 50–69%:0; 30–49%:‑2; <30%:‑3 | V57: ESRS E5, GRI 306, WEEE/VerpackG | W57: ='02_Benchmarks'!$P57 -> Optional – kein aktiver Benchmark | X57: Messgrundlage belegt; Schwellenkalibrierung offen | Y57: Mittel | Z57: Arbeitskalibrierung – fachlich zu validieren | AA57: Standort/Prozess/Aktivität; Bezugsgröße und relevante Umweltmedien | AB57: Primärdaten bevorzugt; Sekundärdaten nur transparent und versioniert; Methode und Systemgrenze dokumentieren | AC57: Limited Assurance; risikobasiert höhere Prüftiefe
A58: WOK-E-115 | B58: SDG 2 – Kein Hunger | C58: 2.1 | D58: Food Waste entlang Kette | E58: Food Waste entlang Kette – Gefährlicher Abfall | F58: kg/t | G58: lower_is_better | H58: R06 | I58: BENCHMARK | N58: ="" | O58: =IF($J58="","",IF(OR('02_Benchmarks'!$P58<>"Aktiv",COUNT('02_Benchmarks'!$J58:$M58)<4),"",IF($G58="lower_is_better",IF($J58<='02_Benchmarks'!$J58,3,IF($J58<'02_Benchmarks'!$K58,2,IF($J58<='02_Benchmarks'!$L58,0,IF($J58<='02_Benchmarks'!$M58,-2,-3)))),IF($J58>='02_Benchmarks'!$J58,3,IF($J58>'02_Benchmarks'!$K58,2,IF($J58>='02_Benchmarks'!$L58,0,IF($J58>='02_Benchmarks'!$M58,-2,-3))))))) | P58: =IF(COUNT($N58:$O58)+IF(ISNUMBER($K58),1,0)=0,"",MIN($N58:$O58,$K58)) | Q58: =IF($P58="","",INDEX('04_Tarifmodell'!$B$6:$B$12,$P58+4)) | R58: =IF($P58="","",INDEX('04_Tarifmodell'!$C$6:$C$12,$P58+4)) | S58: =IF(OR($I58="QUALITATIVE",$I58="MANUAL_HYBRID"),IF($K58="","Assurance-Score fehlt","Assurance-bewertet"),IF($I58="BENCHMARK",IF($W58<>"Aktiv",IF($K58="","Benchmark fehlt","Assurance-bewertet"),IF($J58="","Messwert fehlt",IF($P58="","Nicht bewertbar","Berechnet"))),IF(AND($J58="",$K58<>""),"Nur Assurance-Score",IF($J58="","Messwert fehlt",IF($P58="","Nicht bewertbar",IF($P58<=-2,"Kritische Wirkung / Prüfung","Berechnet")))))) -> Benchmark fehlt | T58: Top-10-Prozent, Mittelwert, 150 % und 250 % müssen aus einer dokumentierten Grundgesamtheit stammen. | U58: Top‑10%:+3; Mittel:0; >150%:‑2; >250%:‑3 | V58: ESRS E5, GRI 306, WEEE/VerpackG | W58: ='02_Benchmarks'!$P58 -> Offen – validierter Benchmark fehlt | X58: Teilbelegt – Benchmarkquelle fehlt | Y58: Hoch | Z58: Validierter Benchmark fehlt | AA58: Standort/Prozess/Aktivität; Bezugsgröße und relevante Umweltmedien | AB58: Primärdaten plus repräsentativer, versionierter Benchmarkdatensatz; Stichprobe und Population offenlegen | AC58: Messwert-Assurance und unabhängige Benchmark-Governance
A59: WOK-E-116 | B59: SDG 3 – Gesundheit | C59: 3.9 | D59: Lokalemissionen NOx/PM/SOx | E59: Lokalemissionen NOx/PM/SOx – Antikorruption | F59: Fälle/1.000 FTE | G59: lower_is_better | H59: R01 | I59: NUM_LOW | N59: =IF($J59="","",IF($J59<=0,3,IF($J59<=0.2,2,IF($J59<=0.5,0,IF($J59<=1,-2,-3))))) | O59: =IF($J59="","",IF(OR('02_Benchmarks'!$P59<>"Aktiv",COUNT('02_Benchmarks'!$J59:$M59)<4),"",IF($G59="lower_is_better",IF($J59<='02_Benchmarks'!$J59,3,IF($J59<'02_Benchmarks'!$K59,2,IF($J59<='02_Benchmarks'!$L59,0,IF($J59<='02_Benchmarks'!$M59,-2,-3)))),IF($J59>='02_Benchmarks'!$J59,3,IF($J59>'02_Benchmarks'!$K59,2,IF($J59>='02_Benchmarks'!$L59,0,IF($J59>='02_Benchmarks'!$M59,-2,-3))))))) | P59: =IF(COUNT($N59:$O59)+IF(ISNUMBER($K59),1,0)=0,"",MIN($N59:$O59,$K59)) | Q59: =IF($P59="","",INDEX('04_Tarifmodell'!$B$6:$B$12,$P59+4)) | R59: =IF($P59="","",INDEX('04_Tarifmodell'!$C$6:$C$12,$P59+4)) | S59: =IF(OR($I59="QUALITATIVE",$I59="MANUAL_HYBRID"),IF($K59="","Assurance-Score fehlt","Assurance-bewertet"),IF($I59="BENCHMARK",IF($W59<>"Aktiv",IF($K59="","Benchmark fehlt","Assurance-bewertet"),IF($J59="","Messwert fehlt",IF($P59="","Nicht bewertbar","Berechnet"))),IF(AND($J59="",$K59<>""),"Nur Assurance-Score",IF($J59="","Messwert fehlt",IF($P59="","Nicht bewertbar",IF($P59<=-2,"Kritische Wirkung / Prüfung","Berechnet")))))) -> Messwert fehlt | T59: Vollständige fünfstufige numerische Regel. | U59: 0:+3; ≤0,2:+2; ≤0,5:0; ≤1:‑2; >1:‑3 | V59: ESRS E1, GHG Protocol (Corporate/Scope 1–3), ISO 14064/14067 | W59: ='02_Benchmarks'!$P59 -> Optional – kein aktiver Benchmark | X59: Messgrundlage belegt; Schwellenkalibrierung offen | Y59: Mittel | Z59: Arbeitskalibrierung – fachlich zu validieren | AA59: Standort/Prozess/Aktivität; Bezugsgröße und relevante Umweltmedien | AB59: Primärdaten bevorzugt; Sekundärdaten nur transparent und versioniert; Methode und Systemgrenze dokumentieren | AC59: Limited Assurance; risikobasiert höhere Prüftiefe
A60: WOK-E-117 | B60: SDG 3 – Gesundheit | C60: 3.9 | D60: Lokalemissionen NOx/PM/SOx | E60: Lokalemissionen NOx/PM/SOx – Whistleblowing | F60: 0–1 | G60: higher_is_better | H60: R16 | I60: NUM_HIGH | N60: =IF($J60="","",IF($J60<0.4,-3,IF($J60<0.6,-2,IF($J60<0.75,0,IF($J60<0.9,2,3))))) | O60: =IF($J60="","",IF(OR('02_Benchmarks'!$P60<>"Aktiv",COUNT('02_Benchmarks'!$J60:$M60)<4),"",IF($G60="lower_is_better",IF($J60<='02_Benchmarks'!$J60,3,IF($J60<'02_Benchmarks'!$K60,2,IF($J60<='02_Benchmarks'!$L60,0,IF($J60<='02_Benchmarks'!$M60,-2,-3)))),IF($J60>='02_Benchmarks'!$J60,3,IF($J60>'02_Benchmarks'!$K60,2,IF($J60>='02_Benchmarks'!$L60,0,IF($J60>='02_Benchmarks'!$M60,-2,-3))))))) | P60: =IF(COUNT($N60:$O60)+IF(ISNUMBER($K60),1,0)=0,"",MIN($N60:$O60,$K60)) | Q60: =IF($P60="","",INDEX('04_Tarifmodell'!$B$6:$B$12,$P60+4)) | R60: =IF($P60="","",INDEX('04_Tarifmodell'!$C$6:$C$12,$P60+4)) | S60: =IF(OR($I60="QUALITATIVE",$I60="MANUAL_HYBRID"),IF($K60="","Assurance-Score fehlt","Assurance-bewertet"),IF($I60="BENCHMARK",IF($W60<>"Aktiv",IF($K60="","Benchmark fehlt","Assurance-bewertet"),IF($J60="","Messwert fehlt",IF($P60="","Nicht bewertbar","Berechnet"))),IF(AND($J60="",$K60<>""),"Nur Assurance-Score",IF($J60="","Messwert fehlt",IF($P60="","Nicht bewertbar",IF($P60<=-2,"Kritische Wirkung / Prüfung","Berechnet")))))) -> Messwert fehlt | T60: Vollständige fünfstufige numerische Regel. | U60: ≥0,9:+3; 0,75–0,89:+2; 0,6–0,74:0; 0,4–0,59:‑2; <0,4:‑3 | V60: ESRS E1, GHG Protocol (Corporate/Scope 1–3), ISO 14064/14067 | W60: ='02_Benchmarks'!$P60 -> Optional – kein aktiver Benchmark | X60: Messgrundlage belegt; Schwellenkalibrierung offen | Y60: Mittel | Z60: Arbeitskalibrierung – fachlich zu validieren | AA60: Standort/Prozess/Aktivität; Bezugsgröße und relevante Umweltmedien | AB60: Primärdaten bevorzugt; Sekundärdaten nur transparent und versioniert; Methode und Systemgrenze dokumentieren | AC60: Limited Assurance; risikobasiert höhere Prüftiefe
A61: WOK-E-118 | B61: SDG 3 – Gesundheit | C61: 3.9 | D61: Lokalemissionen NOx/PM/SOx | E61: Lokalemissionen NOx/PM/SOx – Steuertransparenz | F61: 0–1 | G61: higher_is_better | H61: R08 | I61: QUALITATIVE | N61: ="" | O61: =IF($J61="","",IF(OR('02_Benchmarks'!$P61<>"Aktiv",COUNT('02_Benchmarks'!$J61:$M61)<4),"",IF($G61="lower_is_better",IF($J61<='02_Benchmarks'!$J61,3,IF($J61<'02_Benchmarks'!$K61,2,IF($J61<='02_Benchmarks'!$L61,0,IF($J61<='02_Benchmarks'!$M61,-2,-3)))),IF($J61>='02_Benchmarks'!$J61,3,IF($J61>'02_Benchmarks'!$K61,2,IF($J61>='02_Benchmarks'!$L61,0,IF($J61>='02_Benchmarks'!$M61,-2,-3))))))) | P61: =IF(COUNT($N61:$O61)+IF(ISNUMBER($K61),1,0)=0,"",MIN($N61:$O61,$K61)) | Q61: =IF($P61="","",INDEX('04_Tarifmodell'!$B$6:$B$12,$P61+4)) | R61: =IF($P61="","",INDEX('04_Tarifmodell'!$C$6:$C$12,$P61+4)) | S61: =IF(OR($I61="QUALITATIVE",$I61="MANUAL_HYBRID"),IF($K61="","Assurance-Score fehlt","Assurance-bewertet"),IF($I61="BENCHMARK",IF($W61<>"Aktiv",IF($K61="","Benchmark fehlt","Assurance-bewertet"),IF($J61="","Messwert fehlt",IF($P61="","Nicht bewertbar","Berechnet"))),IF(AND($J61="",$K61<>""),"Nur Assurance-Score",IF($J61="","Messwert fehlt",IF($P61="","Nicht bewertbar",IF($P61<=-2,"Kritische Wirkung / Prüfung","Berechnet")))))) -> Assurance-Score fehlt | T61: Die Kategorie −3 fehlt; Vollständigkeit und Wirksamkeit sind feldspezifisch zu definieren. | U61: vollständig:+3; teilweise:+2; minimal:0; schlecht:‑2 | V61: ESRS E1, GHG Protocol (Corporate/Scope 1–3), ISO 14064/14067 | W61: ='02_Benchmarks'!$P61 -> Optional – kein aktiver Benchmark | X61: Messgrundlage belegt; Schwellenkalibrierung offen | Y61: Hoch | Z61: Assurance und Kriterienkatalog erforderlich | AA61: Standort/Prozess/Aktivität; Bezugsgröße und relevante Umweltmedien | AB61: Dokumentierter Kriterienkatalog; nachvollziehbare Evidenz; DQR A/B bevorzugt | AC61: Unabhängige Fachprüfung/Limited Assurance; bei roten Linien Reasonable Assurance
A62: WOK-S-119 | B62: SDG 3 – Gesundheit | C62: 3.8 | D62: Arbeits- & Gesundheitsschutz | E62: Arbeits- & Gesundheitsschutz – Living Wage | F62: % Beschäftigte | G62: higher_is_better | H62: R27 | I62: NUM_HIGH | N62: =IF($J62="","",IF($J62<40,-3,IF($J62<60,-2,IF($J62<80,0,IF($J62<95,2,3))))) | O62: =IF($J62="","",IF(OR('02_Benchmarks'!$P62<>"Aktiv",COUNT('02_Benchmarks'!$J62:$M62)<4),"",IF($G62="lower_is_better",IF($J62<='02_Benchmarks'!$J62,3,IF($J62<'02_Benchmarks'!$K62,2,IF($J62<='02_Benchmarks'!$L62,0,IF($J62<='02_Benchmarks'!$M62,-2,-3)))),IF($J62>='02_Benchmarks'!$J62,3,IF($J62>'02_Benchmarks'!$K62,2,IF($J62>='02_Benchmarks'!$L62,0,IF($J62>='02_Benchmarks'!$M62,-2,-3))))))) | P62: =IF(COUNT($N62:$O62)+IF(ISNUMBER($K62),1,0)=0,"",MIN($N62:$O62,$K62)) | Q62: =IF($P62="","",INDEX('04_Tarifmodell'!$B$6:$B$12,$P62+4)) | R62: =IF($P62="","",INDEX('04_Tarifmodell'!$C$6:$C$12,$P62+4)) | S62: =IF(OR($I62="QUALITATIVE",$I62="MANUAL_HYBRID"),IF($K62="","Assurance-Score fehlt","Assurance-bewertet"),IF($I62="BENCHMARK",IF($W62<>"Aktiv",IF($K62="","Benchmark fehlt","Assurance-bewertet"),IF($J62="","Messwert fehlt",IF($P62="","Nicht bewertbar","Berechnet"))),IF(AND($J62="",$K62<>""),"Nur Assurance-Score",IF($J62="","Messwert fehlt",IF($P62="","Nicht bewertbar",IF($P62<=-2,"Kritische Wirkung / Prüfung","Berechnet")))))) -> Messwert fehlt | T62: Vollständige fünfstufige numerische Regel. | U62: ≥95:+3; 80–94:+2; 60–79:0; 40–59:‑2; <40:‑3 | V62: ESRS S1, GRI 401/403/405/406, ILO | W62: ='02_Benchmarks'!$P62 -> Optional – kein aktiver Benchmark | X62: Messgrundlage belegt; Schwellenkalibrierung offen | Y62: Mittel | Z62: Arbeitskalibrierung – fachlich zu validieren | AA62: Eigene Belegschaft/Organisation; FTE, Beschäftigtengruppe und Zeitraum | AB62: Primärdaten bevorzugt; Sekundärdaten nur transparent und versioniert; Methode und Systemgrenze dokumentieren | AC62: Limited Assurance; risikobasiert höhere Prüftiefe
A63: WOK-S-120 | B63: SDG 3 – Gesundheit | C63: 3.8 | D63: Arbeits- & Gesundheitsschutz | E63: Arbeits- & Gesundheitsschutz – Tarifbindung | F63: % | G63: higher_is_better | H63: R26 | I63: NUM_HIGH | N63: =IF($J63="","",IF($J63<30,-3,IF($J63<50,-2,IF($J63<70,0,IF($J63<90,2,3))))) | O63: =IF($J63="","",IF(OR('02_Benchmarks'!$P63<>"Aktiv",COUNT('02_Benchmarks'!$J63:$M63)<4),"",IF($G63="lower_is_better",IF($J63<='02_Benchmarks'!$J63,3,IF($J63<'02_Benchmarks'!$K63,2,IF($J63<='02_Benchmarks'!$L63,0,IF($J63<='02_Benchmarks'!$M63,-2,-3)))),IF($J63>='02_Benchmarks'!$J63,3,IF($J63>'02_Benchmarks'!$K63,2,IF($J63>='02_Benchmarks'!$L63,0,IF($J63>='02_Benchmarks'!$M63,-2,-3))))))) | P63: =IF(COUNT($N63:$O63)+IF(ISNUMBER($K63),1,0)=0,"",MIN($N63:$O63,$K63)) | Q63: =IF($P63="","",INDEX('04_Tarifmodell'!$B$6:$B$12,$P63+4)) | R63: =IF($P63="","",INDEX('04_Tarifmodell'!$C$6:$C$12,$P63+4)) | S63: =IF(OR($I63="QUALITATIVE",$I63="MANUAL_HYBRID"),IF($K63="","Assurance-Score fehlt","Assurance-bewertet"),IF($I63="BENCHMARK",IF($W63<>"Aktiv",IF($K63="","Benchmark fehlt","Assurance-bewertet"),IF($J63="","Messwert fehlt",IF($P63="","Nicht bewertbar","Berechnet"))),IF(AND($J63="",$K63<>""),"Nur Assurance-Score",IF($J63="","Messwert fehlt",IF($P63="","Nicht bewertbar",IF($P63<=-2,"Kritische Wirkung / Prüfung","Berechnet")))))) -> Messwert fehlt | T63: Vollständige fünfstufige numerische Regel. | U63: ≥90:+3; 70–89:+2; 50–69:0; 30–49:‑2; <30:‑3 | V63: ESRS S1, GRI 401/403/405/406, ILO | W63: ='02_Benchmarks'!$P63 -> Optional – kein aktiver Benchmark | X63: Messgrundlage belegt; Schwellenkalibrierung offen | Y63: Mittel | Z63: Arbeitskalibrierung – fachlich zu validieren | AA63: Eigene Belegschaft/Organisation; FTE, Beschäftigtengruppe und Zeitraum | AB63: Primärdaten bevorzugt; Sekundärdaten nur transparent und versioniert; Methode und Systemgrenze dokumentieren | AC63: Limited Assurance; risikobasiert höhere Prüftiefe
A64: WOK-S-121 | B64: SDG 3 – Gesundheit | C64: 3.8 | D64: Arbeits- & Gesundheitsschutz | E64: Arbeits- & Gesundheitsschutz – LTIFR | F64: Unfälle/Mio Std. | G64: lower_is_better | H64: R02 | I64: NUM_LOW | N64: =IF($J64="","",IF($J64<=0,3,IF($J64<=1,2,IF($J64<=3,0,IF($J64<=5,-2,-3))))) | O64: =IF($J64="","",IF(OR('02_Benchmarks'!$P64<>"Aktiv",COUNT('02_Benchmarks'!$J64:$M64)<4),"",IF($G64="lower_is_better",IF($J64<='02_Benchmarks'!$J64,3,IF($J64<'02_Benchmarks'!$K64,2,IF($J64<='02_Benchmarks'!$L64,0,IF($J64<='02_Benchmarks'!$M64,-2,-3)))),IF($J64>='02_Benchmarks'!$J64,3,IF($J64>'02_Benchmarks'!$K64,2,IF($J64>='02_Benchmarks'!$L64,0,IF($J64>='02_Benchmarks'!$M64,-2,-3))))))) | P64: =IF(COUNT($N64:$O64)+IF(ISNUMBER($K64),1,0)=0,"",MIN($N64:$O64,$K64)) | Q64: =IF($P64="","",INDEX('04_Tarifmodell'!$B$6:$B$12,$P64+4)) | R64: =IF($P64="","",INDEX('04_Tarifmodell'!$C$6:$C$12,$P64+4)) | S64: =IF(OR($I64="QUALITATIVE",$I64="MANUAL_HYBRID"),IF($K64="","Assurance-Score fehlt","Assurance-bewertet"),IF($I64="BENCHMARK",IF($W64<>"Aktiv",IF($K64="","Benchmark fehlt","Assurance-bewertet"),IF($J64="","Messwert fehlt",IF($P64="","Nicht bewertbar","Berechnet"))),IF(AND($J64="",$K64<>""),"Nur Assurance-Score",IF($J64="","Messwert fehlt",IF($P64="","Nicht bewertbar",IF($P64<=-2,"Kritische Wirkung / Prüfung","Berechnet")))))) -> Messwert fehlt | T64: Vollständige fünfstufige numerische Regel. | U64: 0:+3; ≤1:+2; ≤3:0; ≤5:‑2; >5:‑3 | V64: ESRS S1, GRI 401/403/405/406, ILO | W64: ='02_Benchmarks'!$P64 -> Optional – kein aktiver Benchmark | X64: Messgrundlage belegt; Schwellenkalibrierung offen | Y64: Mittel | Z64: Arbeitskalibrierung – fachlich zu validieren | AA64: Eigene Belegschaft/Organisation; FTE, Beschäftigtengruppe und Zeitraum | AB64: Primärdaten bevorzugt; Sekundärdaten nur transparent und versioniert; Methode und Systemgrenze dokumentieren | AC64: Limited Assurance; risikobasiert höhere Prüftiefe
A65: WOK-P-104 | B65: SDG 3 – Gesundheit | C65: 3.9 | D65: Produktsicherheit & Rückrufe | E65: Produktsicherheit & Rückrufe – PCF | F65: kg CO₂e/Einheit | G65: lower_is_better | H65: R07 | I65: BENCHMARK | N65: ="" | O65: =IF($J65="","",IF(OR('02_Benchmarks'!$P65<>"Aktiv",COUNT('02_Benchmarks'!$J65:$M65)<4),"",IF($G65="lower_is_better",IF($J65<='02_Benchmarks'!$J65,3,IF($J65<'02_Benchmarks'!$K65,2,IF($J65<='02_Benchmarks'!$L65,0,IF($J65<='02_Benchmarks'!$M65,-2,-3)))),IF($J65>='02_Benchmarks'!$J65,3,IF($J65>'02_Benchmarks'!$K65,2,IF($J65>='02_Benchmarks'!$L65,0,IF($J65>='02_Benchmarks'!$M65,-2,-3))))))) | P65: =IF(COUNT($N65:$O65)+IF(ISNUMBER($K65),1,0)=0,"",MIN($N65:$O65,$K65)) | Q65: =IF($P65="","",INDEX('04_Tarifmodell'!$B$6:$B$12,$P65+4)) | R65: =IF($P65="","",INDEX('04_Tarifmodell'!$C$6:$C$12,$P65+4)) | S65: =IF(OR($I65="QUALITATIVE",$I65="MANUAL_HYBRID"),IF($K65="","Assurance-Score fehlt","Assurance-bewertet"),IF($I65="BENCHMARK",IF($W65<>"Aktiv",IF($K65="","Benchmark fehlt","Assurance-bewertet"),IF($J65="","Messwert fehlt",IF($P65="","Nicht bewertbar","Berechnet"))),IF(AND($J65="",$K65<>""),"Nur Assurance-Score",IF($J65="","Messwert fehlt",IF($P65="","Nicht bewertbar",IF($P65<=-2,"Kritische Wirkung / Prüfung","Berechnet")))))) -> Benchmark fehlt | T65: Produktspezifische Referenzpopulation erforderlich. | U65: Top‑10%:+3; ±Benchmark:0; >150%:‑2; >250%:‑3 | V65: ISO 14067/14040/44 (LCA/PCF), PEF/EF 3.1, EU Reparierbarkeitsindex | W65: ='02_Benchmarks'!$P65 -> Offen – validierter Benchmark fehlt | X65: Teilbelegt – Benchmarkquelle fehlt | Y65: Hoch | Z65: Validierter Benchmark fehlt | AA65: Produkt/Funktionseinheit; Lebenszyklusgrenze mindestens cradle-to-gate, bei Nutzungs-/End-of-Life-Relevanz cradle-to-grave | AB65: Primärdaten plus repräsentativer, versionierter Benchmarkdatensatz; Stichprobe und Population offenlegen | AC65: Messwert-Assurance und unabhängige Benchmark-Governance
A66: WOK-P-105 | B66: SDG 3 – Gesundheit | C66: 3.9 | D66: Produktsicherheit & Rückrufe | E66: Produktsicherheit & Rückrufe – Reparierbarkeit | F66: Score 0–10 | G66: higher_is_better | H66: R24 | I66: NUM_HIGH | N66: =IF($J66="","",IF($J66<2,-3,IF($J66<4,-2,IF($J66<6,0,IF($J66<8,2,3))))) | O66: =IF($J66="","",IF(OR('02_Benchmarks'!$P66<>"Aktiv",COUNT('02_Benchmarks'!$J66:$M66)<4),"",IF($G66="lower_is_better",IF($J66<='02_Benchmarks'!$J66,3,IF($J66<'02_Benchmarks'!$K66,2,IF($J66<='02_Benchmarks'!$L66,0,IF($J66<='02_Benchmarks'!$M66,-2,-3)))),IF($J66>='02_Benchmarks'!$J66,3,IF($J66>'02_Benchmarks'!$K66,2,IF($J66>='02_Benchmarks'!$L66,0,IF($J66>='02_Benchmarks'!$M66,-2,-3))))))) | P66: =IF(COUNT($N66:$O66)+IF(ISNUMBER($K66),1,0)=0,"",MIN($N66:$O66,$K66)) | Q66: =IF($P66="","",INDEX('04_Tarifmodell'!$B$6:$B$12,$P66+4)) | R66: =IF($P66="","",INDEX('04_Tarifmodell'!$C$6:$C$12,$P66+4)) | S66: =IF(OR($I66="QUALITATIVE",$I66="MANUAL_HYBRID"),IF($K66="","Assurance-Score fehlt","Assurance-bewertet"),IF($I66="BENCHMARK",IF($W66<>"Aktiv",IF($K66="","Benchmark fehlt","Assurance-bewertet"),IF($J66="","Messwert fehlt",IF($P66="","Nicht bewertbar","Berechnet"))),IF(AND($J66="",$K66<>""),"Nur Assurance-Score",IF($J66="","Messwert fehlt",IF($P66="","Nicht bewertbar",IF($P66<=-2,"Kritische Wirkung / Prüfung","Berechnet")))))) -> Messwert fehlt | T66: Indexsystem, Produktgruppe und Rechtsstand festlegen. Französischer Index und EU-Score sind nicht pauschal austauschbar. | U66: ≥8:+3; 6–7,9:+2; 4–5,9:0; 2–3,9:‑2; <2:‑3 | V66: ISO 14067/14040/44 (LCA/PCF), PEF/EF 3.1, EU Reparierbarkeitsindex | W66: ='02_Benchmarks'!$P66 -> Optional – kein aktiver Benchmark | X66: Teilbelegt – produktspezifisch zu validieren | Y66: Hoch | Z66: Indexsystem und Produktgruppe müssen ausgewiesen werden | AA66: Produkt/Funktionseinheit; Lebenszyklusgrenze mindestens cradle-to-gate, bei Nutzungs-/End-of-Life-Relevanz cradle-to-grave | AB66: Primärdaten oder qualitätsgesicherte Sekundärdaten; Methode, Zeitraum und Systemgrenze dokumentieren | AC66: Limited Assurance; bei materieller Steuerwirkung risikobasiert vertiefen
A67: WOK-P-106 | B67: SDG 3 – Gesundheit | C67: 3.9 | D67: Produktsicherheit & Rückrufe | E67: Produktsicherheit & Rückrufe – Rücknahme/Recycling | F67: % | G67: higher_is_better | H67: R22 | I67: NUM_HIGH | N67: =IF($J67="","",IF($J67<15,-3,IF($J67<30,-2,IF($J67<50,0,IF($J67<70,2,3))))) | O67: =IF($J67="","",IF(OR('02_Benchmarks'!$P67<>"Aktiv",COUNT('02_Benchmarks'!$J67:$M67)<4),"",IF($G67="lower_is_better",IF($J67<='02_Benchmarks'!$J67,3,IF($J67<'02_Benchmarks'!$K67,2,IF($J67<='02_Benchmarks'!$L67,0,IF($J67<='02_Benchmarks'!$M67,-2,-3)))),IF($J67>='02_Benchmarks'!$J67,3,IF($J67>'02_Benchmarks'!$K67,2,IF($J67>='02_Benchmarks'!$L67,0,IF($J67>='02_Benchmarks'!$M67,-2,-3))))))) | P67: =IF(COUNT($N67:$O67)+IF(ISNUMBER($K67),1,0)=0,"",MIN($N67:$O67,$K67)) | Q67: =IF($P67="","",INDEX('04_Tarifmodell'!$B$6:$B$12,$P67+4)) | R67: =IF($P67="","",INDEX('04_Tarifmodell'!$C$6:$C$12,$P67+4)) | S67: =IF(OR($I67="QUALITATIVE",$I67="MANUAL_HYBRID"),IF($K67="","Assurance-Score fehlt","Assurance-bewertet"),IF($I67="BENCHMARK",IF($W67<>"Aktiv",IF($K67="","Benchmark fehlt","Assurance-bewertet"),IF($J67="","Messwert fehlt",IF($P67="","Nicht bewertbar","Berechnet"))),IF(AND($J67="",$K67<>""),"Nur Assurance-Score",IF($J67="","Messwert fehlt",IF($P67="","Nicht bewertbar",IF($P67<=-2,"Kritische Wirkung / Prüfung","Berechnet")))))) -> Messwert fehlt | T67: Vollständige fünfstufige numerische Regel. | U67: ≥70:+3; 50–69:+2; 30–49:0; 15–29:‑2; <15:‑3 | V67: ESRS E5, GRI 306, WEEE/VerpackG | W67: ='02_Benchmarks'!$P67 -> Optional – kein aktiver Benchmark | X67: Messgrundlage belegt; Schwellenkalibrierung offen | Y67: Mittel | Z67: Arbeitskalibrierung – fachlich zu validieren | AA67: Produkt/Funktionseinheit; Lebenszyklusgrenze mindestens cradle-to-gate, bei Nutzungs-/End-of-Life-Relevanz cradle-to-grave | AB67: Primärdaten bevorzugt; Sekundärdaten nur transparent und versioniert; Methode und Systemgrenze dokumentieren | AC67: Limited Assurance; risikobasiert höhere Prüftiefe
A68: WOK-G-110 | B68: SDG 3 – Gesundheit | C68: 3.d | D68: Datenschutz (Gesundheitsdaten) | E68: Datenschutz (Gesundheitsdaten) – Datenschutzvorfälle | F68: Fälle/Mio | G68: lower_is_better | H68: R02 | I68: NUM_LOW | N68: =IF($J68="","",IF($J68<=0,3,IF($J68<=1,2,IF($J68<=3,0,IF($J68<=5,-2,-3))))) | O68: =IF($J68="","",IF(OR('02_Benchmarks'!$P68<>"Aktiv",COUNT('02_Benchmarks'!$J68:$M68)<4),"",IF($G68="lower_is_better",IF($J68<='02_Benchmarks'!$J68,3,IF($J68<'02_Benchmarks'!$K68,2,IF($J68<='02_Benchmarks'!$L68,0,IF($J68<='02_Benchmarks'!$M68,-2,-3)))),IF($J68>='02_Benchmarks'!$J68,3,IF($J68>'02_Benchmarks'!$K68,2,IF($J68>='02_Benchmarks'!$L68,0,IF($J68>='02_Benchmarks'!$M68,-2,-3))))))) | P68: =IF(COUNT($N68:$O68)+IF(ISNUMBER($K68),1,0)=0,"",MIN($N68:$O68,$K68)) | Q68: =IF($P68="","",INDEX('04_Tarifmodell'!$B$6:$B$12,$P68+4)) | R68: =IF($P68="","",INDEX('04_Tarifmodell'!$C$6:$C$12,$P68+4)) | S68: =IF(OR($I68="QUALITATIVE",$I68="MANUAL_HYBRID"),IF($K68="","Assurance-Score fehlt","Assurance-bewertet"),IF($I68="BENCHMARK",IF($W68<>"Aktiv",IF($K68="","Benchmark fehlt","Assurance-bewertet"),IF($J68="","Messwert fehlt",IF($P68="","Nicht bewertbar","Berechnet"))),IF(AND($J68="",$K68<>""),"Nur Assurance-Score",IF($J68="","Messwert fehlt",IF($P68="","Nicht bewertbar",IF($P68<=-2,"Kritische Wirkung / Prüfung","Berechnet")))))) -> Messwert fehlt | T68: Vollständige fünfstufige numerische Regel. | U68: 0:+3; ≤1:+2; ≤3:0; ≤5:‑2; >5:‑3 | V68: ISO/IEC 27001 & 27701, NIS2 | W68: ='02_Benchmarks'!$P68 -> Optional – kein aktiver Benchmark | X68: Messgrundlage belegt; Schwellenkalibrierung offen | Y68: Mittel | Z68: Arbeitskalibrierung – fachlich zu validieren | AA68: Organisation/Governance; konsolidierter Kreis und relevante Rechtseinheiten | AB68: Primärdaten bevorzugt; Sekundärdaten nur transparent und versioniert; Methode und Systemgrenze dokumentieren | AC68: Limited Assurance; risikobasiert höhere Prüftiefe
A69: WOK-G-111 | B69: SDG 3 – Gesundheit | C69: 3.d | D69: Datenschutz (Gesundheitsdaten) | E69: Datenschutz (Gesundheitsdaten) – Privacy by Design | F69: % | G69: higher_is_better | H69: R25 | I69: NUM_HIGH | N69: =IF($J69="","",IF($J69<30,-3,IF($J69<50,-2,IF($J69<70,0,IF($J69<90,2,3))))) | O69: =IF($J69="","",IF(OR('02_Benchmarks'!$P69<>"Aktiv",COUNT('02_Benchmarks'!$J69:$M69)<4),"",IF($G69="lower_is_better",IF($J69<='02_Benchmarks'!$J69,3,IF($J69<'02_Benchmarks'!$K69,2,IF($J69<='02_Benchmarks'!$L69,0,IF($J69<='02_Benchmarks'!$M69,-2,-3)))),IF($J69>='02_Benchmarks'!$J69,3,IF($J69>'02_Benchmarks'!$K69,2,IF($J69>='02_Benchmarks'!$L69,0,IF($J69>='02_Benchmarks'!$M69,-2,-3))))))) | P69: =IF(COUNT($N69:$O69)+IF(ISNUMBER($K69),1,0)=0,"",MIN($N69:$O69,$K69)) | Q69: =IF($P69="","",INDEX('04_Tarifmodell'!$B$6:$B$12,$P69+4)) | R69: =IF($P69="","",INDEX('04_Tarifmodell'!$C$6:$C$12,$P69+4)) | S69: =IF(OR($I69="QUALITATIVE",$I69="MANUAL_HYBRID"),IF($K69="","Assurance-Score fehlt","Assurance-bewertet"),IF($I69="BENCHMARK",IF($W69<>"Aktiv",IF($K69="","Benchmark fehlt","Assurance-bewertet"),IF($J69="","Messwert fehlt",IF($P69="","Nicht bewertbar","Berechnet"))),IF(AND($J69="",$K69<>""),"Nur Assurance-Score",IF($J69="","Messwert fehlt",IF($P69="","Nicht bewertbar",IF($P69<=-2,"Kritische Wirkung / Prüfung","Berechnet")))))) -> Messwert fehlt | T69: Vollständige fünfstufige Prozentregel. | U69: ≥90%:+3; 70–89%:+2; 50–69%:0; 30–49%:‑2; <30%:‑3 | V69: ISO/IEC 27001 & 27701, NIS2 | W69: ='02_Benchmarks'!$P69 -> Optional – kein aktiver Benchmark | X69: Messgrundlage belegt; Schwellenkalibrierung offen | Y69: Mittel | Z69: Arbeitskalibrierung – fachlich zu validieren | AA69: Organisation/Governance; konsolidierter Kreis und relevante Rechtseinheiten | AB69: Primärdaten bevorzugt; Sekundärdaten nur transparent und versioniert; Methode und Systemgrenze dokumentieren | AC69: Limited Assurance; risikobasiert höhere Prüftiefe
A70: WOK-G-112 | B70: SDG 3 – Gesundheit | C70: 3.d | D70: Datenschutz (Gesundheitsdaten) | E70: Datenschutz (Gesundheitsdaten) – Security Reifegrad | F70: 0–1 | G70: higher_is_better | H70: R16 | I70: NUM_HIGH | N70: =IF($J70="","",IF($J70<0.4,-3,IF($J70<0.6,-2,IF($J70<0.75,0,IF($J70<0.9,2,3))))) | O70: =IF($J70="","",IF(OR('02_Benchmarks'!$P70<>"Aktiv",COUNT('02_Benchmarks'!$J70:$M70)<4),"",IF($G70="lower_is_better",IF($J70<='02_Benchmarks'!$J70,3,IF($J70<'02_Benchmarks'!$K70,2,IF($J70<='02_Benchmarks'!$L70,0,IF($J70<='02_Benchmarks'!$M70,-2,-3)))),IF($J70>='02_Benchmarks'!$J70,3,IF($J70>'02_Benchmarks'!$K70,2,IF($J70>='02_Benchmarks'!$L70,0,IF($J70>='02_Benchmarks'!$M70,-2,-3))))))) | P70: =IF(COUNT($N70:$O70)+IF(ISNUMBER($K70),1,0)=0,"",MIN($N70:$O70,$K70)) | Q70: =IF($P70="","",INDEX('04_Tarifmodell'!$B$6:$B$12,$P70+4)) | R70: =IF($P70="","",INDEX('04_Tarifmodell'!$C$6:$C$12,$P70+4)) | S70: =IF(OR($I70="QUALITATIVE",$I70="MANUAL_HYBRID"),IF($K70="","Assurance-Score fehlt","Assurance-bewertet"),IF($I70="BENCHMARK",IF($W70<>"Aktiv",IF($K70="","Benchmark fehlt","Assurance-bewertet"),IF($J70="","Messwert fehlt",IF($P70="","Nicht bewertbar","Berechnet"))),IF(AND($J70="",$K70<>""),"Nur Assurance-Score",IF($J70="","Messwert fehlt",IF($P70="","Nicht bewertbar",IF($P70<=-2,"Kritische Wirkung / Prüfung","Berechnet")))))) -> Messwert fehlt | T70: Vollständige fünfstufige numerische Regel. | U70: ≥0,9:+3; 0,75–0,89:+2; 0,6–0,74:0; 0,4–0,59:‑2; <0,4:‑3 | V70: ISO/IEC 27001 & 27701, NIS2 | W70: ='02_Benchmarks'!$P70 -> Optional – kein aktiver Benchmark | X70: Messgrundlage belegt; Schwellenkalibrierung offen | Y70: Mittel | Z70: Arbeitskalibrierung – fachlich zu validieren | AA70: Organisation/Governance; konsolidierter Kreis und relevante Rechtseinheiten | AB70: Primärdaten bevorzugt; Sekundärdaten nur transparent und versioniert; Methode und Systemgrenze dokumentieren | AC70: Limited Assurance; risikobasiert höhere Prüftiefe
A71: WOK-RE-101 | B71: SDG 3 – Gesundheit | C71: 3.9 | D71: Gesunde Gebäude (IAQ) | E71: Gesunde Gebäude (IAQ) – Betriebsenergie | F71: kWh/m²a | G71: lower_is_better | H71: R05 | I71: BENCHMARK | N71: ="" | O71: =IF($J71="","",IF(OR('02_Benchmarks'!$P71<>"Aktiv",COUNT('02_Benchmarks'!$J71:$M71)<4),"",IF($G71="lower_is_better",IF($J71<='02_Benchmarks'!$J71,3,IF($J71<'02_Benchmarks'!$K71,2,IF($J71<='02_Benchmarks'!$L71,0,IF($J71<='02_Benchmarks'!$M71,-2,-3)))),IF($J71>='02_Benchmarks'!$J71,3,IF($J71>'02_Benchmarks'!$K71,2,IF($J71>='02_Benchmarks'!$L71,0,IF($J71>='02_Benchmarks'!$M71,-2,-3))))))) | P71: =IF(COUNT($N71:$O71)+IF(ISNUMBER($K71),1,0)=0,"",MIN($N71:$O71,$K71)) | Q71: =IF($P71="","",INDEX('04_Tarifmodell'!$B$6:$B$12,$P71+4)) | R71: =IF($P71="","",INDEX('04_Tarifmodell'!$C$6:$C$12,$P71+4)) | S71: =IF(OR($I71="QUALITATIVE",$I71="MANUAL_HYBRID"),IF($K71="","Assurance-Score fehlt","Assurance-bewertet"),IF($I71="BENCHMARK",IF($W71<>"Aktiv",IF($K71="","Benchmark fehlt","Assurance-bewertet"),IF($J71="","Messwert fehlt",IF($P71="","Nicht bewertbar","Berechnet"))),IF(AND($J71="",$K71<>""),"Nur Assurance-Score",IF($J71="","Messwert fehlt",IF($P71="","Nicht bewertbar",IF($P71<=-2,"Kritische Wirkung / Prüfung","Berechnet")))))) -> Benchmark fehlt | T71: Die Grenze >+60 % ist derzeit nicht eindeutig in −2/−3 aufgelöst. | U71: Top 15%:+3; +15–30%:+2; +31–60%:0; >+60%:‑2/‑3 | V71: ESRS E1, ISO 50001 (EnMS), ISO/IEC 30134‑2 (PUE), EU EPBD | W71: ='02_Benchmarks'!$P71 -> Offen – validierter Benchmark fehlt | X71: Teilbelegt – Benchmarkquelle fehlt | Y71: Hoch | Z71: Validierter Benchmark fehlt | AA71: Gebäude/Standort; Betrieb plus relevante Lebenszyklusmodule | AB71: Primärdaten plus repräsentativer, versionierter Benchmarkdatensatz; Stichprobe und Population offenlegen | AC71: Messwert-Assurance und unabhängige Benchmark-Governance
A72: WOK-RE-102 | B72: SDG 3 – Gesundheit | C72: 3.9 | D72: Gesunde Gebäude (IAQ) | E72: Gesunde Gebäude (IAQ) – Graue Emissionen | F72: kg CO₂e/m² | G72: lower_is_better | H72: R06 | I72: BENCHMARK | N72: ="" | O72: =IF($J72="","",IF(OR('02_Benchmarks'!$P72<>"Aktiv",COUNT('02_Benchmarks'!$J72:$M72)<4),"",IF($G72="lower_is_better",IF($J72<='02_Benchmarks'!$J72,3,IF($J72<'02_Benchmarks'!$K72,2,IF($J72<='02_Benchmarks'!$L72,0,IF($J72<='02_Benchmarks'!$M72,-2,-3)))),IF($J72>='02_Benchmarks'!$J72,3,IF($J72>'02_Benchmarks'!$K72,2,IF($J72>='02_Benchmarks'!$L72,0,IF($J72>='02_Benchmarks'!$M72,-2,-3))))))) | P72: =IF(COUNT($N72:$O72)+IF(ISNUMBER($K72),1,0)=0,"",MIN($N72:$O72,$K72)) | Q72: =IF($P72="","",INDEX('04_Tarifmodell'!$B$6:$B$12,$P72+4)) | R72: =IF($P72="","",INDEX('04_Tarifmodell'!$C$6:$C$12,$P72+4)) | S72: =IF(OR($I72="QUALITATIVE",$I72="MANUAL_HYBRID"),IF($K72="","Assurance-Score fehlt","Assurance-bewertet"),IF($I72="BENCHMARK",IF($W72<>"Aktiv",IF($K72="","Benchmark fehlt","Assurance-bewertet"),IF($J72="","Messwert fehlt",IF($P72="","Nicht bewertbar","Berechnet"))),IF(AND($J72="",$K72<>""),"Nur Assurance-Score",IF($J72="","Messwert fehlt",IF($P72="","Nicht bewertbar",IF($P72<=-2,"Kritische Wirkung / Prüfung","Berechnet")))))) -> Benchmark fehlt | T72: Top-10-Prozent, Mittelwert, 150 % und 250 % müssen aus einer dokumentierten Grundgesamtheit stammen. | U72: Top‑10%:+3; Mittel:0; >150%:‑2; >250%:‑3 | V72: ESRS E1, GHG Protocol (Corporate/Scope 1–3), ISO 14064/14067 | W72: ='02_Benchmarks'!$P72 -> Offen – validierter Benchmark fehlt | X72: Teilbelegt – Benchmarkquelle fehlt | Y72: Hoch | Z72: Validierter Benchmark fehlt | AA72: Gebäude/Standort; Betrieb plus relevante Lebenszyklusmodule | AB72: Primärdaten plus repräsentativer, versionierter Benchmarkdatensatz; Stichprobe und Population offenlegen | AC72: Messwert-Assurance und unabhängige Benchmark-Governance
A73: WOK-RE-103 | B73: SDG 3 – Gesundheit | C73: 3.9 | D73: Gesunde Gebäude (IAQ) | E73: Gesunde Gebäude (IAQ) – ÖPNV‑Erreichbarkeit | F73: 0–1 | G73: higher_is_better | H73: R14 | I73: NUM_HIGH | N73: =IF($J73="","",IF($J73<0.2,-3,IF($J73<0.4,-2,IF($J73<0.6,0,IF($J73<0.8,2,3))))) | O73: =IF($J73="","",IF(OR('02_Benchmarks'!$P73<>"Aktiv",COUNT('02_Benchmarks'!$J73:$M73)<4),"",IF($G73="lower_is_better",IF($J73<='02_Benchmarks'!$J73,3,IF($J73<'02_Benchmarks'!$K73,2,IF($J73<='02_Benchmarks'!$L73,0,IF($J73<='02_Benchmarks'!$M73,-2,-3)))),IF($J73>='02_Benchmarks'!$J73,3,IF($J73>'02_Benchmarks'!$K73,2,IF($J73>='02_Benchmarks'!$L73,0,IF($J73>='02_Benchmarks'!$M73,-2,-3))))))) | P73: =IF(COUNT($N73:$O73)+IF(ISNUMBER($K73),1,0)=0,"",MIN($N73:$O73,$K73)) | Q73: =IF($P73="","",INDEX('04_Tarifmodell'!$B$6:$B$12,$P73+4)) | R73: =IF($P73="","",INDEX('04_Tarifmodell'!$C$6:$C$12,$P73+4)) | S73: =IF(OR($I73="QUALITATIVE",$I73="MANUAL_HYBRID"),IF($K73="","Assurance-Score fehlt","Assurance-bewertet"),IF($I73="BENCHMARK",IF($W73<>"Aktiv",IF($K73="","Benchmark fehlt","Assurance-bewertet"),IF($J73="","Messwert fehlt",IF($P73="","Nicht bewertbar","Berechnet"))),IF(AND($J73="",$K73<>""),"Nur Assurance-Score",IF($J73="","Messwert fehlt",IF($P73="","Nicht bewertbar",IF($P73<=-2,"Kritische Wirkung / Prüfung","Berechnet")))))) -> Messwert fehlt | T73: Konkreten Datenhalter, GIS-Layer, Stichtag und Methodik ergänzen. Vollständige fünfstufige numerische Regel. | U73: ≥0,8:+3; 0,6–0,79:+2; 0,4–0,59:0; 0,2–0,39:‑2; <0,2:‑3 | V73: EN 15978 (Bau LCA), EU EPBD, ISO 52000 | W73: ='02_Benchmarks'!$P73 -> Optional – kein aktiver Benchmark | X73: Platzhalter – konkrete Datenquelle fehlt | Y73: Hoch | Z73: Arbeitskalibrierung – fachlich zu validieren | AA73: Gebäude/Standort; Betrieb plus relevante Lebenszyklusmodule | AB73: Primärdaten oder qualitätsgesicherte Sekundärdaten; Methode, Zeitraum und Systemgrenze dokumentieren | AC73: Limited Assurance; bei materieller Steuerwirkung risikobasiert vertiefen
A74: WOK-SYS-104 | B74: SDG 3 – Gesundheit | C74: 3.4 | D74: Kultur/Bewegung fördern | E74: Kultur/Bewegung fördern – Index | F74: 0–1 | G74: higher_is_better | H74: R15 | I74: NUM_HIGH | N74: =IF($J74="","",IF($J74<0.5,-3,IF($J74<0.6,-2,IF($J74<0.7,0,IF($J74<0.8,2,3))))) | O74: =IF($J74="","",IF(OR('02_Benchmarks'!$P74<>"Aktiv",COUNT('02_Benchmarks'!$J74:$M74)<4),"",IF($G74="lower_is_better",IF($J74<='02_Benchmarks'!$J74,3,IF($J74<'02_Benchmarks'!$K74,2,IF($J74<='02_Benchmarks'!$L74,0,IF($J74<='02_Benchmarks'!$M74,-2,-3)))),IF($J74>='02_Benchmarks'!$J74,3,IF($J74>'02_Benchmarks'!$K74,2,IF($J74>='02_Benchmarks'!$L74,0,IF($J74>='02_Benchmarks'!$M74,-2,-3))))))) | P74: =IF(COUNT($N74:$O74)+IF(ISNUMBER($K74),1,0)=0,"",MIN($N74:$O74,$K74)) | Q74: =IF($P74="","",INDEX('04_Tarifmodell'!$B$6:$B$12,$P74+4)) | R74: =IF($P74="","",INDEX('04_Tarifmodell'!$C$6:$C$12,$P74+4)) | S74: =IF(OR($I74="QUALITATIVE",$I74="MANUAL_HYBRID"),IF($K74="","Assurance-Score fehlt","Assurance-bewertet"),IF($I74="BENCHMARK",IF($W74<>"Aktiv",IF($K74="","Benchmark fehlt","Assurance-bewertet"),IF($J74="","Messwert fehlt",IF($P74="","Nicht bewertbar","Berechnet"))),IF(AND($J74="",$K74<>""),"Nur Assurance-Score",IF($J74="","Messwert fehlt",IF($P74="","Nicht bewertbar",IF($P74<=-2,"Kritische Wirkung / Prüfung","Berechnet")))))) -> Messwert fehlt | T74: Item-Bezeichnung und Messdefinition passen nicht ausreichend zusammen. SROI/SDG 17 ist keine hinreichend konkrete Mess- oder Schwellenquelle. Vollständige fünfstufige numerische Regel. | U74: ≥0,8:+3; 0,7–0,79:+2; 0,6–0,69:0; 0,5–0,59:‑2; <0,5:‑3 | V74: SDG 16/17, WJP, V‑Dem | W74: ='02_Benchmarks'!$P74 -> Optional – kein aktiver Benchmark | X74: Platzhalter – fachliche Operationalisierung offen | Y74: Kritisch | Z74: Arbeitskalibrierung – fachlich zu validieren | AA74: Programm/Portfolio/Systemraum; Empfängergruppe, Region und Zeitraum explizit definieren | AB74: Primärdaten bevorzugt; Sekundärdaten nur transparent und versioniert; Methode und Systemgrenze dokumentieren | AC74: Limited Assurance; risikobasiert höhere Prüftiefe
A75: WOK-SYS-105 | B75: SDG 3 – Gesundheit | C75: 3.4 | D75: Kultur/Bewegung fördern | E75: Kultur/Bewegung fördern – Exposure | F75: % | G75: lower_is_better | H75: R13 | I75: NUM_LOW | N75: =IF($J75="","",IF($J75<=5,3,IF($J75<=10,2,IF($J75<=20,0,IF($J75<=30,-2,-3))))) | O75: =IF($J75="","",IF(OR('02_Benchmarks'!$P75<>"Aktiv",COUNT('02_Benchmarks'!$J75:$M75)<4),"",IF($G75="lower_is_better",IF($J75<='02_Benchmarks'!$J75,3,IF($J75<'02_Benchmarks'!$K75,2,IF($J75<='02_Benchmarks'!$L75,0,IF($J75<='02_Benchmarks'!$M75,-2,-3)))),IF($J75>='02_Benchmarks'!$J75,3,IF($J75>'02_Benchmarks'!$K75,2,IF($J75>='02_Benchmarks'!$L75,0,IF($J75>='02_Benchmarks'!$M75,-2,-3))))))) | P75: =IF(COUNT($N75:$O75)+IF(ISNUMBER($K75),1,0)=0,"",MIN($N75:$O75,$K75)) | Q75: =IF($P75="","",INDEX('04_Tarifmodell'!$B$6:$B$12,$P75+4)) | R75: =IF($P75="","",INDEX('04_Tarifmodell'!$C$6:$C$12,$P75+4)) | S75: =IF(OR($I75="QUALITATIVE",$I75="MANUAL_HYBRID"),IF($K75="","Assurance-Score fehlt","Assurance-bewertet"),IF($I75="BENCHMARK",IF($W75<>"Aktiv",IF($K75="","Benchmark fehlt","Assurance-bewertet"),IF($J75="","Messwert fehlt",IF($P75="","Nicht bewertbar","Berechnet"))),IF(AND($J75="",$K75<>""),"Nur Assurance-Score",IF($J75="","Messwert fehlt",IF($P75="","Nicht bewertbar",IF($P75<=-2,"Kritische Wirkung / Prüfung","Berechnet")))))) -> Messwert fehlt | T75: Item-Bezeichnung und Messdefinition passen nicht ausreichend zusammen. SROI/SDG 17 ist keine hinreichend konkrete Mess- oder Schwellenquelle. Vollständige fünfstufige numerische Regel. | U75: ≤5:+3; 6–10:+2; 11–20:0; 21–30:‑2; >30:‑3 | V75: SROI/SDG17 | W75: ='02_Benchmarks'!$P75 -> Optional – kein aktiver Benchmark | X75: Platzhalter – fachliche Operationalisierung offen | Y75: Kritisch | Z75: Arbeitskalibrierung – fachlich zu validieren | AA75: Programm/Portfolio/Systemraum; Empfängergruppe, Region und Zeitraum explizit definieren | AB75: Primärdaten bevorzugt; Sekundärdaten nur transparent und versioniert; Methode und Systemgrenze dokumentieren | AC75: Limited Assurance; risikobasiert höhere Prüftiefe
A76: WOK-SYS-106 | B76: SDG 3 – Gesundheit | C76: 3.4 | D76: Kultur/Bewegung fördern | E76: Kultur/Bewegung fördern – Kooperationen | F76: #/Jahr | G76: higher_is_better | H76: R20 | I76: NUM_HIGH | N76: =IF($J76="","",IF($J76<0,-3,IF($J76<1,-2,IF($J76<3,0,IF($J76<5,2,3))))) | O76: =IF($J76="","",IF(OR('02_Benchmarks'!$P76<>"Aktiv",COUNT('02_Benchmarks'!$J76:$M76)<4),"",IF($G76="lower_is_better",IF($J76<='02_Benchmarks'!$J76,3,IF($J76<'02_Benchmarks'!$K76,2,IF($J76<='02_Benchmarks'!$L76,0,IF($J76<='02_Benchmarks'!$M76,-2,-3)))),IF($J76>='02_Benchmarks'!$J76,3,IF($J76>'02_Benchmarks'!$K76,2,IF($J76>='02_Benchmarks'!$L76,0,IF($J76>='02_Benchmarks'!$M76,-2,-3))))))) | P76: =IF(COUNT($N76:$O76)+IF(ISNUMBER($K76),1,0)=0,"",MIN($N76:$O76,$K76)) | Q76: =IF($P76="","",INDEX('04_Tarifmodell'!$B$6:$B$12,$P76+4)) | R76: =IF($P76="","",INDEX('04_Tarifmodell'!$C$6:$C$12,$P76+4)) | S76: =IF(OR($I76="QUALITATIVE",$I76="MANUAL_HYBRID"),IF($K76="","Assurance-Score fehlt","Assurance-bewertet"),IF($I76="BENCHMARK",IF($W76<>"Aktiv",IF($K76="","Benchmark fehlt","Assurance-bewertet"),IF($J76="","Messwert fehlt",IF($P76="","Nicht bewertbar","Berechnet"))),IF(AND($J76="",$K76<>""),"Nur Assurance-Score",IF($J76="","Messwert fehlt",IF($P76="","Nicht bewertbar",IF($P76<=-2,"Kritische Wirkung / Prüfung","Berechnet")))))) -> Messwert fehlt | T76: Item-Bezeichnung und Messdefinition passen nicht ausreichend zusammen. SROI/SDG 17 ist keine hinreichend konkrete Mess- oder Schwellenquelle. Für sachlogisch nichtnegative Zählwerte ist 0 die schlechteste reguläre Klasse (−2). | U76: ≥5:+3; 3–4:+2; 1–2:0; 0:‑2 | V76: SDG 16/17, WJP, V‑Dem | W76: ='02_Benchmarks'!$P76 -> Optional – kein aktiver Benchmark | X76: Platzhalter – fachliche Operationalisierung offen | Y76: Kritisch | Z76: Klasse −3 nur für negative/unzulässige Werte ergänzt | AA76: Programm/Portfolio/Systemraum; Empfängergruppe, Region und Zeitraum explizit definieren | AB76: Primärdaten bevorzugt; Sekundärdaten nur transparent und versioniert; Methode und Systemgrenze dokumentieren | AC76: Limited Assurance; risikobasiert höhere Prüftiefe
A77: WOK-S-122 | B77: SDG 3 – Gesundheit | C77: 3.4 | D77: Psycho‑soziale Risiken | E77: Psycho‑soziale Risiken – Living Wage | F77: % Beschäftigte | G77: higher_is_better | H77: R27 | I77: NUM_HIGH | N77: =IF($J77="","",IF($J77<40,-3,IF($J77<60,-2,IF($J77<80,0,IF($J77<95,2,3))))) | O77: =IF($J77="","",IF(OR('02_Benchmarks'!$P77<>"Aktiv",COUNT('02_Benchmarks'!$J77:$M77)<4),"",IF($G77="lower_is_better",IF($J77<='02_Benchmarks'!$J77,3,IF($J77<'02_Benchmarks'!$K77,2,IF($J77<='02_Benchmarks'!$L77,0,IF($J77<='02_Benchmarks'!$M77,-2,-3)))),IF($J77>='02_Benchmarks'!$J77,3,IF($J77>'02_Benchmarks'!$K77,2,IF($J77>='02_Benchmarks'!$L77,0,IF($J77>='02_Benchmarks'!$M77,-2,-3))))))) | P77: =IF(COUNT($N77:$O77)+IF(ISNUMBER($K77),1,0)=0,"",MIN($N77:$O77,$K77)) | Q77: =IF($P77="","",INDEX('04_Tarifmodell'!$B$6:$B$12,$P77+4)) | R77: =IF($P77="","",INDEX('04_Tarifmodell'!$C$6:$C$12,$P77+4)) | S77: =IF(OR($I77="QUALITATIVE",$I77="MANUAL_HYBRID"),IF($K77="","Assurance-Score fehlt","Assurance-bewertet"),IF($I77="BENCHMARK",IF($W77<>"Aktiv",IF($K77="","Benchmark fehlt","Assurance-bewertet"),IF($J77="","Messwert fehlt",IF($P77="","Nicht bewertbar","Berechnet"))),IF(AND($J77="",$K77<>""),"Nur Assurance-Score",IF($J77="","Messwert fehlt",IF($P77="","Nicht bewertbar",IF($P77<=-2,"Kritische Wirkung / Prüfung","Berechnet")))))) -> Messwert fehlt | T77: Vollständige fünfstufige numerische Regel. | U77: ≥95:+3; 80–94:+2; 60–79:0; 40–59:‑2; <40:‑3 | V77: ESRS S1, GRI 401/403/405/406, ILO | W77: ='02_Benchmarks'!$P77 -> Optional – kein aktiver Benchmark | X77: Messgrundlage belegt; Schwellenkalibrierung offen | Y77: Mittel | Z77: Arbeitskalibrierung – fachlich zu validieren | AA77: Eigene Belegschaft/Organisation; FTE, Beschäftigtengruppe und Zeitraum | AB77: Primärdaten bevorzugt; Sekundärdaten nur transparent und versioniert; Methode und Systemgrenze dokumentieren | AC77: Limited Assurance; risikobasiert höhere Prüftiefe
A78: WOK-S-123 | B78: SDG 3 – Gesundheit | C78: 3.4 | D78: Psycho‑soziale Risiken | E78: Psycho‑soziale Risiken – Tarifbindung | F78: % | G78: higher_is_better | H78: R26 | I78: NUM_HIGH | N78: =IF($J78="","",IF($J78<30,-3,IF($J78<50,-2,IF($J78<70,0,IF($J78<90,2,3))))) | O78: =IF($J78="","",IF(OR('02_Benchmarks'!$P78<>"Aktiv",COUNT('02_Benchmarks'!$J78:$M78)<4),"",IF($G78="lower_is_better",IF($J78<='02_Benchmarks'!$J78,3,IF($J78<'02_Benchmarks'!$K78,2,IF($J78<='02_Benchmarks'!$L78,0,IF($J78<='02_Benchmarks'!$M78,-2,-3)))),IF($J78>='02_Benchmarks'!$J78,3,IF($J78>'02_Benchmarks'!$K78,2,IF($J78>='02_Benchmarks'!$L78,0,IF($J78>='02_Benchmarks'!$M78,-2,-3))))))) | P78: =IF(COUNT($N78:$O78)+IF(ISNUMBER($K78),1,0)=0,"",MIN($N78:$O78,$K78)) | Q78: =IF($P78="","",INDEX('04_Tarifmodell'!$B$6:$B$12,$P78+4)) | R78: =IF($P78="","",INDEX('04_Tarifmodell'!$C$6:$C$12,$P78+4)) | S78: =IF(OR($I78="QUALITATIVE",$I78="MANUAL_HYBRID"),IF($K78="","Assurance-Score fehlt","Assurance-bewertet"),IF($I78="BENCHMARK",IF($W78<>"Aktiv",IF($K78="","Benchmark fehlt","Assurance-bewertet"),IF($J78="","Messwert fehlt",IF($P78="","Nicht bewertbar","Berechnet"))),IF(AND($J78="",$K78<>""),"Nur Assurance-Score",IF($J78="","Messwert fehlt",IF($P78="","Nicht bewertbar",IF($P78<=-2,"Kritische Wirkung / Prüfung","Berechnet")))))) -> Messwert fehlt | T78: Vollständige fünfstufige numerische Regel. | U78: ≥90:+3; 70–89:+2; 50–69:0; 30–49:‑2; <30:‑3 | V78: ESRS S1, GRI 401/403/405/406, ILO | W78: ='02_Benchmarks'!$P78 -> Optional – kein aktiver Benchmark | X78: Messgrundlage belegt; Schwellenkalibrierung offen | Y78: Mittel | Z78: Arbeitskalibrierung – fachlich zu validieren | AA78: Eigene Belegschaft/Organisation; FTE, Beschäftigtengruppe und Zeitraum | AB78: Primärdaten bevorzugt; Sekundärdaten nur transparent und versioniert; Methode und Systemgrenze dokumentieren | AC78: Limited Assurance; risikobasiert höhere Prüftiefe
A79: WOK-S-124 | B79: SDG 3 – Gesundheit | C79: 3.4 | D79: Psycho‑soziale Risiken | E79: Psycho‑soziale Risiken – LTIFR | F79: Unfälle/Mio Std. | G79: lower_is_better | H79: R02 | I79: NUM_LOW | N79: =IF($J79="","",IF($J79<=0,3,IF($J79<=1,2,IF($J79<=3,0,IF($J79<=5,-2,-3))))) | O79: =IF($J79="","",IF(OR('02_Benchmarks'!$P79<>"Aktiv",COUNT('02_Benchmarks'!$J79:$M79)<4),"",IF($G79="lower_is_better",IF($J79<='02_Benchmarks'!$J79,3,IF($J79<'02_Benchmarks'!$K79,2,IF($J79<='02_Benchmarks'!$L79,0,IF($J79<='02_Benchmarks'!$M79,-2,-3)))),IF($J79>='02_Benchmarks'!$J79,3,IF($J79>'02_Benchmarks'!$K79,2,IF($J79>='02_Benchmarks'!$L79,0,IF($J79>='02_Benchmarks'!$M79,-2,-3))))))) | P79: =IF(COUNT($N79:$O79)+IF(ISNUMBER($K79),1,0)=0,"",MIN($N79:$O79,$K79)) | Q79: =IF($P79="","",INDEX('04_Tarifmodell'!$B$6:$B$12,$P79+4)) | R79: =IF($P79="","",INDEX('04_Tarifmodell'!$C$6:$C$12,$P79+4)) | S79: =IF(OR($I79="QUALITATIVE",$I79="MANUAL_HYBRID"),IF($K79="","Assurance-Score fehlt","Assurance-bewertet"),IF($I79="BENCHMARK",IF($W79<>"Aktiv",IF($K79="","Benchmark fehlt","Assurance-bewertet"),IF($J79="","Messwert fehlt",IF($P79="","Nicht bewertbar","Berechnet"))),IF(AND($J79="",$K79<>""),"Nur Assurance-Score",IF($J79="","Messwert fehlt",IF($P79="","Nicht bewertbar",IF($P79<=-2,"Kritische Wirkung / Prüfung","Berechnet")))))) -> Messwert fehlt | T79: Vollständige fünfstufige numerische Regel. | U79: 0:+3; ≤1:+2; ≤3:0; ≤5:‑2; >5:‑3 | V79: ESRS S1, GRI 401/403/405/406, ILO | W79: ='02_Benchmarks'!$P79 -> Optional – kein aktiver Benchmark | X79: Messgrundlage belegt; Schwellenkalibrierung offen | Y79: Mittel | Z79: Arbeitskalibrierung – fachlich zu validieren | AA79: Eigene Belegschaft/Organisation; FTE, Beschäftigtengruppe und Zeitraum | AB79: Primärdaten bevorzugt; Sekundärdaten nur transparent und versioniert; Methode und Systemgrenze dokumentieren | AC79: Limited Assurance; risikobasiert höhere Prüftiefe
A80: WOK-E-119 | B80: SDG 3 – Gesundheit | C80: 3.9 | D80: Chemikaliensicherheit/REACH | E80: Chemikaliensicherheit/REACH – Abfallintensität | F80: kg/t | G80: lower_is_better | H80: R06 | I80: BENCHMARK | N80: ="" | O80: =IF($J80="","",IF(OR('02_Benchmarks'!$P80<>"Aktiv",COUNT('02_Benchmarks'!$J80:$M80)<4),"",IF($G80="lower_is_better",IF($J80<='02_Benchmarks'!$J80,3,IF($J80<'02_Benchmarks'!$K80,2,IF($J80<='02_Benchmarks'!$L80,0,IF($J80<='02_Benchmarks'!$M80,-2,-3)))),IF($J80>='02_Benchmarks'!$J80,3,IF($J80>'02_Benchmarks'!$K80,2,IF($J80>='02_Benchmarks'!$L80,0,IF($J80>='02_Benchmarks'!$M80,-2,-3))))))) | P80: =IF(COUNT($N80:$O80)+IF(ISNUMBER($K80),1,0)=0,"",MIN($N80:$O80,$K80)) | Q80: =IF($P80="","",INDEX('04_Tarifmodell'!$B$6:$B$12,$P80+4)) | R80: =IF($P80="","",INDEX('04_Tarifmodell'!$C$6:$C$12,$P80+4)) | S80: =IF(OR($I80="QUALITATIVE",$I80="MANUAL_HYBRID"),IF($K80="","Assurance-Score fehlt","Assurance-bewertet"),IF($I80="BENCHMARK",IF($W80<>"Aktiv",IF($K80="","Benchmark fehlt","Assurance-bewertet"),IF($J80="","Messwert fehlt",IF($P80="","Nicht bewertbar","Berechnet"))),IF(AND($J80="",$K80<>""),"Nur Assurance-Score",IF($J80="","Messwert fehlt",IF($P80="","Nicht bewertbar",IF($P80<=-2,"Kritische Wirkung / Prüfung","Berechnet")))))) -> Benchmark fehlt | T80: Top-10-Prozent, Mittelwert, 150 % und 250 % müssen aus einer dokumentierten Grundgesamtheit stammen. | U80: Top‑10%:+3; Mittel:0; >150%:‑2; >250%:‑3 | V80: ESRS E5, GRI 306, WEEE/VerpackG | W80: ='02_Benchmarks'!$P80 -> Offen – validierter Benchmark fehlt | X80: Teilbelegt – Benchmarkquelle fehlt | Y80: Hoch | Z80: Validierter Benchmark fehlt | AA80: Standort/Prozess/Aktivität; Bezugsgröße und relevante Umweltmedien | AB80: Primärdaten plus repräsentativer, versionierter Benchmarkdatensatz; Stichprobe und Population offenlegen | AC80: Messwert-Assurance und unabhängige Benchmark-Governance
A81: WOK-E-120 | B81: SDG 3 – Gesundheit | C81: 3.9 | D81: Chemikaliensicherheit/REACH | E81: Chemikaliensicherheit/REACH – Recyclingquote | F81: % | G81: higher_is_better | H81: R25 | I81: NUM_HIGH | N81: =IF($J81="","",IF($J81<30,-3,IF($J81<50,-2,IF($J81<70,0,IF($J81<90,2,3))))) | O81: =IF($J81="","",IF(OR('02_Benchmarks'!$P81<>"Aktiv",COUNT('02_Benchmarks'!$J81:$M81)<4),"",IF($G81="lower_is_better",IF($J81<='02_Benchmarks'!$J81,3,IF($J81<'02_Benchmarks'!$K81,2,IF($J81<='02_Benchmarks'!$L81,0,IF($J81<='02_Benchmarks'!$M81,-2,-3)))),IF($J81>='02_Benchmarks'!$J81,3,IF($J81>'02_Benchmarks'!$K81,2,IF($J81>='02_Benchmarks'!$L81,0,IF($J81>='02_Benchmarks'!$M81,-2,-3))))))) | P81: =IF(COUNT($N81:$O81)+IF(ISNUMBER($K81),1,0)=0,"",MIN($N81:$O81,$K81)) | Q81: =IF($P81="","",INDEX('04_Tarifmodell'!$B$6:$B$12,$P81+4)) | R81: =IF($P81="","",INDEX('04_Tarifmodell'!$C$6:$C$12,$P81+4)) | S81: =IF(OR($I81="QUALITATIVE",$I81="MANUAL_HYBRID"),IF($K81="","Assurance-Score fehlt","Assurance-bewertet"),IF($I81="BENCHMARK",IF($W81<>"Aktiv",IF($K81="","Benchmark fehlt","Assurance-bewertet"),IF($J81="","Messwert fehlt",IF($P81="","Nicht bewertbar","Berechnet"))),IF(AND($J81="",$K81<>""),"Nur Assurance-Score",IF($J81="","Messwert fehlt",IF($P81="","Nicht bewertbar",IF($P81<=-2,"Kritische Wirkung / Prüfung","Berechnet")))))) -> Messwert fehlt | T81: Vollständige fünfstufige Prozentregel. | U81: ≥90%:+3; 70–89%:+2; 50–69%:0; 30–49%:‑2; <30%:‑3 | V81: ESRS E5, GRI 306, WEEE/VerpackG | W81: ='02_Benchmarks'!$P81 -> Optional – kein aktiver Benchmark | X81: Messgrundlage belegt; Schwellenkalibrierung offen | Y81: Mittel | Z81: Arbeitskalibrierung – fachlich zu validieren | AA81: Standort/Prozess/Aktivität; Bezugsgröße und relevante Umweltmedien | AB81: Primärdaten bevorzugt; Sekundärdaten nur transparent und versioniert; Methode und Systemgrenze dokumentieren | AC81: Limited Assurance; risikobasiert höhere Prüftiefe
A82: WOK-E-121 | B82: SDG 3 – Gesundheit | C82: 3.9 | D82: Chemikaliensicherheit/REACH | E82: Chemikaliensicherheit/REACH – Gefährlicher Abfall | F82: kg/t | G82: lower_is_better | H82: R06 | I82: BENCHMARK | N82: ="" | O82: =IF($J82="","",IF(OR('02_Benchmarks'!$P82<>"Aktiv",COUNT('02_Benchmarks'!$J82:$M82)<4),"",IF($G82="lower_is_better",IF($J82<='02_Benchmarks'!$J82,3,IF($J82<'02_Benchmarks'!$K82,2,IF($J82<='02_Benchmarks'!$L82,0,IF($J82<='02_Benchmarks'!$M82,-2,-3)))),IF($J82>='02_Benchmarks'!$J82,3,IF($J82>'02_Benchmarks'!$K82,2,IF($J82>='02_Benchmarks'!$L82,0,IF($J82>='02_Benchmarks'!$M82,-2,-3))))))) | P82: =IF(COUNT($N82:$O82)+IF(ISNUMBER($K82),1,0)=0,"",MIN($N82:$O82,$K82)) | Q82: =IF($P82="","",INDEX('04_Tarifmodell'!$B$6:$B$12,$P82+4)) | R82: =IF($P82="","",INDEX('04_Tarifmodell'!$C$6:$C$12,$P82+4)) | S82: =IF(OR($I82="QUALITATIVE",$I82="MANUAL_HYBRID"),IF($K82="","Assurance-Score fehlt","Assurance-bewertet"),IF($I82="BENCHMARK",IF($W82<>"Aktiv",IF($K82="","Benchmark fehlt","Assurance-bewertet"),IF($J82="","Messwert fehlt",IF($P82="","Nicht bewertbar","Berechnet"))),IF(AND($J82="",$K82<>""),"Nur Assurance-Score",IF($J82="","Messwert fehlt",IF($P82="","Nicht bewertbar",IF($P82<=-2,"Kritische Wirkung / Prüfung","Berechnet")))))) -> Benchmark fehlt | T82: Top-10-Prozent, Mittelwert, 150 % und 250 % müssen aus einer dokumentierten Grundgesamtheit stammen. | U82: Top‑10%:+3; Mittel:0; >150%:‑2; >250%:‑3 | V82: ESRS E5, GRI 306, WEEE/VerpackG | W82: ='02_Benchmarks'!$P82 -> Offen – validierter Benchmark fehlt | X82: Teilbelegt – Benchmarkquelle fehlt | Y82: Hoch | Z82: Validierter Benchmark fehlt | AA82: Standort/Prozess/Aktivität; Bezugsgröße und relevante Umweltmedien | AB82: Primärdaten plus repräsentativer, versionierter Benchmarkdatensatz; Stichprobe und Population offenlegen | AC82: Messwert-Assurance und unabhängige Benchmark-Governance
A83: WOK-G-113 | B83: SDG 3 – Gesundheit | C83: 3.8 | D83: Patientensicherheit Kliniken | E83: Patientensicherheit Kliniken – Antikorruption | F83: Fälle/1.000 FTE | G83: lower_is_better | H83: R01 | I83: NUM_LOW | N83: =IF($J83="","",IF($J83<=0,3,IF($J83<=0.2,2,IF($J83<=0.5,0,IF($J83<=1,-2,-3))))) | O83: =IF($J83="","",IF(OR('02_Benchmarks'!$P83<>"Aktiv",COUNT('02_Benchmarks'!$J83:$M83)<4),"",IF($G83="lower_is_better",IF($J83<='02_Benchmarks'!$J83,3,IF($J83<'02_Benchmarks'!$K83,2,IF($J83<='02_Benchmarks'!$L83,0,IF($J83<='02_Benchmarks'!$M83,-2,-3)))),IF($J83>='02_Benchmarks'!$J83,3,IF($J83>'02_Benchmarks'!$K83,2,IF($J83>='02_Benchmarks'!$L83,0,IF($J83>='02_Benchmarks'!$M83,-2,-3))))))) | P83: =IF(COUNT($N83:$O83)+IF(ISNUMBER($K83),1,0)=0,"",MIN($N83:$O83,$K83)) | Q83: =IF($P83="","",INDEX('04_Tarifmodell'!$B$6:$B$12,$P83+4)) | R83: =IF($P83="","",INDEX('04_Tarifmodell'!$C$6:$C$12,$P83+4)) | S83: =IF(OR($I83="QUALITATIVE",$I83="MANUAL_HYBRID"),IF($K83="","Assurance-Score fehlt","Assurance-bewertet"),IF($I83="BENCHMARK",IF($W83<>"Aktiv",IF($K83="","Benchmark fehlt","Assurance-bewertet"),IF($J83="","Messwert fehlt",IF($P83="","Nicht bewertbar","Berechnet"))),IF(AND($J83="",$K83<>""),"Nur Assurance-Score",IF($J83="","Messwert fehlt",IF($P83="","Nicht bewertbar",IF($P83<=-2,"Kritische Wirkung / Prüfung","Berechnet")))))) -> Messwert fehlt | T83: Item-Bezeichnung und Messdefinition passen nicht ausreichend zusammen. Vollständige fünfstufige numerische Regel. | U83: 0:+3; ≤0,2:+2; ≤0,5:0; ≤1:‑2; >1:‑3 | V83: ESRS G1, GRI 205/207, OECD Anti‑Bribery | W83: ='02_Benchmarks'!$P83 -> Optional – kein aktiver Benchmark | X83: Messgrundlage belegt; Schwellenkalibrierung offen | Y83: Kritisch | Z83: Arbeitskalibrierung – fachlich zu validieren | AA83: Organisation/Governance; konsolidierter Kreis und relevante Rechtseinheiten | AB83: Primärdaten bevorzugt; Sekundärdaten nur transparent und versioniert; Methode und Systemgrenze dokumentieren | AC83: Limited Assurance; risikobasiert höhere Prüftiefe
A84: WOK-G-114 | B84: SDG 3 – Gesundheit | C84: 3.8 | D84: Patientensicherheit Kliniken | E84: Patientensicherheit Kliniken – Whistleblowing | F84: 0–1 | G84: higher_is_better | H84: R16 | I84: NUM_HIGH | N84: =IF($J84="","",IF($J84<0.4,-3,IF($J84<0.6,-2,IF($J84<0.75,0,IF($J84<0.9,2,3))))) | O84: =IF($J84="","",IF(OR('02_Benchmarks'!$P84<>"Aktiv",COUNT('02_Benchmarks'!$J84:$M84)<4),"",IF($G84="lower_is_better",IF($J84<='02_Benchmarks'!$J84,3,IF($J84<'02_Benchmarks'!$K84,2,IF($J84<='02_Benchmarks'!$L84,0,IF($J84<='02_Benchmarks'!$M84,-2,-3)))),IF($J84>='02_Benchmarks'!$J84,3,IF($J84>'02_Benchmarks'!$K84,2,IF($J84>='02_Benchmarks'!$L84,0,IF($J84>='02_Benchmarks'!$M84,-2,-3))))))) | P84: =IF(COUNT($N84:$O84)+IF(ISNUMBER($K84),1,0)=0,"",MIN($N84:$O84,$K84)) | Q84: =IF($P84="","",INDEX('04_Tarifmodell'!$B$6:$B$12,$P84+4)) | R84: =IF($P84="","",INDEX('04_Tarifmodell'!$C$6:$C$12,$P84+4)) | S84: =IF(OR($I84="QUALITATIVE",$I84="MANUAL_HYBRID"),IF($K84="","Assurance-Score fehlt","Assurance-bewertet"),IF($I84="BENCHMARK",IF($W84<>"Aktiv",IF($K84="","Benchmark fehlt","Assurance-bewertet"),IF($J84="","Messwert fehlt",IF($P84="","Nicht bewertbar","Berechnet"))),IF(AND($J84="",$K84<>""),"Nur Assurance-Score",IF($J84="","Messwert fehlt",IF($P84="","Nicht bewertbar",IF($P84<=-2,"Kritische Wirkung / Prüfung","Berechnet")))))) -> Messwert fehlt | T84: Item-Bezeichnung und Messdefinition passen nicht ausreichend zusammen. Vollständige fünfstufige numerische Regel. | U84: ≥0,9:+3; 0,75–0,89:+2; 0,6–0,74:0; 0,4–0,59:‑2; <0,4:‑3 | V84: ESRS G1, GRI 205/207, OECD Anti‑Bribery | W84: ='02_Benchmarks'!$P84 -> Optional – kein aktiver Benchmark | X84: Messgrundlage belegt; Schwellenkalibrierung offen | Y84: Kritisch | Z84: Arbeitskalibrierung – fachlich zu validieren | AA84: Organisation/Governance; konsolidierter Kreis und relevante Rechtseinheiten | AB84: Primärdaten bevorzugt; Sekundärdaten nur transparent und versioniert; Methode und Systemgrenze dokumentieren | AC84: Limited Assurance; risikobasiert höhere Prüftiefe
A85: WOK-G-115 | B85: SDG 3 – Gesundheit | C85: 3.8 | D85: Patientensicherheit Kliniken | E85: Patientensicherheit Kliniken – Steuertransparenz | F85: 0–1 | G85: higher_is_better | H85: R08 | I85: QUALITATIVE | N85: ="" | O85: =IF($J85="","",IF(OR('02_Benchmarks'!$P85<>"Aktiv",COUNT('02_Benchmarks'!$J85:$M85)<4),"",IF($G85="lower_is_better",IF($J85<='02_Benchmarks'!$J85,3,IF($J85<'02_Benchmarks'!$K85,2,IF($J85<='02_Benchmarks'!$L85,0,IF($J85<='02_Benchmarks'!$M85,-2,-3)))),IF($J85>='02_Benchmarks'!$J85,3,IF($J85>'02_Benchmarks'!$K85,2,IF($J85>='02_Benchmarks'!$L85,0,IF($J85>='02_Benchmarks'!$M85,-2,-3))))))) | P85: =IF(COUNT($N85:$O85)+IF(ISNUMBER($K85),1,0)=0,"",MIN($N85:$O85,$K85)) | Q85: =IF($P85="","",INDEX('04_Tarifmodell'!$B$6:$B$12,$P85+4)) | R85: =IF($P85="","",INDEX('04_Tarifmodell'!$C$6:$C$12,$P85+4)) | S85: =IF(OR($I85="QUALITATIVE",$I85="MANUAL_HYBRID"),IF($K85="","Assurance-Score fehlt","Assurance-bewertet"),IF($I85="BENCHMARK",IF($W85<>"Aktiv",IF($K85="","Benchmark fehlt","Assurance-bewertet"),IF($J85="","Messwert fehlt",IF($P85="","Nicht bewertbar","Berechnet"))),IF(AND($J85="",$K85<>""),"Nur Assurance-Score",IF($J85="","Messwert fehlt",IF($P85="","Nicht bewertbar",IF($P85<=-2,"Kritische Wirkung / Prüfung","Berechnet")))))) -> Assurance-Score fehlt | T85: Item-Bezeichnung und Messdefinition passen nicht ausreichend zusammen. Die Kategorie −3 fehlt; Vollständigkeit und Wirksamkeit sind feldspezifisch zu definieren. | U85: vollständig:+3; teilweise:+2; minimal:0; schlecht:‑2 | V85: ESRS G1, GRI 205/207, OECD Anti‑Bribery | W85: ='02_Benchmarks'!$P85 -> Optional – kein aktiver Benchmark | X85: Messgrundlage belegt; Schwellenkalibrierung offen | Y85: Kritisch | Z85: Assurance und Kriterienkatalog erforderlich | AA85: Organisation/Governance; konsolidierter Kreis und relevante Rechtseinheiten | AB85: Dokumentierter Kriterienkatalog; nachvollziehbare Evidenz; DQR A/B bevorzugt | AC85: Unabhängige Fachprüfung/Limited Assurance; bei roten Linien Reasonable Assurance
